Workbook
Name Coal_trade: #REF!
Name Fuels: #REF!
Name gasdemand: #REF!
Name INDIC_T6_APS: #REF!
Name INDIC_T6_NZE: #REF!
Name INDIC_T6_STEPS: #REF!
Name IQ_CH: 110000
Name IQ_CQ: 5000
Name IQ_CY: 10000
Name IQ_DAILY: 500000
Name IQ_FH: 100000
Name IQ_FQ: 500
Name IQ_FWD_CY: 10001
Name IQ_FWD_CY1: 10002
Name IQ_FWD_CY2: 10003
Name IQ_FWD_FY: 1001

Sheet NOUSELCOE_Expand_toAPS
B1: CAPEX-Large | C1: ANM-Large | E1: CAPEX-rooftop | F1: ANM-rooftop | K1: This spreadsheet contains the derived ANM rather than
B3: 2023 | C3: 2023 | E3: 2023 | F3: 2023 | K3: Update 2023
A5: European Union | B5: =L5 -> 750 | C5: =M5 -> 12 | E5: =O5 -> 990 | F5: =P5 -> 14 | K5: European Union | L5: 750 | M5: 12 | O5: 990 | P5: 14
A6: United States | B6: =L6 -> 1110 | C6: =M6 -> 16 | E6: =O6 -> 3460 | F6: =P6 -> 52 | K6: United States | L6: 1110 | M6: 16 | O6: 3460 | P6: 52
A7: Japan | B7: =L7 -> 1880 | C7: =M7 -> 28 | E7: =O7 -> 1850 | F7: =P7 -> 28 | K7: Japan | L7: 1880 | M7: 28 | O7: 1850 | P7: 28
A8: Russia | B8: =L8 -> 1250 | C8: =M8 -> 18 | E8: =O8 -> 1610 | F8: =P8 -> 24 | K8: Russia | L8: 1250 | M8: 18 | O8: 1610 | P8: 24
A9: China | B9: =L9 -> 670 | C9: =M9 -> 12 | E9: =O9 -> 750 | F9: =P9 -> 14 | K9: China | L9: 670 | M9: 12 | O9: 750 | P9: 14
A10: India | B10: =L10 -> 710 | C10: =M10 -> 10 | E10: =O10 -> 780 | F10: =P10 -> 12 | K10: India | L10: 710 | M10: 10 | O10: 780 | P10: 12
A11: Middle East | B11: =L11 -> 610 | C11: =M11 -> 10 | E11: =O11 -> 1010 | F11: =P11 -> 16 | K11: Middle East | L11: 610 | M11: 10 | O11: 1010 | P11: 16
A12: Africa | B12: =L12 -> 1330 | C12: =M12 -> 20 | E12: =O12 -> 1830 | F12: =P12 -> 28 | K12: Africa | L12: 1330 | M12: 20 | O12: 1830 | P12: 28
A13: Brazil | B13: =L13 -> 730 | C13: =M13 -> 10 | E13: =O13 -> 560 | F13: =P13 -> 8 | K13: Brazil | L13: 730 | M13: 10 | O13: 560 | P13: 8
B15: PV capacity | C15: PV capacity | E15: PV capacity | F15: PV capacity
B16: 2023 | C16: 2023 | E16: 2023 | F16: 2023
A17: European Union | B17: ='Summari-ForCount (2030)'!AO60 -> 266.93 | C17: =B17 -> 266.93 | E17: =B17 -> 266.93 | F17: =C17 -> 266.93
A18: United States | B18: ='Summari-ForCount (2030)'!AO62 -> 169.75 | C18: =B18 -> 169.75 | E18: =B18 -> 169.75 | F18: =C18 -> 169.75
A19: Japan | B19: ='Summari-ForCount (2030)'!AO66 -> 108.16 | C19: =B19 -> 108.16 | E19: =B19 -> 108.16 | F19: =C19 -> 108.16
A20: Russia | B20: ='Summari-ForCount (2030)'!AO63 -> 2.13 | C20: =B20 -> 2.13 | E20: =B20 -> 2.13 | F20: =C20 -> 2.13
A21: China | B21: ='Summari-ForCount (2030)'!AO64 -> 688.24 | C21: =B21 -> 688.24 | E21: =B21 -> 688.24 | F21: =C21 -> 688.24
A22: India | B22: ='Summari-ForCount (2030)'!AO65 -> 94.77 | C22: =B22 -> 94.77 | E22: =B22 -> 94.77 | F22: =C22 -> 94.77
A23: Middle East | B23: ='Summarize-ForReg(Current&2050)'!AL65 -> 13.85 | C23: =B23 -> 13.85 | E23: =B23 -> 13.85 | F23: =C23 -> 13.85
A24: Africa | B24: ='Summarize-ForReg(Current&2050)'!AL66 -> 17.04 | C24: =B24 -> 17.04 | E24: =B24 -> 17.04 | F24: =C24 -> 17.04
A25: Brazil | B25: ='Summari-ForCount (2030)'!AO61 -> 41.48 | C25: =B25 -> 41.48 | E25: =B25 -> 41.48 | F25: =C25 -> 41.48
K26: CAPEX-Large | L26: ANM-Large | N26: CAPEX-rooftop | O26: ANM-rooftop | S26: Which input to LCOE calculation code
B27: PV capacity | C27: PV capacity | E27: PV capacity | F27: PV capacity | S27: CAPEX-Large | V27: OM-Large | Y27: CAPEX-Rooftop | AB27: OM-Rooftop
B28: APS-2030 | C28: 2030 | E28: 2030 | F28: 2030 | K28: APS-2030 | L28: 2030 | N28: 2030 | O28: 2030 | S28: =K28 -> APS-2030 | T28: =K40 -> APS-2050 | V28: =N28 -> 2030 | W28: =N40 -> 2050
A29: European Union | B29: ='Summari-ForCount (2030)'!AR60 -> 746.62 | C29: =B29 -> 746.62 | E29: =B29 -> 746.62 | F29: =C29 -> 746.62 | J29: European Union | K29: =B5*(0.8)^(LOG((B29/B17),2)) -> 538.58625 | L29: =C5*(0.8)^(LOG((C29/C17),2)) -> 8.6173801 | N29: =E5*(0.8)^(LOG((E29/E17),2)) -> 710.93385 | O29: =F5*(0.8)^(LOG((F29/F17),2)) -> 10.05361 | R29: European Union | S29: =K29 -> 538.58625 | T29: =K41 -> 476.6209 | V29: =L29 -> 8.6173801 | W29: =L41 -> 7.6259345 | Y29: =N29 -> 710.93385 | Z29: =N41 -> 629.13959 | AB29: =O29 -> 10.05361 | AC29: =O41 -> 8.8969235
A30: United States | B30: ='Summari-ForCount (2030)'!AR62 -> 719.52 | C30: =B30 -> 719.52 | E30: =B30 -> 719.52 | F30: =C30 -> 719.52 | J30: United States | K30: =B6*(0.8)^(LOG((B30/B18),2)) -> 697.26686 | L30: =C6*(0.8)^(LOG((C30/C18),2)) -> 10.050694 | N30: =E6*(0.8)^(LOG((E30/E18),2)) -> 2173.4625 | O30: =F6*(0.8)^(LOG((F30/F18),2)) -> 32.664754 | R30: United States | S30: =K30 -> 697.26686 | T30: =K42 -> 497.13653 | V30: =L30 -> 10.050694 | W30: =L42 -> 7.1659319 | Y30: =N30 -> 2173.4625 | Z30: =N42 -> 1549.6328 | AB30: =O30 -> 32.664754 | AC30: =O42 -> 23.289279
A31: Japan | B31: ='Summari-ForCount (2030)'!AR66 -> 172.08 | C31: =B31 -> 172.08 | E31: =B31 -> 172.08 | F31: =C31 -> 172.08 | J31: Japan | K31: =B7*(0.8)^(LOG((B31/B19),2)) -> 1618.9619 | L31: =C7*(0.8)^(LOG((C31/C19),2)) -> 24.112199 | N31: =E7*(0.8)^(LOG((E31/E19),2)) -> 1593.1274 | O31: =F7*(0.8)^(LOG((F31/F19),2)) -> 24.112199 | R31: Japan | S31: =K31 -> 1618.9619 | T31: =K43 -> 1490.6173 | V31: =L31 -> 24.112199 | W31: =L43 -> 22.200683 | Y31: =N31 -> 1593.1274 | Z31: =N43 -> 1466.8308 | AB31: =O31 -> 24.112199 | AC31: =O43 -> 22.200683
A32: Russia | B32: ='Summari-ForCount (2030)'!AR63 -> 5.49 | C32: =B32 -> 5.49 | E32: =B32 -> 5.49 | F32: =C32 -> 5.49 | J32: Russia | K32: =B8*(0.8)^(LOG((B32/B20),2)) -> 921.58525 | L32: =C8*(0.8)^(LOG((C32/C20),2)) -> 13.270828 | N32: =E8*(0.8)^(LOG((E32/E20),2)) -> 1187.0018 | O32: =F8*(0.8)^(LOG((F32/F20),2)) -> 17.694437 | R32: Russia | S32: =K32 -> 921.58525 | T32: =K44 -> 609.11356 | V32: =L32 -> 13.270828 | W32: =L44 -> 8.7712352 | Y32: =N32 -> 1187.0018 | Z32: =N44 -> 784.53826 | AB32: =O32 -> 17.694437 | AC32: =O44 -> 11.69498
A33: China | B33: ='Summari-ForCount (2030)'!AR64 -> 3315.59 | C33: =B33 -> 3315.59 | E33: =B33 -> 3315.59 | F33: =C33 -> 3315.59 | J33: China | K33: =B9*(0.8)^(LOG((B33/B21),2)) -> 403.88299 | L33: =C9*(0.8)^(LOG((C33/C21),2)) -> 7.2337253 | N33: =E9*(0.8)^(LOG((E33/E21),2)) -> 452.10783 | O33: =F9*(0.8)^(LOG((F33/F21),2)) -> 8.4393462 | R33: China | S33: =K33 -> 403.88299 | T33: =K45 -> 286.84943 | V33: =L33 -> 7.2337253 | W33: =L45 -> 5.1376017 | Y33: =N33 -> 452.10783 | Z33: =N45 -> 321.10011 | AB33: =O33 -> 8.4393462 | AC33: =O45 -> 5.9938687
A34: India | B34: ='Summari-ForCount (2030)'!AR65 -> 385.32 | C34: =B34 -> 385.32 | E34: =B34 -> 385.32 | F34: =C34 -> 385.32 | J34: India | K34: =B10*(0.8)^(LOG((B34/B22),2)) -> 452.0179 | L34: =C10*(0.8)^(LOG((C34/C22),2)) -> 6.3664493 | N34: =E10*(0.8)^(LOG((E34/E22),2)) -> 496.58305 | O34: =F10*(0.8)^(LOG((F34/F22),2)) -> 7.6397392 | R34: India | S34: =K34 -> 452.0179 | T34: =K46 -> 271.25563 | V34: =L34 -> 6.3664493 | W34: =L46 -> 3.8205018 | Y34: =N34 -> 496.58305 | Z34: =N46 -> 297.99914 | AB34: =O34 -> 7.6397392 | AC34: =O46 -> 4.5846022
A35: Middle East | B35: ='Summarize-ForReg(2030)'!AP65 -> 132.56 | C35: =B35 -> 132.56 | E35: =B35 -> 132.56 | F35: =C35 -> 132.56 | J35: Middle East | K35: =B11*(0.8)^(LOG((B35/B23),2)) -> 294.80197 | L35: =C11*(0.8)^(LOG((C35/C23),2)) -> 4.8328191 | N35: =E11*(0.8)^(LOG((E35/E23),2)) -> 488.11473 | O35: =F11*(0.8)^(LOG((F35/F23),2)) -> 7.7325106 | R35: Middle East | S35: =K35 -> 294.80197 | T35: =K47 -> 152.44005 | V35: =L35 -> 4.8328191 | W35: =L47 -> 2.4990171 | Y35: =N35 -> 488.11473 | Z35: =N47 -> 252.40073 | AB35: =O35 -> 7.7325106 | AC35: =O47 -> 3.9984274
A36: Africa | B36: ='Summarize-ForReg(2030)'!AP66 -> 175.19 | C36: =B36 -> 175.19 | E36: =B36 -> 175.19 | F36: =C36 -> 175.19 | J36: Africa | K36: =B12*(0.8)^(LOG((B36/B24),2)) -> 628.12723 | L36: =C12*(0.8)^(LOG((C36/C24),2)) -> 9.4455223 | N36: =E12*(0.8)^(LOG((E36/E24),2)) -> 864.26529 | O36: =F12*(0.8)^(LOG((F36/F24),2)) -> 13.223731 | R36: Africa | S36: =K36 -> 628.12723 | T36: =K48 -> 365.0569 | V36: =L36 -> 9.4455223 | W36: =L48 -> 5.4895774 | Y36: =N36 -> 864.26529 | Z36: =N48 -> 502.29634 | AB36: =O36 -> 13.223731 | AC36: =O48 -> 7.6854084
A37: Brazil | B37: ='Summari-ForCount (2030)'!AR61 -> 135.34 | C37: =B37 -> 135.34 | E37: =B37 -> 135.34 | F37: =C37 -> 135.34 | J37: Brazil | K37: =B13*(0.8)^(LOG((B37/B25),2)) -> 498.86684 | L37: =C13*(0.8)^(LOG((C37/C25),2)) -> 6.8337924 | N37: =E13*(0.8)^(LOG((E37/E25),2)) -> 382.69237 | O37: =F13*(0.8)^(LOG((F37/F25),2)) -> 5.4670339 | R37: Brazil | S37: =K37 -> 498.86684 | T37: =K49 -> 411.63787 | V37: =L37 -> 6.8337924 | W37: =L49 -> 5.638875 | Y37: =N37 -> 382.69237 | Z37: =N49 -> 315.777 | AB37: =O37 -> 5.4670339 | AC37: =O49 -> 4.5111
B39: PV capacity | C39: PV capacity | E39: PV capacity | F39: PV capacity
B40: APS-2050 | C40: 2050 | E40: 2050 | F40: 2050 | K40: APS-2050 | L40: 2050 | N40: 2050 | O40: 2050
A41: European Union | B41: ='Summari-ForCount (Current&2050)'!AB95 -> 1091.41 | C41: =B41 -> 1091.41 | E41: =B41 -> 1091.41 | F41: =C41 -> 1091.41 | K41: =B5*(0.8)^(LOG((B41/B17),2)) -> 476.6209 | L41: =C5*(0.8)^(LOG((C41/C17),2)) -> 7.6259345 | N41: =E5*(0.8)^(LOG((E41/E17),2)) -> 629.13959 | O41: =F5*(0.8)^(LOG((F41/F17),2)) -> 8.8969235
A42: United States | B42: ='Summari-ForCount (Current&2050)'!AB97 -> 2057.92 | C42: =B42 -> 2057.92 | E42: =B42 -> 2057.92 | F42: =C42 -> 2057.92 | K42: =B6*(0.8)^(LOG((B42/B18),2)) -> 497.13653 | L42: =C6*(0.8)^(LOG((C42/C18),2)) -> 7.1659319 | N42: =E6*(0.8)^(LOG((E42/E18),2)) -> 1549.6328 | O42: =F6*(0.8)^(LOG((F42/F18),2)) -> 23.289279
A43: Japan | B43: ='Summari-ForCount (Current&2050)'!AB101 -> 222.41 | C43: =B43 -> 222.41 | E43: =B43 -> 222.41 | F43: =C43 -> 222.41 | K43: =B7*(0.8)^(LOG((B43/B19),2)) -> 1490.6173 | L43: =C7*(0.8)^(LOG((C43/C19),2)) -> 22.200683 | N43: =E7*(0.8)^(LOG((E43/E19),2)) -> 1466.8308 | O43: =F7*(0.8)^(LOG((F43/F19),2)) -> 22.200683
A44: Russia | B44: ='Summari-ForCount (Current&2050)'!AB98 -> 19.87 | C44: =B44 -> 19.87 | E44: =B44 -> 19.87 | F44: =C44 -> 19.87 | K44: =B8*(0.8)^(LOG((B44/B20),2)) -> 609.11356 | L44: =C8*(0.8)^(LOG((C44/C20),2)) -> 8.7712352 | N44: =E8*(0.8)^(LOG((E44/E20),2)) -> 784.53826 | O44: =F8*(0.8)^(LOG((F44/F20),2)) -> 11.69498
A45: China | B45: ='Summari-ForCount (Current&2050)'!AB99 -> 9597.53 | C45: =B45 -> 9597.53 | E45: =B45 -> 9597.53 | F45: =C45 -> 9597.53 | K45: =B9*(0.8)^(LOG((B45/B21),2)) -> 286.84943 | L45: =C9*(0.8)^(LOG((C45/C21),2)) -> 5.1376017 | N45: =E9*(0.8)^(LOG((E45/E21),2)) -> 321.10011 | O45: =F9*(0.8)^(LOG((F45/F21),2)) -> 5.9938687
A46: India | B46: ='Summari-ForCount (Current&2050)'!AB100 -> 1882.45 | C46: =B46 -> 1882.45 | E46: =B46 -> 1882.45 | F46: =C46 -> 1882.45 | K46: =B10*(0.8)^(LOG((B46/B22),2)) -> 271.25563 | L46: =C10*(0.8)^(LOG((C46/C22),2)) -> 3.8205018 | N46: =E10*(0.8)^(LOG((E46/E22),2)) -> 297.99914 | O46: =F10*(0.8)^(LOG((F46/F22),2)) -> 4.5846022
A47: Middle East | B47: ='Summarize-ForReg(Current&2050)'!AQ65 -> 1028.37 | C47: =B47 -> 1028.37 | E47: =B47 -> 1028.37 | F47: =C47 -> 1028.37 | K47: =B11*(0.8)^(LOG((B47/B23),2)) -> 152.44005 | L47: =C11*(0.8)^(LOG((C47/C23),2)) -> 2.4990171 | N47: =E11*(0.8)^(LOG((E47/E23),2)) -> 252.40073 | O47: =F11*(0.8)^(LOG((F47/F23),2)) -> 3.9984274
A48: Africa | B48: ='Summarize-ForReg(Current&2050)'!AQ66 -> 945.41 | C48: =B48 -> 945.41 | E48: =B48 -> 945.41 | F48: =C48 -> 945.41 | K48: =B12*(0.8)^(LOG((B48/B24),2)) -> 365.0569 | L48: =C12*(0.8)^(LOG((C48/C24),2)) -> 5.4895774 | N48: =E12*(0.8)^(LOG((E48/E24),2)) -> 502.29634 | O48: =F12*(0.8)^(LOG((F48/F24),2)) -> 7.6854084
A49: Brazil | B49: ='Summari-ForCount (Current&2050)'!AB96 -> 245.87 | C49: =B49 -> 245.87 | E49: =B49 -> 245.87 | F49: =C49 -> 245.87 | K49: =B13*(0.8)^(LOG((B49/B25),2)) -> 411.63787 | L49: =C13*(0.8)^(LOG((C49/C25),2)) -> 5.638875 | N49: =E13*(0.8)^(LOG((E49/E25),2)) -> 315.777 | O49: =F13*(0.8)^(LOG((F49/F25),2)) -> 4.5111

Sheet NOUSE
B1: CAPEX-Large | C1: ANM-Large | E1: CAPEX-rooftop | F1: ANM-rooftop | K1: This spreadsheet contains the NZE_ ANM rather than | U1: Annual O&M Costs (USD/kW)
B3: 2022 | C3: 2022 | E3: 2022 | F3: 2022 | U3: 2030 | V3: 2050
A5: European Union | B5: 990 | C5: 14 | E5: 1320 | F5: 20 | T5: Large | U5: 14 | V5: 12
A6: United States | B6: 1120 | C6: 16 | E6: 3490 | F6: 52 | U6: 16 | V6: 16
A7: Japan | B7: 1910 | C7: 28 | E7: 1880 | F7: 28 | U7: 24 | V7: 22
A8: Russia | B8: 1710 | C8: 26 | E8: 2210 | F8: 34 | U8: 22 | V8: 22
A9: China | B9: 720 | C9: 12 | E9: 800 | F9: 14 | U9: 10 | V9: 10
A10: India | B10: 640 | C10: 10 | E10: 700 | F10: 10 | U10: 8 | V10: 8
A11: Middle East | B11: 620 | C11: 10 | E11: 1020 | F11: 16 | U11: 8 | V11: 8
A12: Africa | B12: 1420 | C12: 22 | E12: 1970 | F12: 30 | U12: 18 | V12: 18
A13: Brazil | B13: 750 | C13: 12 | E13: 580 | F13: 8 | U13: 10 | V13: 10
B15: PV capacity | C15: PV capacity | E15: PV capacity | F15: PV capacity | T15: Rooftop | U15: 18 | V15: 14
B16: 2022 | C16: 2022 | E16: 2022 | F16: 2022 | U16: 46 | V16: 44
A17: European Union | B17: ='Summari-ForCount (2030)'!AO60 -> 266.93 | C17: =B17 -> 266.93 | E17: =B17 -> 266.93 | F17: =C17 -> 266.93 | U17: 24 | V17: 22
A18: United States | B18: ='Summari-ForCount (2030)'!AO62 -> 169.75 | C18: =B18 -> 169.75 | E18: =B18 -> 169.75 | F18: =C18 -> 169.75 | U18: 30 | V18: 28
A19: Japan | B19: ='Summari-ForCount (2030)'!AO66 -> 108.16 | C19: =B19 -> 108.16 | E19: =B19 -> 108.16 | F19: =C19 -> 108.16 | U19: 10 | V19: 10
A20: Russia | B20: ='Summari-ForCount (2030)'!AO63 -> 2.13 | C20: =B20 -> 2.13 | E20: =B20 -> 2.13 | F20: =C20 -> 2.13 | U20: 10 | V20: 8
A21: China | B21: ='Summari-ForCount (2030)'!AO64 -> 688.24 | C21: =B21 -> 688.24 | E21: =B21 -> 688.24 | F21: =C21 -> 688.24 | U21: 14 | V21: 12
A22: India | B22: ='Summari-ForCount (2030)'!AO65 -> 94.77 | C22: =B22 -> 94.77 | E22: =B22 -> 94.77 | F22: =C22 -> 94.77 | U22: 26 | V22: 24
A23: Middle East | B23: ='Summarize-ForReg(Current&2050)'!AL65 -> 13.85 | C23: =B23 -> 13.85 | E23: =B23 -> 13.85 | F23: =C23 -> 13.85 | U23: 8 | V23: 8
A24: Africa | B24: ='Summarize-ForReg(Current&2050)'!AL66 -> 17.04 | C24: =B24 -> 17.04 | E24: =B24 -> 17.04 | F24: =C24 -> 17.04
A25: Brazil | B25: ='Summari-ForCount (2030)'!AO61 -> 41.48 | C25: =B25 -> 41.48 | E25: =B25 -> 41.48 | F25: =C25 -> 41.48
K26: CAPEX-Large | L26: ANM-Large | N26: CAPEX-rooftop | O26: ANM-rooftop | S26: Which input to LCOE calculation code
B27: PV capacity | C27: PV capacity | E27: PV capacity | F27: PV capacity | S27: CAPEX-Large | V27: OM-Large | Y27: CAPEX-Rooftop | AB27: OM-Rooftop
B28: APS-2030 | C28: 2030 | E28: 2030 | F28: 2030 | K28: APS-2030 | L28: 2030 | N28: 2030 | O28: 2030 | S28: =K28 -> APS-2030 | T28: =K40 -> APS-2050 | V28: =N28 -> 2030 | W28: =N40 -> 2050
A29: European Union | B29: ='Summari-ForCount (2030)'!AR60 -> 746.62 | C29: =B29 -> 746.62 | E29: =B29 -> 746.62 | F29: =C29 -> 746.62 | K29: =B5*(0.8)^(LOG((B29/B17),2)) -> 710.93385 | L29: 14 | N29: =E5*(0.8)^(LOG((E29/E17),2)) -> 947.91181 | O29: 18 | R29: European Union | S29: =K29 -> 710.93385 | T29: =K41 -> 629.13959 | V29: =L29 -> 14 | W29: =L41 -> 12 | Y29: =N29 -> 947.91181 | Z29: =N41 -> 838.85279 | AB29: =O29 -> 18 | AC29: =O41 -> 14
A30: United States | B30: ='Summari-ForCount (2030)'!AR62 -> 719.52 | C30: =B30 -> 719.52 | E30: =B30 -> 719.52 | F30: =C30 -> 719.52 | K30: =B6*(0.8)^(LOG((B30/B18),2)) -> 703.54855 | L30: 16 | N30: =E6*(0.8)^(LOG((E30/E18),2)) -> 2192.3075 | O30: 46 | R30: United States | S30: =K30 -> 703.54855 | T30: =K42 -> 501.61523 | V30: =L30 -> 16 | W30: =L42 -> 16 | Y30: =N30 -> 2192.3075 | Z30: =N42 -> 1563.0689 | AB30: =O30 -> 46 | AC30: =O42 -> 44
A31: Japan | B31: ='Summari-ForCount (2030)'!AR66 -> 172.08 | C31: =B31 -> 172.08 | E31: =B31 -> 172.08 | F31: =C31 -> 172.08 | K31: =B7*(0.8)^(LOG((B31/B19),2)) -> 1644.7964 | L31: 24 | N31: =E7*(0.8)^(LOG((E31/E19),2)) -> 1618.9619 | O31: 24 | R31: Japan | S31: =K31 -> 1644.7964 | T31: =K43 -> 1514.4037 | V31: =L31 -> 24 | W31: =L43 -> 22 | Y31: =N31 -> 1618.9619 | Z31: =N43 -> 1490.6173 | AB31: =O31 -> 24 | AC31: =O43 -> 22
A32: Russia | B32: ='Summari-ForCount (2030)'!AR63 -> 5.49 | C32: =B32 -> 5.49 | E32: =B32 -> 5.49 | F32: =C32 -> 5.49 | K32: =B8*(0.8)^(LOG((B32/B20),2)) -> 1260.7286 | L32: 22 | N32: =E8*(0.8)^(LOG((E32/E20),2)) -> 1629.3627 | O32: 30 | R32: Russia | S32: =K32 -> 1260.7286 | T32: =K44 -> 833.26735 | V32: =L32 -> 22 | W32: =L44 -> 22 | Y32: =N32 -> 1629.3627 | Z32: =N44 -> 1076.9128 | AB32: =O32 -> 30 | AC32: =O44 -> 28
A33: China | B33: ='Summari-ForCount (2030)'!AR64 -> 3315.59 | C33: =B33 -> 3315.59 | E33: =B33 -> 3315.59 | F33: =C33 -> 3315.59 | K33: =B9*(0.8)^(LOG((B33/B21),2)) -> 434.02352 | L33: 10 | N33: =E9*(0.8)^(LOG((E33/E21),2)) -> 482.24835 | O33: 10 | R33: China | S33: =K33 -> 434.02352 | T33: =K45 -> 308.2561 | V33: =L33 -> 10 | W33: =L45 -> 10 | Y33: =N33 -> 482.24835 | Z33: =N45 -> 342.50678 | AB33: =O33 -> 10 | AC33: =O45 -> 10
A34: India | B34: ='Summari-ForCount (2030)'!AR65 -> 385.32 | C34: =B34 -> 385.32 | E34: =B34 -> 385.32 | F34: =C34 -> 385.32 | K34: =B10*(0.8)^(LOG((B34/B22),2)) -> 407.45276 | L34: 8 | N34: =E10*(0.8)^(LOG((E34/E22),2)) -> 445.65145 | O34: 10 | R34: India | S34: =K34 -> 407.45276 | T34: =K46 -> 244.51212 | V34: =L34 -> 8 | W34: =L46 -> 8 | Y34: =N34 -> 445.65145 | Z34: =N46 -> 267.43513 | AB34: =O34 -> 10 | AC34: =O46 -> 8
A35: Middle East | B35: ='Summarize-ForReg(2030)'!AP65 -> 132.56 | C35: =B35 -> 132.56 | E35: =B35 -> 132.56 | F35: =C35 -> 132.56 | K35: =B11*(0.8)^(LOG((B35/B23),2)) -> 299.63478 | L35: 8 | N35: =E11*(0.8)^(LOG((E35/E23),2)) -> 492.94755 | O35: 14 | R35: Middle East | S35: =K35 -> 299.63478 | T35: =K47 -> 154.93906 | V35: =L35 -> 8 | W35: =L47 -> 8 | Y35: =N35 -> 492.94755 | Z35: =N47 -> 254.89975 | AB35: =O35 -> 14 | AC35: =O47 -> 12
A36: Africa | B36: ='Summarize-ForReg(2030)'!AP66 -> 175.19 | C36: =B36 -> 175.19 | E36: =B36 -> 175.19 | F36: =C36 -> 175.19 | K36: =B12*(0.8)^(LOG((B36/B24),2)) -> 670.63208 | L36: 18 | N36: =E12*(0.8)^(LOG((E36/E24),2)) -> 930.38394 | O36: 26 | R36: Africa | S36: =K36 -> 670.63208 | T36: =K48 -> 389.76 | V36: =L36 -> 18 | W36: =L48 -> 18 | Y36: =N36 -> 930.38394 | Z36: =N48 -> 540.72338 | AB36: =O36 -> 26 | AC36: =O48 -> 24
A37: Brazil | B37: ='Summari-ForCount (2030)'!AR61 -> 135.34 | C37: =B37 -> 135.34 | E37: =B37 -> 135.34 | F37: =C37 -> 135.34 | K37: =B13*(0.8)^(LOG((B37/B25),2)) -> 512.53443 | L37: 10 | N37: =E13*(0.8)^(LOG((E37/E25),2)) -> 396.35996 | O37: 8 | R37: Brazil | S37: =K37 -> 512.53443 | T37: =K49 -> 422.91562 | V37: =L37 -> 10 | W37: =L49 -> 10 | Y37: =N37 -> 396.35996 | Z37: =N49 -> 327.05475 | AB37: =O37 -> 8 | AC37: =O49 -> 8
B39: PV capacity | C39: PV capacity | E39: PV capacity | F39: PV capacity
B40: APS-2050 | C40: 2050 | E40: 2050 | F40: 2050 | K40: APS-2050 | L40: 2050 | N40: 2050 | O40: 2050
A41: European Union | B41: ='Summari-ForCount (Current&2050)'!AB95 -> 1091.41 | C41: =B41 -> 1091.41 | E41: =B41 -> 1091.41 | F41: =C41 -> 1091.41 | K41: =B5*(0.8)^(LOG((B41/B17),2)) -> 629.13959 | L41: 12 | N41: =E5*(0.8)^(LOG((E41/E17),2)) -> 838.85279 | O41: 14
A42: United States | B42: ='Summari-ForCount (Current&2050)'!AB97 -> 2057.92 | C42: =B42 -> 2057.92 | E42: =B42 -> 2057.92 | F42: =C42 -> 2057.92 | K42: =B6*(0.8)^(LOG((B42/B18),2)) -> 501.61523 | L42: 16 | N42: =E6*(0.8)^(LOG((E42/E18),2)) -> 1563.0689 | O42: 44
A43: Japan | B43: ='Summari-ForCount (Current&2050)'!AB101 -> 222.41 | C43: =B43 -> 222.41 | E43: =B43 -> 222.41 | F43: =C43 -> 222.41 | K43: =B7*(0.8)^(LOG((B43/B19),2)) -> 1514.4037 | L43: 22 | N43: =E7*(0.8)^(LOG((E43/E19),2)) -> 1490.6173 | O43: 22
A44: Russia | B44: ='Summari-ForCount (Current&2050)'!AB98 -> 19.87 | C44: =B44 -> 19.87 | E44: =B44 -> 19.87 | F44: =C44 -> 19.87 | K44: =B8*(0.8)^(LOG((B44/B20),2)) -> 833.26735 | L44: 22 | N44: =E8*(0.8)^(LOG((E44/E20),2)) -> 1076.9128 | O44: 28
A45: China | B45: ='Summari-ForCount (Current&2050)'!AB99 -> 9597.53 | C45: =B45 -> 9597.53 | E45: =B45 -> 9597.53 | F45: =C45 -> 9597.53 | K45: =B9*(0.8)^(LOG((B45/B21),2)) -> 308.2561 | L45: 10 | N45: =E9*(0.8)^(LOG((E45/E21),2)) -> 342.50678 | O45: 10
A46: India | B46: ='Summari-ForCount (Current&2050)'!AB100 -> 1882.45 | C46: =B46 -> 1882.45 | E46: =B46 -> 1882.45 | F46: =C46 -> 1882.45 | K46: =B10*(0.8)^(LOG((B46/B22),2)) -> 244.51212 | L46: 8 | N46: =E10*(0.8)^(LOG((E46/E22),2)) -> 267.43513 | O46: 8
A47: Middle East | B47: ='Summarize-ForReg(Current&2050)'!AQ65 -> 1028.37 | C47: =B47 -> 1028.37 | E47: =B47 -> 1028.37 | F47: =C47 -> 1028.37 | K47: =B11*(0.8)^(LOG((B47/B23),2)) -> 154.93906 | L47: 8 | N47: =E11*(0.8)^(LOG((E47/E23),2)) -> 254.89975 | O47: 12
A48: Africa | B48: ='Summarize-ForReg(Current&2050)'!AQ66 -> 945.41 | C48: =B48 -> 945.41 | E48: =B48 -> 945.41 | F48: =C48 -> 945.41 | K48: =B12*(0.8)^(LOG((B48/B24),2)) -> 389.76 | L48: 18 | N48: =E12*(0.8)^(LOG((E48/E24),2)) -> 540.72338 | O48: 24
A49: Brazil | B49: ='Summari-ForCount (Current&2050)'!AB96 -> 245.87 | C49: =B49 -> 245.87 | E49: =B49 -> 245.87 | F49: =C49 -> 245.87 | K49: =B13*(0.8)^(LOG((B49/B25),2)) -> 422.91562 | L49: 10 | N49: =E13*(0.8)^(LOG((E49/E25),2)) -> 327.05475 | O49: 8

Sheet Summari-ForCount (2030)
A1: *Priciple: Exclusive the duplicate records from WEO, IEA2020, IRENA from Data of Brief; Use the record of now (preferring latest year); if there are multiple records in a same reference (except those notifying maximum or minimum value), average them to represent the figure for this reference
F3: WEO2024 (large, ground-mounted) | G3: WEO2024 (rooftop) | H3: IRENA2024 (large, ground-mounted) | I3: IEA2020 (large, ground-mounted, 3% disc-rate) | J3: IEA2020 (large, ground-mounted, 7% discount rate) | K3: IEA2020 (large, ground-mounted, 10% discount rate) | L3: IEA2020 (rooftop, 3% disc-rate) | M3: IEA2020 (rooftop, 7% discount rate) | N3: IEA2020 (rooftop, 10% discount rate) | O3: Hatton et al., 2024 (large, ground-mounted) | V3: USA
D4: Europe | E4: EU-27 | F4: =Attached_WEO2023!B12 -> 750 | G4: =Attached_WEO2023!F12 -> 990 | O4: =AVERAGE('Attached-DIB_GNESTE_Solar_Power'!W70:W74) -> 860.90269 | X4: Stated Policies (STEPS) | AD4: Announced Pledges (APS)
E5: Greece | H5: ='Attached-IRENA2024 report'!J20 -> 626.34564 | V5: 2023 | X5: 2030 | Y5: 2035 | Z5: 2040 | AA5: 2045 | AB5: 2050 | AD5: 2030 | AE5: 2035 | AF5: 2040 | AG5: 2045 | AH5: 2050
E6: Netherlands | H6: ='Attached-IRENA2024 report'!J22 -> 753.19994 | I6: ='Attached-IEA2020Projected Costs'!K39 -> 819.39997 | J6: ='Attached-IEA2020Projected Costs'!L39 -> 835.15911 | K6: ='Attached-IEA2020Projected Costs'!M39 -> 846.78601 | L6: ='Attached-IEA2020Projected Costs'!K38 -> 858.48319 | M6: ='Attached-IEA2020Projected Costs'!L38 -> 874.994 | N6: ='Attached-IEA2020Projected Costs'!M38 -> 887.17547 | O6: =AVERAGE('Attached-DIB_GNESTE_Solar_Power'!V66:V68) -> 787.41448 | V6: 169.75 | X6: 563.37 | Y6: 912.72 | Z6: 1278.24 | AA6: 1626.29 | AB6: 1894.82 | AD6: 719.52 | AE6: 1210.5 | AF6: 1604.45 | AG6: 1916.62 | AH6: 2057.92
E7: Germany | H7: ='Attached-IRENA2024 report'!J24 -> 730.77006 | O7: =AVERAGE('Attached-DIB_GNESTE_Solar_Power'!X89:X90) -> 757.7542
E8: United Kingdom | H8: ='Attached-IRENA2024 report'!J26 -> 932.69058
E9: Portugal | H9: ='Attached-IRENA2024 report'!J28 -> 723.26964
E10: France | H10: ='Attached-IRENA2024 report'!J30 -> 954.78012 | I10: {='Attached-IEA2020Projected Costs'!K21:M21} -> 718.7719 | J10: 732.59571 | K10: 742.79475 | L10: =AVERAGE('Attached-IEA2020Projected Costs'!K19:K20) -> 1293.7894 | M10: =AVERAGE('Attached-IEA2020Projected Costs'!L19:L20) -> 1318.6723 | N10: =AVERAGE('Attached-IEA2020Projected Costs'!M19:M20) -> 1337.0305 | V10: BRZ
E11: Italy | H11: ='Attached-IRENA2024 report'!J32 -> 821.34079 | I11: =AVERAGE('Attached-IEA2020Projected Costs'!K31:K32) -> 844.08816 | J11: =AVERAGE('Attached-IEA2020Projected Costs'!L31:L32) -> 860.32211 | K11: =AVERAGE('Attached-IEA2020Projected Costs'!M31:M32) -> 872.29933 | L11: =AVERAGE('Attached-IEA2020Projected Costs'!K26:K30) -> 1347.0298 | M11: =AVERAGE('Attached-IEA2020Projected Costs'!L26:L30) -> 1372.9366 | N11: =AVERAGE('Attached-IEA2020Projected Costs'!M26:M30) -> 1392.0503 | X11: Stated Policies (STEPS) | AD11: Announced Pledges (APS)
E12: Spain | H12: ='Attached-IRENA2024 report'!J57 -> 670.76717 | V12: 2023 | X12: 2030 | Y12: 2035 | Z12: 2040 | AA12: 2045 | AB12: 2050 | AD12: 2030 | AE12: 2035 | AF12: 2040 | AG12: 2045 | AH12: 2050
E13: Turkey | H13: ='Attached-IRENA2024 report'!J58 -> 715.36 | V13: 41.48 | X13: 91.81 | Y13: 106.1 | Z13: 120.79 | AA13: 135.53 | AB13: 150.96 | AD13: 135.34 | AE13: 175.49 | AF13: 201.5 | AG13: 223.35 | AH13: 245.87
E14: Hungary | H14: ='Attached-IRENA2024 report'!J62 -> 1078 | I14: ='Attached-IEA2020Projected Costs'!K25 -> 978.03747 | J14: ='Attached-IEA2020Projected Costs'!L25 -> 996.84761 | K14: ='Attached-IEA2020Projected Costs'!M25 -> 1010.7255 | L14: =AVERAGE('Attached-IEA2020Projected Costs'!K22:K24) -> 1445.272 | M14: =AVERAGE('Attached-IEA2020Projected Costs'!L22:L24) -> 1473.0682 | N14: =AVERAGE('Attached-IEA2020Projected Costs'!M22:M24) -> 1493.5759
E15: Belgium | H15: ='Attached-IRENA2024 report'!J63 -> 965 | I15: ='Attached-IEA2020Projected Costs'!K12 -> 1006.2807 | J15: ='Attached-IEA2020Projected Costs'!L12 -> 1025.634 | K15: ='Attached-IEA2020Projected Costs'!M12 -> 1039.9126 | L15: =AVERAGE('Attached-IEA2020Projected Costs'!K9:K11) -> 1419.3349 | M15: =AVERAGE('Attached-IEA2020Projected Costs'!L9:L11) -> 1446.6323 | N15: =AVERAGE('Attached-IEA2020Projected Costs'!M9:M11) -> 1466.772
E16: Cyprus | H16: ='Attached-IRENA2024 report'!J64 -> 854 | V16: EU-27
E17: Slovakia | H17: ='Attached-IRENA2024 report'!J65 -> 844 | X17: Stated Policies (STEPS) | AD17: Announced Pledges (APS)
E18: Romania | H18: ='Attached-IRENA2024 report'!J67 -> 743 | V18: 2023 | X18: 2030 | Y18: 2035 | Z18: 2040 | AA18: 2045 | AB18: 2050 | AD18: 2030 | AE18: 2035 | AF18: 2040 | AG18: 2045 | AH18: 2050
E19: Latvia | H19: ='Attached-IRENA2024 report'!J68 -> 716 | V19: 266.93 | X19: 646.76 | Y19: 870.02 | Z19: 991.11 | AA19: 1055.84 | AB19: 1078.1 | AD19: 746.62 | AE19: 967.2 | AF19: 1050.68 | AG19: 1081.83 | AH19: 1091.41
E20: Estonia | H20: ='Attached-IRENA2024 report'!J69 -> 705
E21: Poland | H21: ='Attached-IRENA2024 report'!J70 -> 700
E22: Ireland | H22: ='Attached-IRENA2024 report'!J71 -> 686 | V22: Russia
E23: Luxembourg | H23: ='Attached-IRENA2024 report'!J72 -> 684 | X23: Stated Policies (STEPS) | AD23: Announced Pledges (APS)
E24: Austria | H24: ='Attached-IRENA2024 report'!J73 -> 678 | I24: ='Attached-IEA2020Projected Costs'!K6 -> 729.55348 | J24: ='Attached-IEA2020Projected Costs'!L6 -> 743.58464 | K24: ='Attached-IEA2020Projected Costs'!M6 -> 753.93667 | L24: ='Attached-IEA2020Projected Costs'!K6 -> 729.55348 | M24: ='Attached-IEA2020Projected Costs'!L6 -> 743.58464 | N24: ='Attached-IEA2020Projected Costs'!M6 -> 753.93667 | V24: 2023 | X24: 2030 | Y24: 2035 | Z24: 2040 | AA24: 2045 | AB24: 2050 | AD24: 2030 | AE24: 2035 | AF24: 2040 | AG24: 2045 | AH24: 2050
E25: Czech Republic | H25: ='Attached-IRENA2024 report'!J74 -> 663 | V25: 2.13 | X25: 4.14 | Y25: 4.94 | Z25: 6.01 | AA25: 7.15 | AB25: 8.41 | AD25: 5.49 | AE25: 8.85 | AF25: 12.61 | AG25: 16.55 | AH25: 19.87
E26: Bulgaria | H26: ='Attached-IRENA2024 report'!J75 -> 659
E27: Denmark | I27: =AVERAGE('Attached-IEA2020Projected Costs'!K17:K18) -> 587.43464 | J27: =AVERAGE('Attached-IEA2020Projected Costs'!L17:L18) -> 598.7325 | K27: =AVERAGE('Attached-IEA2020Projected Costs'!M17:M18) -> 607.06792 | L27: =AVERAGE('Attached-IEA2020Projected Costs'!K15:K16) -> 1026.7533 | M27: =AVERAGE('Attached-IEA2020Projected Costs'!L15:L16) -> 1046.5004 | N27: =AVERAGE('Attached-IEA2020Projected Costs'!M15:M16) -> 1061.0695
E28: Norway | L28: ='Attached-IEA2020Projected Costs'!K40 -> 998.35392 | M28: ='Attached-IEA2020Projected Costs'!L40 -> 1017.5548 | N28: ='Attached-IEA2020Projected Costs'!M40 -> 1031.721 | V28: CN
E29: Croatia | X29: Stated Policies (STEPS) | AD29: Announced Pledges (APS)
D30: South America | E30: Chile | H30: ='Attached-IRENA2024 report'!J50 -> 953.80679 | V30: 2023 | X30: 2030 | Y30: 2035 | Z30: 2040 | AA30: 2045 | AB30: 2050 | AD30: 2030 | AE30: 2035 | AF30: 2040 | AG30: 2045 | AH30: 2050
E31: Argentina | H31: ='Attached-IRENA2024 report'!J53 -> 830 | V31: 688.24 | X31: 3263.4 | Y31: 5343.62 | Z31: 7290.94 | AA31: 8887.57 | AB31: 9432.63 | AD31: 3315.59 | AE31: 5433.22 | AF31: 7415.35 | AG31: 9040.46 | AH31: 9597.53
E32: Brazil | F32: =Attached_WEO2023!B18 -> 730 | G32: =Attached_WEO2023!F18 -> 560 | H32: ='Attached-IRENA2024 report'!J48 -> 726.98559 | I32: ='Attached-IEA2020Projected Costs'!K60 -> 1215.2033 | J32: ='Attached-IEA2020Projected Costs'!L60 -> 1238.5747 | K32: ='Attached-IEA2020Projected Costs'!M60 -> 1255.8179 | O32: ='Attached-DIB_GNESTE_Solar_Power'!V134 -> 1382.1652
E33: South America | O33: ='Attached-DIB_GNESTE_Solar_Power'!AA338 -> 819.85934
D34: North America | E34: United States | F34: =Attached_WEO2023!B13 -> 1110 | G34: =Attached_WEO2023!F13 -> 3460 | H34: ='Attached-IRENA2024 report'!J42 -> 1108.5304 | I34: =AVERAGE('Attached-IEA2020Projected Costs'!K51:K55) -> 1087.637 | J34: =AVERAGE('Attached-IEA2020Projected Costs'!L51:L55) -> 1108.555 | K34: =AVERAGE('Attached-IEA2020Projected Costs'!M51:M55) -> 1123.9881 | L34: =AVERAGE('Attached-IEA2020Projected Costs'!K41:K50) -> 1789.2317 | M34: =AVERAGE('Attached-IEA2020Projected Costs'!L41:L50) -> 1823.6432 | N34: =AVERAGE('Attached-IEA2020Projected Costs'!M41:M50) -> 1849.0316 | O34: =AVERAGE('Attached-DIB_GNESTE_Solar_Power'!V15,'Attached-DIB_GNESTE_Solar_Power'!Z17:Z310,'Attached-DIB_GNESTE_Solar_Power'!AB313:AB315,'Attached-DIB_GNESTE_Solar_Power'!Z319,'Attached-DIB_GNESTE_Solar_Power'!X325,'Attached-DIB_GNESTE_Solar_Power'!Y326,'Attached-DIB_GNESTE_Solar_Power'!X331,'Attached-DIB_GNESTE_Solar_Power'!Y332) -> 1349.0303
E35: Canada | H35: ='Attached-IRENA2024 report'!J38 -> 1336.5221 | I35: =AVERAGE('Attached-IEA2020Projected Costs'!K13:K14) -> 1328.7693 | J35: =AVERAGE('Attached-IEA2020Projected Costs'!L13:L14) -> 1354.3249 | K35: =AVERAGE('Attached-IEA2020Projected Costs'!M13:M14) -> 1373.1795
E36: Mexico | H36: ='Attached-IRENA2024 report'!J40 -> 1049.5172 | O36: ='Attached-DIB_GNESTE_Solar_Power'!V137 -> 990.405 | V36: ASEAN
E37: North America | O37: ='Attached-DIB_GNESTE_Solar_Power'!AA337 -> 936.56791 | X37: Stated Policies (STEPS) | AD37: Announced Pledges (APS)
D38: Eurasia | E38: Russia | F38: =Attached_WEO2023!B15 -> 1250 | G38: =Attached_WEO2023!F15 -> 1610 | H38: ='Attached-IRENA2024 report'!J83 -> 1248 | O38: ='Attached-DIB_GNESTE_Solar_Power'!AA341 -> 787.78925 | V38: 2023 | X38: 2030 | Y38: 2035 | Z38: 2040 | AA38: 2045 | AB38: 2050 | AD38: 2030 | AE38: 2035 | AF38: 2040 | AG38: 2045 | AH38: 2050
D39: Asia Pacific | E39: Japan | F39: =Attached_WEO2023!B14 -> 1880 | G39: =Attached_WEO2023!F14 -> 1850 | H39: ='Attached-IRENA2024 report'!J15 -> 1875.2399 | I39: ='Attached-IEA2020Projected Costs'!K34 -> 2035.9917 | J39: ='Attached-IEA2020Projected Costs'!L34 -> 2075.149 | K39: ='Attached-IEA2020Projected Costs'!M34 -> 2104.0388 | L39: ='Attached-IEA2020Projected Costs'!K33 -> 2367.4727 | M39: ='Attached-IEA2020Projected Costs'!L33 -> 2413.0052 | N39: ='Attached-IEA2020Projected Costs'!M33 -> 2446.5985 | V39: 32.13 | X39: 82.67 | Y39: 150.99 | Z39: 236.9 | AA39: 319.85 | AB39: 408.09 | AD39: 165.71 | AE39: 368.34 | AF39: 669.78 | AG39: 898.17 | AH39: 1074.26
E40: China | F40: =Attached_WEO2023!B16 -> 670 | G40: =Attached_WEO2023!F16 -> 750 | H40: ='Attached-IRENA2024 report'!J11 -> 671.12616 | I40: ='Attached-IEA2020Projected Costs'!K61 -> 741.29534 | J40: ='Attached-IEA2020Projected Costs'!L61 -> 755.55232 | K40: ='Attached-IEA2020Projected Costs'!M61 -> 766.07096 | O40: ='Attached-DIB_GNESTE_Solar_Power'!AA342 -> 694.64666
E41: India | F41: =Attached_WEO2023!B17 -> 710 | G41: =Attached_WEO2023!F17 -> 780 | H41: ='Attached-IRENA2024 report'!J13 -> 711.32819 | I41: ='Attached-IEA2020Projected Costs'!K62 -> 638.03526 | J41: ='Attached-IEA2020Projected Costs'!L62 -> 650.30629 | K41: ='Attached-IEA2020Projected Costs'!M62 -> 659.35972 | O41: =AVERAGE('Attached-DIB_GNESTE_Solar_Power'!W25,'Attached-DIB_GNESTE_Solar_Power'!V135,'Attached-DIB_GNESTE_Solar_Power'!AA343) -> 670.57179
E42: Republic of Korea | H42: ='Attached-IRENA2024 report'!J17 -> 1205.2601 | I42: ='Attached-IEA2020Projected Costs'!K36 -> 1244.0419 | J42: ='Attached-IEA2020Projected Costs'!L36 -> 1267.9679 | K42: ='Attached-IEA2020Projected Costs'!M36 -> 1285.6203 | L42: ='Attached-IEA2020Projected Costs'!K35 -> 1258.5589 | M42: ='Attached-IEA2020Projected Costs'!L35 -> 1282.7641 | N42: ='Attached-IEA2020Projected Costs'!M35 -> 1300.6225
E43: Australia | H43: ='Attached-IRENA2024 report'!J45 -> 988.62812 | I43: ='Attached-IEA2020Projected Costs'!K7 -> 895.14787 | J43: ='Attached-IEA2020Projected Costs'!L7 -> 912.36383 | K43: ='Attached-IEA2020Projected Costs'!M7 -> 925.06556 | O43: =AVERAGE('Attached-DIB_GNESTE_Solar_Power'!AA19:AA21) -> 932.2705 | V43: India
E44: Indonesia | H44: ='Attached-IRENA2024 report'!J78 -> 798 | O44: =AVERAGE('Attached-DIB_GNESTE_Solar_Power'!V3:V4,'Attached-DIB_GNESTE_Solar_Power'!V133) -> 1913.4028 | X44: Stated Policies (STEPS) | AD44: Announced Pledges (APS)
E45: Malaysia | O45: =AVERAGE('Attached-DIB_GNESTE_Solar_Power'!V5:V6) -> 2262.804 | V45: 2023 | X45: 2030 | Y45: 2035 | Z45: 2040 | AA45: 2045 | AB45: 2050 | AD45: 2030 | AE45: 2035 | AF45: 2040 | AG45: 2045 | AH45: 2050
E46: Philippines | O46: =AVERAGE('Attached-DIB_GNESTE_Solar_Power'!V7:V8) -> 2229.198 | V46: 94.77 | X46: 372.48 | Y46: 645.98 | Z46: 934.4 | AA46: 1201.1 | AB46: 1429.1 | AD46: 385.32 | AE46: 767.79 | AF46: 1243.49 | AG46: 1584.94 | AH46: 1882.45
E47: Thailand | O47: =AVERAGE('Attached-DIB_GNESTE_Solar_Power'!V136) -> 1108.1532
E48: Asia | O48: ='Attached-DIB_GNESTE_Solar_Power'!V11 -> 2254.9626
E49: Southeast Asia | O49: ='Attached-DIB_GNESTE_Solar_Power'!AA344 -> 718.76686
E50: OECD Asia & Oceania | O50: ='Attached-DIB_GNESTE_Solar_Power'!AA345 -> 922.20862
D51: Global | H51: ='Attached-IRENA2024 report'!AB11 -> 757.68783 | O51: =AVERAGE('Attached-DIB_GNESTE_Solar_Power'!W76:W322) -> 918.0296 | V51: Japan
X52: Stated Policies (STEPS) | AD52: Announced Pledges (APS)
V53: 2023 | X53: 2030 | Y53: 2035 | Z53: 2040 | AA53: 2045 | AB53: 2050 | AD53: 2030 | AE53: 2035 | AF53: 2040 | AG53: 2045 | AH53: 2050
V54: 108.16 | X54: 169.15 | Y54: 199.96 | Z54: 210.54 | AA54: 211.48 | AB54: 211.51 | AD54: 172.08 | AE54: 204.21 | AF54: 219.15 | AG54: 222.29 | AH54: 222.41
B58: CAPEX | E58: Current-2023 | H58: SPS-2030 | K58: APS-2030 | N58: NZE-2030 | X58: Stated Policies (STEPS) | AD58: Announced Pledges (APS)
E59: Large, ground-mounted PV | F59: Rooftop PV | G59: Differences | V59: 2023 | X59: 2030 | Y59: 2035 | Z59: 2040 | AA59: 2045 | AB59: 2050 | AD59: 2030 | AE59: 2035 | AF59: 2040 | AG59: 2045 | AH59: 2050 | AM59: Capacity | AO59: 2023 | AP59: SPS-2030 | AQ59: SPS-2050 | AR59: APS-2030 | AS59: APS-2050
D60: =D83 -> European Union | E60: =E83 -> 750 | F60: =F83 -> 990 | G60: =F60-E60 -> 240 | H60: =J117 -> 480 | I60: =J127 -> 650 | J60: =I60-H60 -> 170 | K60: =H60*(0.8)^(LOG((AD19/X19),2)) -> 458.31803 | L60: =I60*(0.8)^(LOG((AD19/X19),2)) -> 620.63899 | M60: =L60-K60 -> 162.32097 | N60: Should refer to PG assumption file | V60: 17.04 | X60: 81.43 | Y60: 152.02 | Z60: 220.44 | AA60: 285.15 | AB60: 332.13 | AD60: 175.19 | AE60: 347.96 | AF60: 535.77 | AG60: 737.89 | AH60: 945.41 | AN60: European Union | AO60: =V19 -> 266.93 | AP60: =X19 -> 646.76 | AQ60: =AB19 -> 1078.1 | AR60: =AD19 -> 746.62 | AS60: =AH19 -> 1091.41
D61: =D89 -> Brazil | E61: =E89 -> 730 | F61: =F89 -> 560 | G61: =F61-E61 -> -170 | H61: =J125 -> 460 | I61: =J135 -> 350 | J61: =I61-H61 -> -110 | K61: =H61*(0.8)^(LOG((AD13/X13),2)) -> 405.97688 | L61: =I61*(0.8)^(LOG((AD13/X13),2)) -> 308.89545 | M61: =L61-K61 -> -97.081427 | AN61: Brazil | AO61: =V13 -> 41.48 | AP61: =X13 -> 91.81 | AQ61: =AB13 -> 150.96 | AR61: =AD13 -> 135.34 | AS61: =AH13 -> 245.87
D62: =D84 -> United States | E62: =E84 -> 1110 | F62: =F84 -> 3460 | G62: =F62-E62 -> 2350 | H62: =J118 -> 690 | I62: =J128 -> 2200 | J62: =I62-H62 -> 1510 | K62: =H62*(0.8)^(LOG((AD6/X6),2)) -> 637.74124 | L62: =I62*(0.8)^(LOG((AD6/X6),2)) -> 2033.3779 | M62: =L62-K62 -> 1395.6366 | AN62: United States | AO62: =V6 -> 169.75 | AP62: =X6 -> 563.37 | AQ62: =AB6 -> 1894.82 | AR62: =AD6 -> 719.52 | AS62: =AH6 -> 2057.92
D63: =D86 -> Russia | E63: =E86 -> 1250 | F63: =F86 -> 1610 | G63: =F63-E63 -> 360 | H63: =J120 -> 820 | I63: =J130 -> 1080 | J63: =I63-H63 -> 260 | K63: =H63*(0.8)^(LOG((AD25/X25),2)) -> 748.78042 | L63: =I63*(0.8)^(LOG((AD25/X25),2)) -> 986.19861 | M63: =L63-K63 -> 237.41818 | AN63: Russia | AO63: =V25 -> 2.13 | AP63: =X25 -> 4.14 | AQ63: =AB25 -> 8.41 | AR63: =AD25 -> 5.49 | AS63: =AH25 -> 19.87
D64: =D87 -> China | E64: =E87 -> 670 | F64: =F87 -> 750 | G64: =F64-E64 -> 80 | H64: =J121 -> 410 | I64: =J131 -> 450 | J64: =I64-H64 -> 40 | K64: =H64*(0.8)^(LOG((AD31/X31),2)) -> 407.91118 | L64: =I64*(0.8)^(LOG((AD31/X31),2)) -> 447.70739 | M64: =L64-K64 -> 39.796213 | AN64: China | AO64: =V31 -> 688.24 | AP64: =X31 -> 3263.4 | AQ64: =AB31 -> 9432.63 | AR64: =AD31 -> 3315.59 | AS64: =AH31 -> 9597.53
D65: =D88 -> India | E65: =E88 -> 710 | F65: =F88 -> 780 | G65: =F65-E65 -> 70 | H65: =J122 -> 450 | I65: =J132 -> 490 | J65: =I65-H65 -> 40 | K65: =H65*(0.8)^(LOG((AD46/X46),2)) -> 445.117 | L65: =I65*(0.8)^(LOG((AD46/X46),2)) -> 484.68296 | M65: =L65-K65 -> 39.565956 | AN65: India | AO65: =V46 -> 94.77 | AP65: =X46 -> 372.48 | AQ65: =AB46 -> 1429.1 | AR65: =AD46 -> 385.32 | AS65: =AH46 -> 1882.45
D66: =D85 -> Japan | E66: =E85 -> 1880 | F66: =F85 -> 1850 | G66: =F66-E66 -> -30 | H66: =J119 -> 1260 | I66: =J129 -> 1280 | J66: =I66-H66 -> 20 | K66: =H66*(0.8)^(LOG((AD54/X54),2)) -> 1253.0531 | L66: =I66*(0.8)^(LOG((AD54/X54),2)) -> 1272.9428 | M66: =L66-K66 -> 19.889732 | AN66: Japan | AO66: =V54 -> 108.16 | AP66: =X54 -> 169.15 | AQ66: =AB54 -> 211.51 | AR66: =AD54 -> 172.08 | AS66: =AH54 -> 222.41
D67: Southeast Asia | E67: =AVERAGE(H44,O44:O47,O49) -> 1505.0541 | F67: ='Summarize-ForReg(2030)'!F64 -> 1605.4469 | G67: =F67-E67 -> 100.39273 | H67: =E67*(0.8)^(LOG((X39/V39),2)) -> 1110.2502 | I67: =F67*(0.8)^(LOG((X39/V39),2)) -> 1184.308 | J67: =I67-H67 -> 74.057835 | K67: =E67*(0.8)^(LOG((AD39/V39),2)) -> 887.56122 | L67: =F67*(0.8)^(LOG((AD39/V39),2)) -> 946.76487 | M67: =L67-K67 -> 59.203649 | N67: - | O67: - | P67: - | AN67: Southeast Asia | AO67: =V39 -> 32.13 | AP67: =X39 -> 82.67 | AQ67: =AB39 -> 408.09 | AR67: =AD39 -> 165.71 | AS67: =AH39 -> 1074.26
B72: Costs related to CAPEX | E72: Current (2023) | F72: SPS-2030 | G72: APS-2030 | I72: Recalculated but not applied | P72: Current (2023) | Q72: SPS-2030 | R72: SPS-2050 | S72: APS-2030 | T72: APS-2050
D73: European Union | E73: =(E60*0.6+F60*0.4)*AO60/1000 -> 225.82278 | F73: =(H60*0.6+I60*0.4)*AP60/1000 -> 354.42448 | G73: =(K60*0.6+L60*0.4)*AR60/1000 -> 390.66624 | I73: European Union | O73: European Union | P73: 225.82278 | Q73: 354.42448 | R73: 422.6152 | S73: 453.59053 | T73: 586.77299
D74: Brazil | E74: =(E61*0.6+F61*0.4)*AO61/1000 -> 27.45976 | F74: =(H61*0.6+I61*0.4)*AP61/1000 -> 38.19296 | G74: =(K61*0.6+L61*0.4)*AR61/1000 -> 49.68931 | I74: Brazil | O74: Brazil | P74: 27.45976 | Q74: 38.19296 | R74: 45.58992 | S74: 61.227417 | T74: 91.781679
D75: United States | E75: =(E62*0.6+F62*0.4)*AO62/1000 -> 347.9875 | F75: =(H62*0.6+I62*0.4)*AP62/1000 -> 729.00078 | G75: =(K62*0.6+L62*0.4)*AR62/1000 -> 860.54297 | I75: United States | O75: United States | P75: 347.9875 | Q75: 729.00078 | R75: 1675.0209 | S75: 926.55836 | T75: 1889.4484
D76: Russia | E76: =(E63*0.6+F63*0.4)*AO63/1000 -> 2.96922 | F76: =(H63*0.6+I63*0.4)*AP63/1000 -> 3.82536 | G76: =(K63*0.6+L63*0.4)*AR63/1000 -> 4.6321748 | I76: Russia | O76: Russia | P76: 2.96922 | Q76: 3.82536 | R76: 5.5506 | S76: 5.6423578 | T76: 13.497362
D77: China | E77: =(E64*0.6+F64*0.4)*AO64/1000 -> 483.14448 | F77: =(H64*0.6+I64*0.4)*AP64/1000 -> 1390.2084 | G77: =(K64*0.6+L64*0.4)*AR64/1000 -> 1405.2454 | I77: China | O77: China | P77: 483.14448 | Q77: 1390.2084 | R77: 2754.328 | S77: 1403.0679 | T77: 2884.5348
D78: India | E78: =(E65*0.6+F65*0.4)*AO65/1000 -> 69.94026 | F78: =(H65*0.6+I65*0.4)*AP65/1000 -> 173.57568 | G78: =(K65*0.6+L65*0.4)*AR65/1000 -> 177.61071 | I78: India | O78: India | P78: 69.94026 | Q78: 173.57568 | R78: 445.8792 | S78: 181.04027 | T78: 530.76249
D79: Japan | E79: =(E66*0.6+F66*0.4)*AO66/1000 -> 202.04288 | F79: =(H66*0.6+I66*0.4)*AP66/1000 -> 214.4822 | G79: =(K66*0.6+L66*0.4)*AR66/1000 -> 216.99443 | I79: Japan | O79: Japan | P79: 202.04288 | Q79: 214.4822 | R79: 203.0496 | S79: 276.81273 | T79: 329.41205
D80: Southeast Asia | E80: =(E67*0.6+F67*0.4)*V39/1000 -> 49.647637 | F80: =(H67*0.6+I67*0.4)*AP67/1000 -> 94.233327 | G80: =(K67*0.6+L67*0.4)*AR67/1000 -> 151.00202 | O80: Southeast Asia | P80: 49.647637 | Q80: 94.233327 | R80: 278.21787 | S80: 151.00202 | T80: 536.30875
D83: European Union | E83: =J85 -> 750 | F83: =J95 -> 990 | G83: =F83-E83 -> 240 | J83: 2023
D84: United States | E84: =J86 -> 1110 | F84: =J96 -> 3460 | G84: =F84-E84 -> 2350 | I84: Solar photovoltaics - Large scale unit
D85: Japan | E85: =J87 -> 1880 | F85: =J97 -> 1850 | G85: =F85-E85 -> -30 | I85: European Union | J85: 750
D86: Russia | E86: =J88 -> 1250 | F86: =J98 -> 1610 | G86: =F86-E86 -> 360 | I86: United States | J86: 1110
D87: China | E87: =J89 -> 670 | F87: =J99 -> 750 | G87: =F87-E87 -> 80 | I87: Japan | J87: 1880
D88: India | E88: =J90 -> 710 | F88: =J100 -> 780 | G88: =F88-E88 -> 70 | I88: Russia | J88: 1250
D89: Brazil | E89: =J93 -> 730 | F89: =J103 -> 560 | G89: =F89-E89 -> -170 | I89: China | J89: 670
I90: India | J90: 710
I91: Middle East | J91: 610
I92: Africa | J92: 1330
D93: 50-PCT | I93: Brazil | J93: 730
D94: European Union | E94: =(E60*0.5+F60*0.5)*AO60/1000-E73 -> 6.40632 | F94: =(H60*0.5+I60*0.5)*AP60/1000-F73 -> 10.99492 | G94: =(K60*0.5+L60*0.5)*AR60/1000-G73 -> 12.119208 | I94: Solar photovoltaics - Buildings
D95: Brazil | E95: =(E61*0.5+F61*0.5)*AO61/1000-E74 -> -0.70516 | F95: =(H61*0.5+I61*0.5)*AP61/1000-F74 -> -1.00991 | G95: =(K61*0.5+L61*0.5)*AR61/1000-G74 -> -1.3139 | I95: European Union | J95: 990
D96: United States | E96: =(E62*0.5+F62*0.5)*AO62/1000-E75 -> 39.89125 | F96: =(H62*0.5+I62*0.5)*AP62/1000-F75 -> 85.06887 | G96: =(K62*0.5+L62*0.5)*AR62/1000-G75 -> 100.41885 | I96: United States | J96: 3460
D97: Russia | E97: =(E63*0.5+F63*0.5)*AO63/1000-E76 -> 0.07668 | F97: =(H63*0.5+I63*0.5)*AP63/1000-F76 -> 0.10764 | G97: =(K63*0.5+L63*0.5)*AR63/1000-G76 -> 0.13034258 | I97: Japan | J97: 1850
D98: China | E98: =(E64*0.5+F64*0.5)*AO64/1000-E77 -> 5.50592 | F98: =(H64*0.5+I64*0.5)*AP64/1000-F77 -> 13.0536 | G98: =(K64*0.5+L64*0.5)*AR64/1000-G77 -> 13.194792 | I98: Russia | J98: 1610 | L98: 450 | M98: 620
D99: India | E99: =(E65*0.5+F65*0.5)*AO65/1000-E78 -> 0.66339 | F99: =(H65*0.5+I65*0.5)*AP65/1000-F78 -> 1.48992 | G99: =(K65*0.5+L65*0.5)*AR65/1000-G78 -> 1.5245554 | I99: China | J99: 750 | L99: 330 | M99: 260
D100: Japan | E100: =(E66*0.5+F66*0.5)*AO66/1000-E79 -> -0.32448 | F100: =(H66*0.5+I66*0.5)*AP66/1000-F79 -> 0.3383 | G100: =(K66*0.5+L66*0.5)*AR66/1000-G79 -> 0.34226251 | I100: India | J100: 780 | L100: 480 | M100: 1510
D101: Southeast Asia | E101: =(E67*0.5+F67*0.5)*AO67/1000-E80 -> 0.32256186 | F101: =(H67*0.5+I67*0.5)*AP67/1000-F80 -> 0.61223613 | G101: =(K67*0.5+L67*0.5)*AR67/1000-G80 -> 0.98106367 | I101: Middle East | J101: 1010 | L101: 770 | M101: 1010
I102: Africa | J102: 1830 | L102: 300 | M102: 340
I103: Brazil | J103: 560 | L103: 270 | M103: 290
D104: 40-pct | E104: =E94*2 -> 12.81264 | F104: =F94*2 -> 21.98984 | G104: =G94*2 -> 24.238416 | L104: 940 | M104: 990
E105: =E95*2 -> -1.41032 | F105: =F95*2 -> -2.01982 | G105: =G95*2 -> -2.6278001
E106: =E96*2 -> 79.7825 | F106: =F96*2 -> 170.13774 | G106: =G96*2 -> 200.83769
E107: =E97*2 -> 0.15336 | F107: =F97*2 -> 0.21528 | G107: =G97*2 -> 0.26068516
E108: =E98*2 -> 11.01184 | F108: =F98*2 -> 26.1072 | G108: =G98*2 -> 26.389585
E109: =E99*2 -> 1.32678 | F109: =F99*2 -> 2.97984 | G109: =G99*2 -> 3.0491108
E110: =E100*2 -> -0.64896 | F110: =F100*2 -> 0.6766 | G110: =G100*2 -> 0.68452501
...

Sheet Summari-ForCount (Current&2050)
A1: *Priciple: Exclusive the duplicate records from WEO, IEA2020, IRENA from Data of Brief; Use the record of now (preferring latest year); if there are multiple records in a same reference (except those notifying maximum or minimum value), average them to represent the figure for this reference | BD1: Baseline PV generation mix (40% rooftop vs. 60% ground-mounted)
BD2: Capital expenditure ($ billion) | BE2: 2023 | BF2: SPS-2030 | BG2: SPS-2050 | BH2: APS-2030 | BI2: APS-2050 | BJ2: NZE-2030 | BK2: NZE-2050 | CA2: 2023 | CB2: SPS-2030 | CC2: SPS-2050 | CD2: APS-2030 | CE2: APS-2050 | CF2: NZE-2030 | CG2: NZE-2050 | CQ2: 2023 | CR2: SPS-2030 | CS2: SPS-2050 | CT2: APS-2030 | CU2: APS-2050
F3: WEO2024 (large, ground-mounted) | G3: WEO2024 (rooftop) | H3: IRENA2024 (large, ground-mounted) | I3: IEA2020 (large, ground-mounted, 3% disc-rate) | J3: IEA2020 (large, ground-mounted, 7% discount rate) | K3: IEA2020 (large, ground-mounted, 10% discount rate) | L3: IEA2020 (rooftop, 3% disc-rate) | M3: IEA2020 (rooftop, 7% discount rate) | N3: IEA2020 (rooftop, 10% discount rate) | O3: Hatton et al., 2024 (large, ground-mounted) | V3: USA | BD3: EUR | BE3: 301.27137 | BF3: 560.69282 | BG3: 800.1611 | BH3: 618.17907 | BI3: 851.92279 | BK3: - | BZ3: European Union | CA3: 299.49546 | CB3: 457.90608 | CC3: 558.4558 | CD3: 601.57043 | CE3: 778.20247 | CP3: EU-27 | CQ3: 299.49546 | CR3: 457.90608 | CS3: 558.4558 | CT3: 601.57043 | CU3: 778.20247
D4: Europe | E4: EU-27 | F4: =Attached_WEO2023!B12 -> 750 | G4: =Attached_WEO2023!F12 -> 990 | O4: =AVERAGE('Attached-DIB_GNESTE_Solar_Power'!W70:W74) -> 860.90269 | X4: Stated Policies (STEPS) | AD4: Announced Pledges (APS) | BD4: CSA | BE4: 52.237595 | BF4: 92.909724 | BG4: 155.5699 | BH4: 124.48575 | BI4: 261.60448 | BK4: - | BZ4: Brazil | CA4: 28.28936 | CB4: 38.19296 | CC4: 45.58992 | CD4: 63.077188 | CE4: 94.554539 | CP4: BR | CQ4: 28.28936 | CR4: 38.19296 | CS4: 45.58992 | CT4: 63.077188 | CU4: 94.554539
E5: Greece | H5: ='Attached-IRENA2024 report'!J20 -> 626.34564 | V5: 2023 | X5: 2030 | Y5: 2035 | Z5: 2040 | AA5: 2045 | AB5: 2050 | AD5: 2030 | AE5: 2035 | AF5: 2040 | AG5: 2045 | AH5: 2050 | BD5: NA | BE5: 301.64656 | BF5: 667.68688 | BG5: 1495.101 | BH5: 782.83762 | BI5: 1664.5941 | BK5: - | BZ5: United States | CA5: 351.043 | CB5: 719.98686 | CC5: 1690.1794 | CD5: 934.69399 | CE5: 1906.0387 | CP5: USA | CQ5: 351.043 | CR5: 719.98686 | CS5: 1690.1794 | CT5: 934.69399 | CU5: 1906.0387
E6: Netherlands | H6: ='Attached-IRENA2024 report'!J22 -> 753.19994 | I6: ='Attached-IEA2020Projected Costs'!K39 -> 819.39997 | J6: ='Attached-IEA2020Projected Costs'!L39 -> 835.15911 | K6: ='Attached-IEA2020Projected Costs'!M39 -> 846.78601 | L6: ='Attached-IEA2020Projected Costs'!K38 -> 858.48319 | M6: ='Attached-IEA2020Projected Costs'!L38 -> 874.994 | N6: ='Attached-IEA2020Projected Costs'!M38 -> 887.17547 | O6: =AVERAGE('Attached-DIB_GNESTE_Solar_Power'!V66:V68) -> 787.41448 | V6: 169.75 | X6: 563.37 | Y6: 912.72 | Z6: 1278.24 | AA6: 1626.29 | AB6: 1894.82 | AD6: 719.52 | AE6: 1210.5 | AF6: 1604.45 | AG6: 1916.62 | AH6: 2057.92 | BD6: Eurasia | BE6: 7.6758419 | BF6: 18.507324 | BG6: 29.019717 | BH6: 21.637334 | BI6: 52.544319 | BK6: - | BZ6: Russia | CA6: 4.0683 | CB6: 5.0922 | CC6: 7.28306 | CD6: 7.7309207 | CE6: 18.493516 | CP6: RU | CQ6: 4.0683 | CR6: 5.0922 | CS6: 7.28306 | CT6: 7.7309207 | CU6: 18.493516
E7: Germany | H7: ='Attached-IRENA2024 report'!J24 -> 730.77006 | O7: =AVERAGE('Attached-DIB_GNESTE_Solar_Power'!X89:X90) -> 757.7542 | BD7: APJ | BE7: 1358.9988 | BF7: 3515.1532 | BG7: 7294.6065 | BH7: 3642.1984 | BI7: 7915.9966 | BK7: - | BZ7: China | CA7: 517.55648 | CB7: 1468.53 | CC7: 2980.7111 | CD7: 1503.0015 | CE7: 3089.986 | CP7: CN | CQ7: 517.55648 | CR7: 1468.53 | CS7: 2980.7111 | CT7: 1503.0015 | CU7: 3089.986
E8: United Kingdom | H8: ='Attached-IRENA2024 report'!J26 -> 932.69058 | BD8: ME | BE8: 10.803 | BF8: 43.156772 | BG8: 134.83278 | BH8: 49.969803 | BI8: 200.45331 | BK8: - | BZ8: India | CA8: 62.92728 | CB8: 151.22688 | CC8: 397.2898 | CD8: 162.88718 | CE8: 477.5424 | CP8: IN | CQ8: 62.92728 | CR8: 151.22688 | CS8: 397.2898 | CT8: 162.88718 | CU8: 477.5424
E9: Portugal | H9: ='Attached-IRENA2024 report'!J28 -> 723.26964 | BD9: AF | BE9: 27.9456 | BF9: 80.711933 | BG9: 217.87728 | BH9: 135.69041 | BI9: 425.57191 | BK9: - | BZ9: Japan | CA9: 205.28768 | CB9: 213.4673 | CC9: 203.0496 | CD9: 281.25833 | CE9: 334.70239 | CP9: JP | CQ9: 205.28768 | CR9: 213.4673 | CS9: 203.0496 | CT9: 281.25833 | CU9: 334.70239
E10: France | H10: ='Attached-IRENA2024 report'!J30 -> 954.78012 | I10: {='Attached-IEA2020Projected Costs'!K21:M21} -> 718.7719 | J10: 732.59571 | K10: 742.79475 | L10: =AVERAGE('Attached-IEA2020Projected Costs'!K19:K20) -> 1293.7894 | M10: =AVERAGE('Attached-IEA2020Projected Costs'!L19:L20) -> 1318.6723 | N10: =AVERAGE('Attached-IEA2020Projected Costs'!M19:M20) -> 1337.0305 | V10: BRZ | BD10: Global | BE10: 1809.9278 | BF10: 4335.5785 | BG10: 8749.8537 | BH10: 4684.3552 | BI10: 10011.42 | BJ10: 4759.1397 | BK10: 10532.937 | BZ10: Southeast Asia | CA10: 49.647637 | CB10: 94.233327 | CC10: 278.21787 | CD10: 151.00202 | CE10: 536.30875 | CP10: ASEAN | CQ10: 49.647637 | CR10: 94.233327 | CS10: 278.21787 | CT10: 151.00202 | CU10: 536.30875
E11: Italy | H11: ='Attached-IRENA2024 report'!J32 -> 821.34079 | I11: =AVERAGE('Attached-IEA2020Projected Costs'!K31:K32) -> 844.08816 | J11: =AVERAGE('Attached-IEA2020Projected Costs'!L31:L32) -> 860.32211 | K11: =AVERAGE('Attached-IEA2020Projected Costs'!M31:M32) -> 872.29933 | L11: =AVERAGE('Attached-IEA2020Projected Costs'!K26:K30) -> 1347.0298 | M11: =AVERAGE('Attached-IEA2020Projected Costs'!L26:L30) -> 1372.9366 | N11: =AVERAGE('Attached-IEA2020Projected Costs'!M26:M30) -> 1392.0503 | X11: Stated Policies (STEPS) | AD11: Announced Pledges (APS) | BD11: 50% rooftop, 50% ground-mounted
E12: Spain | H12: ='Attached-IRENA2024 report'!J57 -> 670.76717 | V12: 2023 | X12: 2030 | Y12: 2035 | Z12: 2040 | AA12: 2045 | AB12: 2050 | AD12: 2030 | AE12: 2035 | AF12: 2040 | AG12: 2045 | AH12: 2050 | BD12: EUR | BE12: 11.615989 | BF12: 21.618388 | BG12: 30.851462 | BH12: 23.834861 | BI12: 32.847215 | BK12: - | BM12: =BE3+BE12 -> 312.88736 | BN12: =BF3+BF12 -> 582.31121 | BO12: =BG3+BG12 -> 831.01256 | BP12: =BH3+BH12 -> 642.01393 | BQ12: =BI3+BI12 -> 884.77 | BR12: - | BS12: - | CP12: EU-27 | CQ12: =CA3+CA24 -> 308.30415 | CR12: =CB3+CB24 -> 472.1348 | CS12: =CC3+CC24 -> 576.7835 | CT12: =CD3+CD24 -> 619.26367 | CU12: =CE3+CE24 -> 801.09078
E13: Turkey | H13: ='Attached-IRENA2024 report'!J58 -> 715.36 | V13: 41.48 | X13: 91.81 | Y13: 106.1 | Z13: 120.79 | AA13: 135.53 | AB13: 150.96 | AD13: 135.34 | AE13: 175.49 | AF13: 201.5 | AG13: 223.35 | AH13: 245.87 | BD13: CSA | BE13: -2.7196991 | BF13: -4.8372536 | BG13: -8.0995944 | BH13: -6.4812286 | BI13: -13.620181 | BK13: - | BM13: =BE4+BE13 -> 49.517896 | BN13: =BF4+BF13 -> 88.072471 | BO13: =BG4+BG13 -> 147.47031 | BP13: =BH4+BH13 -> 118.00452 | BQ13: =BI4+BI13 -> 247.9843 | BR13: - | BS13: - | CP13: BR | CQ13: =CA4+CA25 -> 27.5842 | CR13: =CB4+CB25 -> 37.18305 | CS13: =CC4+CC25 -> 44.5332 | CT13: =CD4+CD25 -> 61.504883 | CU13: =CE4+CE25 -> 92.197608
E14: Hungary | H14: ='Attached-IRENA2024 report'!J62 -> 1078 | I14: ='Attached-IEA2020Projected Costs'!K25 -> 978.03747 | J14: ='Attached-IEA2020Projected Costs'!L25 -> 996.84761 | K14: ='Attached-IEA2020Projected Costs'!M25 -> 1010.7255 | L14: =AVERAGE('Attached-IEA2020Projected Costs'!K22:K24) -> 1445.272 | M14: =AVERAGE('Attached-IEA2020Projected Costs'!L22:L24) -> 1473.0682 | N14: =AVERAGE('Attached-IEA2020Projected Costs'!M22:M24) -> 1493.5759 | BD14: NA | BE14: 20.053988 | BF14: 44.388986 | BG14: 99.396918 | BH14: 52.044407 | BI14: 110.66512 | BK14: - | BM14: =BE5+BE14 -> 321.70055 | BN14: =BF5+BF14 -> 712.07586 | BO14: =BG5+BG14 -> 1594.4979 | BP14: =BH5+BH14 -> 834.88202 | BQ14: =BI5+BI14 -> 1775.2592 | BR14: - | BS14: - | CP14: USA | CQ14: =CA5+CA26 -> 391.27375 | CR14: =CB5+CB26 -> 802.80225 | CS14: =CC5+CC26 -> 1885.3459 | CT14: =CD5+CD26 -> 1041.8132 | CU14: =CE5+CE26 -> 2124.4774
E15: Belgium | H15: ='Attached-IRENA2024 report'!J63 -> 965 | I15: ='Attached-IEA2020Projected Costs'!K12 -> 1006.2807 | J15: ='Attached-IEA2020Projected Costs'!L12 -> 1025.634 | K15: ='Attached-IEA2020Projected Costs'!M12 -> 1039.9126 | L15: =AVERAGE('Attached-IEA2020Projected Costs'!K9:K11) -> 1419.3349 | M15: =AVERAGE('Attached-IEA2020Projected Costs'!L9:L11) -> 1446.6323 | N15: =AVERAGE('Attached-IEA2020Projected Costs'!M9:M11) -> 1466.772 | BD15: Eurasia | BE15: 0.45185968 | BF15: 1.0894849 | BG15: 1.708326 | BH15: 1.2737416 | BI15: 3.0931668 | BK15: - | BM15: =BE6+BE15 -> 8.1277016 | BN15: =BF6+BF15 -> 19.596809 | BO15: =BG6+BG15 -> 30.728043 | BP15: =BH6+BH15 -> 22.911075 | BQ15: =BI6+BI15 -> 55.637486 | BR15: - | BS15: - | CP15: RU | CQ15: =CA6+CA27 -> 4.1748 | CR15: =CB6+CB27 -> 5.2371 | CS15: =CC6+CC27 -> 7.4849 | CT15: =CD6+CD27 -> 7.9333008 | CU15: =CE6+CE27 -> 18.977639
E16: Cyprus | H16: ='Attached-IRENA2024 report'!J64 -> 854 | V16: EU-27 | BD16: APJ | BE16: 42.602525 | BF16: 110.19465 | BG16: 228.6747 | BH16: 114.17732 | BI16: 248.15433 | BK16: - | BM16: =BE7+BE16 -> 1401.6014 | BN16: =BF7+BF16 -> 3625.3478 | BO16: =BG7+BG16 -> 7523.2812 | BP16: =BH7+BH16 -> 3756.3758 | BQ16: =BI7+BI16 -> 8164.1509 | BR16: - | BS16: - | CP16: CN | CQ16: =CA7+CA28 -> 523.0624 | CR16: =CB7+CB28 -> 1484.847 | CS16: =CC7+CC28 -> 3018.4416 | CT16: =CD7+CD28 -> 1518.9909 | CU16: =CE7+CE28 -> 3122.8582
E17: Slovakia | H17: ='Attached-IRENA2024 report'!J65 -> 844 | X17: Stated Policies (STEPS) | AD17: Announced Pledges (APS) | BD17: ME | BE17: 0.554 | BF17: 2.2131678 | BG17: 6.16882 | BH17: 2.562554 | BI17: 10.279657 | BK17: - | BM17: =BE8+BE17 -> 11.357 | BN17: =BF8+BF17 -> 45.36994 | BO17: =BG8+BG17 -> 141.0016 | BP17: =BH8+BH17 -> 52.532357 | BQ17: =BI8+BI17 -> 210.73297 | BR17: - | BS17: - | CP17: IN | CQ17: =CA8+CA29 -> 63.4959 | CR17: =CB8+CB29 -> 152.7168 | CS17: =CC8+CC29 -> 400.148 | CT17: =CD8+CD29 -> 164.35906 | CU17: =CE8+CE29 -> 481.85754
E18: Romania | H18: ='Attached-IRENA2024 report'!J67 -> 743 | V18: 2023 | X18: 2030 | Y18: 2035 | Z18: 2040 | AA18: 2045 | AB18: 2050 | AD18: 2030 | AE18: 2035 | AF18: 2040 | AG18: 2045 | AH18: 2050 | BD18: AF | BE18: 0.9372 | BF18: 2.7068026 | BG18: 6.31047 | BH18: 4.5505929 | BI18: 14.272229 | BK18: - | BM18: =BE9+BE18 -> 28.8828 | BN18: =BF9+BF18 -> 83.418736 | BO18: =BG9+BG18 -> 224.18775 | BP18: =BH9+BH18 -> 140.241 | BQ18: =BI9+BI18 -> 439.84414 | BR18: - | BS18: - | CP18: JP | CQ18: =CA9+CA30 -> 204.9632 | CR18: =CB9+CB30 -> 213.97475 | CS18: =CC9+CC30 -> 204.10715 | CT18: =CD9+CD30 -> 280.81377 | CU18: =CE9+CE30 -> 334.17336
E19: Latvia | H19: ='Attached-IRENA2024 report'!J68 -> 716 | V19: 266.93 | X19: 646.76 | Y19: 870.02 | Z19: 991.11 | AA19: 1055.84 | AB19: 1078.1 | AD19: 746.62 | AE19: 967.2 | AF19: 1050.68 | AG19: 1081.83 | AH19: 1091.41 | BD19: Global | BE19: 115.27104 | BF19: 276.12518 | BG19: 557.26241 | BH19: 298.33814 | BI19: 637.60927 | BJ19: 303.10103 | BK19: 670.8238 | BM19: =BE10+BE19 -> 1925.1988 | BN19: =BF10+BF19 -> 4611.7037 | BO19: =BG10+BG19 -> 9307.1161 | BP19: =BH10+BH19 -> 4982.6933 | BQ19: =BI10+BI19 -> 10649.029 | BR19: =BJ10+BJ19 -> 5062.2407 | BS19: =BK10+BK19 -> 11203.761 | CP19: ASEAN | CQ19: =CA10+CA31 -> 49.970199 | CR19: =CB10+CB31 -> 94.845563 | CS19: =CC10+CC31 -> 280.02546 | CT19: =CD10+CD31 -> 151.98309 | CU19: =CE10+CE31 -> 539.79316
E20: Estonia | H20: ='Attached-IRENA2024 report'!J69 -> 705 | BD20: 60% rooftop, 40% ground-mounted
E21: Poland | H21: ='Attached-IRENA2024 report'!J70 -> 700 | BD21: EUR | BE21: 23.231978 | BF21: 43.236777 | BG21: 61.702925 | BH21: 47.669721 | BI21: 65.694431 | BK21: - | BM21: =BE3+BE21 -> 324.50335 | BN21: =BF3+BF21 -> 603.92959 | BO21: =BG3+BG21 -> 861.86403 | BP21: =BH3+BH21 -> 665.84879 | BQ21: =BI3+BI21 -> 917.61722 | BR21: - | BS21: - | CP21: EU-27 | CQ21: =CA3+CA34 -> 317.11284 | CR21: =CB3+CB34 -> 486.36352 | CS21: =CC3+CC34 -> 595.1112 | CT21: =CD3+CD34 -> 636.95692 | CU21: =CE3+CE34 -> 823.97909
E22: Ireland | H22: ='Attached-IRENA2024 report'!J71 -> 686 | V22: Russia | BD22: CSA | BE22: -5.4393983 | BF22: -9.6745073 | BG22: -16.199189 | BH22: -12.962457 | BI22: -27.240361 | BK22: - | BM22: =BE4+BE22 -> 46.798197 | BN22: =BF4+BF22 -> 83.235217 | BO22: =BG4+BG22 -> 139.37072 | BP22: =BH4+BH22 -> 111.5233 | BQ22: =BI4+BI22 -> 234.36412 | BR22: - | BS22: - | CP22: BR | CQ22: =CA4+CA35 -> 26.87904 | CR22: =CB4+CB35 -> 36.17314 | CS22: =CC4+CC35 -> 43.47648 | CT22: =CD4+CD35 -> 59.932578 | CU22: =CE4+CE35 -> 89.840676
E23: Luxembourg | H23: ='Attached-IRENA2024 report'!J72 -> 684 | X23: Stated Policies (STEPS) | AD23: Announced Pledges (APS) | BD23: NA | BE23: 40.107977 | BF23: 88.777972 | BG23: 198.79384 | BH23: 104.08881 | BI23: 221.33023 | BK23: - | BM23: =BE5+BE23 -> 341.75454 | BN23: =BF5+BF23 -> 756.46485 | BO23: =BG5+BG23 -> 1693.8949 | BP23: =BH5+BH23 -> 886.92643 | BQ23: =BI5+BI23 -> 1885.9244 | BR23: - | BS23: - | BZ23: 50-PCT | CP23: USA | CQ23: =CA5+CA36 -> 431.5045 | CR23: =CB5+CB36 -> 885.61764 | CS23: =CC5+CC36 -> 2080.5124 | CT23: =CD5+CD36 -> 1148.9324 | CU23: =CE5+CE36 -> 2342.9161
E24: Austria | H24: ='Attached-IRENA2024 report'!J73 -> 678 | I24: ='Attached-IEA2020Projected Costs'!K6 -> 729.55348 | J24: ='Attached-IEA2020Projected Costs'!L6 -> 743.58464 | K24: ='Attached-IEA2020Projected Costs'!M6 -> 753.93667 | L24: ='Attached-IEA2020Projected Costs'!K6 -> 729.55348 | M24: ='Attached-IEA2020Projected Costs'!L6 -> 743.58464 | N24: ='Attached-IEA2020Projected Costs'!M6 -> 753.93667 | V24: 2023 | X24: 2030 | Y24: 2035 | Z24: 2040 | AA24: 2045 | AB24: 2050 | AD24: 2030 | AE24: 2035 | AF24: 2040 | AG24: 2045 | AH24: 2050 | BD24: Eurasia | BE24: 0.90371937 | BF24: 2.1789698 | BG24: 3.4166519 | BH24: 2.5474831 | BI24: 6.1863336 | BK24: - | BM24: =BE6+BE24 -> 8.5795613 | BN24: =BF6+BF24 -> 20.686294 | BO24: =BG6+BG24 -> 32.436369 | BP24: =BH6+BH24 -> 24.184817 | BQ24: =BI6+BI24 -> 58.730652 | BR24: - | BS24: - | BZ24: European Union | CA24: 8.80869 | CB24: 14.22872 | CC24: 18.3277 | CD24: 17.693248 | CE24: 22.888308 | CP24: RU | CQ24: =CA6+CA37 -> 4.2813 | CR24: =CB6+CB37 -> 5.382 | CS24: =CC6+CC37 -> 7.68674 | CT24: =CD6+CD37 -> 8.1356809 | CU24: =CE6+CE37 -> 19.461763
E25: Czech Republic | H25: ='Attached-IRENA2024 report'!J74 -> 663 | V25: 2.13 | X25: 4.14 | Y25: 4.94 | Z25: 6.01 | AA25: 7.15 | AB25: 8.41 | AD25: 5.49 | AE25: 8.85 | AF25: 12.61 | AG25: 16.55 | AH25: 19.87 | BD25: APJ | BE25: 85.205049 | BF25: 220.3893 | BG25: 457.34941 | BH25: 228.35465 | BI25: 496.30865 | BK25: - | BM25: =BE7+BE25 -> 1444.2039 | BN25: =BF7+BF25 -> 3735.5425 | BO25: =BG7+BG25 -> 7751.9559 | BP25: =BH7+BH25 -> 3870.5531 | BQ25: =BI7+BI25 -> 8412.3052 | BR25: - | BS25: - | BZ25: Brazil | CA25: -0.70516 | CB25: -1.00991 | CC25: -1.05672 | CD25: -1.5723053 | CE25: -2.3569313 | CP25: CN | CQ25: =CA7+CA38 -> 528.56832 | CR25: =CB7+CB38 -> 1501.164 | CS25: =CC7+CC38 -> 3056.1721 | CT25: =CD7+CD38 -> 1534.9803 | CU25: =CE7+CE38 -> 3155.7304
E26: Bulgaria | H26: ='Attached-IRENA2024 report'!J75 -> 659 | BD26: ME | BE26: 1.108 | BF26: 4.4263356 | BG26: 12.33764 | BH26: 5.125108 | BI26: 20.559314 | BK26: - | BM26: =BE8+BE26 -> 11.911 | BN26: =BF8+BF26 -> 47.583108 | BO26: =BG8+BG26 -> 147.17042 | BP26: =BH8+BH26 -> 55.094911 | BQ26: =BI8+BI26 -> 221.01263 | BR26: - | BS26: - | BZ26: United States | CA26: 40.23075 | CB26: 82.81539 | CC26: 195.16646 | CD26: 107.11919 | CE26: 218.43867 | CP26: IN | CQ26: =CA8+CA39 -> 64.06452 | CR26: =CB8+CB39 -> 154.20672 | CS26: =CC8+CC39 -> 403.0062 | CT26: =CD8+CD39 -> 165.83093 | CU26: =CE8+CE39 -> 486.17269
E27: Denmark | I27: =AVERAGE('Attached-IEA2020Projected Costs'!K17:K18) -> 587.43464 | J27: =AVERAGE('Attached-IEA2020Projected Costs'!L17:L18) -> 598.7325 | K27: =AVERAGE('Attached-IEA2020Projected Costs'!M17:M18) -> 607.06792 | L27: =AVERAGE('Attached-IEA2020Projected Costs'!K15:K16) -> 1026.7533 | M27: =AVERAGE('Attached-IEA2020Projected Costs'!L15:L16) -> 1046.5004 | N27: =AVERAGE('Attached-IEA2020Projected Costs'!M15:M16) -> 1061.0695 | BD27: AF | BE27: 1.8744 | BF27: 5.4136053 | BG27: 12.62094 | BH27: 9.1011857 | BI27: 28.544458 | BK27: - | BM27: =BE9+BE27 -> 29.82 | BN27: =BF9+BF27 -> 86.125538 | BO27: =BG9+BG27 -> 230.49822 | BP27: =BH9+BH27 -> 144.79159 | BQ27: =BI9+BI27 -> 454.11637 | BR27: - | BS27: - | BZ27: Russia | CA27: 0.1065 | CB27: 0.1449 | CC27: 0.20184 | CD27: 0.20238012 | CE27: 0.48412346 | CP27: JP | CQ27: =CA9+CA40 -> 204.63872 | CR27: =CB9+CB40 -> 214.4822 | CS27: =CC9+CC40 -> 205.1647 | CT27: =CD9+CD40 -> 280.36921 | CU27: =CE9+CE40 -> 333.64432
E28: Norway | L28: ='Attached-IEA2020Projected Costs'!K40 -> 998.35392 | M28: ='Attached-IEA2020Projected Costs'!L40 -> 1017.5548 | N28: ='Attached-IEA2020Projected Costs'!M40 -> 1031.721 | V28: CN | BD28: Global | BE28: 230.54207 | BF28: 552.25036 | BG28: 1114.5248 | BH28: 596.67628 | BI28: 1275.2185 | BJ28: 606.20205 | BK28: 1341.6476 | BM28: =BE10+BE28 -> 2040.4698 | BN28: =BF10+BF28 -> 4887.8289 | BO28: =BG10+BG28 -> 9864.3785 | BP28: =BH10+BH28 -> 5281.0315 | BQ28: =BI10+BI28 -> 11286.638 | BR28: =BJ10+BJ28 -> 5365.3417 | BS28: =BK10+BK28 -> 11874.585 | BZ28: China | CA28: 5.50592 | CB28: 16.317 | CC28: 37.73052 | CD28: 15.989378 | CE28: 32.872191 | CP28: ASEAN | CQ28: =CA10+CA41 -> 50.292761 | CR28: =CB10+CB41 -> 95.457799 | CS28: =CC10+CC41 -> 281.83304 | CT28: =CD10+CD41 -> 152.96415 | CU28: =CE10+CE41 -> 543.27757
E29: Croatia | X29: Stated Policies (STEPS) | AD29: Announced Pledges (APS) | BD29: 70% rooftop, 30% ground-mounted | BZ29: India | CA29: 0.56862 | CB29: 1.48992 | CC29: 2.8582 | CD29: 1.4718721 | CE29: 4.3151422
D30: South America | E30: Chile | H30: ='Attached-IRENA2024 report'!J50 -> 953.80679 | V30: 2023 | X30: 2030 | Y30: 2035 | Z30: 2040 | AA30: 2045 | AB30: 2050 | AD30: 2030 | AE30: 2035 | AF30: 2040 | AG30: 2045 | AH30: 2050 | BD30: EUR | BE30: 34.847966 | BF30: 64.855165 | BG30: 92.554387 | BH30: 71.504582 | BI30: 98.541646 | BK30: - | BM30: =BE3+BE30 -> 336.11934 | BN30: =BF3+BF30 -> 625.54798 | BO30: =BG3+BG30 -> 892.71549 | BP30: =BH3+BH30 -> 689.68365 | BQ30: =BI3+BI30 -> 950.46444 | BR30: - | BS30: - | BZ30: Japan | CA30: -0.32448 | CB30: 0.50745 | CC30: 1.05755 | CD30: -0.44456005 | CE30: -0.52903434 | CP30: EU-27 | CQ30: =CA3+CA44 -> 325.92153 | CR30: =CB3+CB44 -> 500.59224 | CS30: =CC3+CC44 -> 613.4389 | CT30: =CD3+CD44 -> 654.65017 | CU30: =CE3+CE44 -> 846.8674
E31: Argentina | H31: ='Attached-IRENA2024 report'!J53 -> 830 | V31: 688.24 | X31: 3263.4 | Y31: 5343.62 | Z31: 7290.94 | AA31: 8887.57 | AB31: 9432.63 | AD31: 3315.59 | AE31: 5433.22 | AF31: 7415.35 | AG31: 9040.46 | AH31: 9597.53 | BD31: CSA | BE31: -8.1590974 | BF31: -14.511761 | BG31: -24.298783 | BH31: -19.443686 | BI31: -40.860542 | BK31: - | BM31: =BE4+BE31 -> 44.078497 | BN31: =BF4+BF31 -> 78.397963 | BO31: =BG4+BG31 -> 131.27112 | BP31: =BH4+BH31 -> 105.04207 | BQ31: =BI4+BI31 -> 220.74394 | BR31: - | BS31: - | BZ31: Southeast Asia | CA31: 0.32256186 | CB31: 0.61223613 | CC31: 1.807588 | CD31: 0.98106367 | CE31: 3.4844105 | CP31: BR | CQ31: =CA4+CA45 -> 26.17388 | CR31: =CB4+CB45 -> 35.16323 | CS31: =CC4+CC45 -> 42.41976 | CT31: =CD4+CD45 -> 58.360272 | CU31: =CE4+CE45 -> 87.483745
E32: Brazil | F32: =Attached_WEO2023!B18 -> 730 | G32: =Attached_WEO2023!F18 -> 560 | H32: ='Attached-IRENA2024 report'!J48 -> 726.98559 | I32: ='Attached-IEA2020Projected Costs'!K60 -> 1215.2033 | J32: ='Attached-IEA2020Projected Costs'!L60 -> 1238.5747 | K32: ='Attached-IEA2020Projected Costs'!M60 -> 1255.8179 | O32: ='Attached-DIB_GNESTE_Solar_Power'!V134 -> 1382.1652 | BD32: NA | BE32: 60.161965 | BF32: 133.16696 | BG32: 298.19075 | BH32: 156.13322 | BI32: 331.99535 | BK32: - | BM32: =BE5+BE32 -> 361.80853 | BN32: =BF5+BF32 -> 800.85383 | BO32: =BG5+BG32 -> 1793.2918 | BP32: =BH5+BH32 -> 938.97084 | BQ32: =BI5+BI32 -> 1996.5895 | BR32: - | BS32: - | CP32: USA | CQ32: =CA5+CA46 -> 471.73525 | CR32: =CB5+CB46 -> 968.43303 | CS32: =CC5+CC46 -> 2275.6788 | CT32: =CD5+CD46 -> 1256.0516 | CU32: =CE5+CE46 -> 2561.3547
E33: South America | O33: ='Attached-DIB_GNESTE_Solar_Power'!AA338 -> 819.85934 | BD33: Eurasia | BE33: 1.3555791 | BF33: 3.2684546 | BG33: 5.1249779 | BH33: 3.8212247 | BI33: 9.2795004 | BK33: - | BM33: =BE6+BE33 -> 9.0314209 | BN33: =BF6+BF33 -> 21.775779 | BO33: =BG6+BG33 -> 34.144695 | BP33: =BH6+BH33 -> 25.458558 | BQ33: =BI6+BI33 -> 61.823819 | BR33: - | BS33: - | CP33: RU | CQ33: =CA6+CA47 -> 4.3878 | CR33: =CB6+CB47 -> 5.5269 | CS33: =CC6+CC47 -> 7.88858 | CT33: =CD6+CD47 -> 8.338061 | CU33: =CE6+CE47 -> 19.945886
D34: North America | E34: United States | F34: =Attached_WEO2023!B13 -> 1110 | G34: =Attached_WEO2023!F13 -> 3460 | H34: ='Attached-IRENA2024 report'!J42 -> 1108.5304 | I34: =AVERAGE('Attached-IEA2020Projected Costs'!K51:K55) -> 1087.637 | J34: =AVERAGE('Attached-IEA2020Projected Costs'!L51:L55) -> 1108.555 | K34: =AVERAGE('Attached-IEA2020Projected Costs'!M51:M55) -> 1123.9881 | L34: =AVERAGE('Attached-IEA2020Projected Costs'!K41:K50) -> 1789.2317 | M34: =AVERAGE('Attached-IEA2020Projected Costs'!L41:L50) -> 1823.6432 | N34: =AVERAGE('Attached-IEA2020Projected Costs'!M41:M50) -> 1849.0316 | O34: =AVERAGE('Attached-DIB_GNESTE_Solar_Power'!V15,'Attached-DIB_GNESTE_Solar_Power'!Z17:Z310,'Attached-DIB_GNESTE_Solar_Power'!AB313:AB315,'Attached-DIB_GNESTE_Solar_Power'!Z319,'Attached-DIB_GNESTE_Solar_Power'!X325,'Attached-DIB_GNESTE_Solar_Power'!Y326,'Attached-DIB_GNESTE_Solar_Power'!X331,'Attached-DIB_GNESTE_Solar_Power'!Y332) -> 1349.0303 | BD34: APJ | BE34: 127.80757 | BF34: 330.58395 | BG34: 686.02411 | BH34: 342.53197 | BI34: 744.46298 | BK34: - | BM34: =BE7+BE34 -> 1486.8064 | BN34: =BF7+BF34 -> 3845.7371 | BO34: =BG7+BG34 -> 7980.6306 | BP34: =BH7+BH34 -> 3984.7304 | BQ34: =BI7+BI34 -> 8660.4595 | BR34: - | BS34: - | BZ34: 40-pct | CA34: 17.61738 | CB34: 28.45744 | CC34: 36.6554 | CD34: 35.386496 | CE34: 45.776616 | CP34: CN | CQ34: =CA7+CA48 -> 534.07424 | CR34: =CB7+CB48 -> 1517.481 | CS34: =CC7+CC48 -> 3093.9026 | CT34: =CD7+CD48 -> 1550.9697 | CU34: =CE7+CE48 -> 3188.6025
E35: Canada | H35: ='Attached-IRENA2024 report'!J38 -> 1336.5221 | I35: =AVERAGE('Attached-IEA2020Projected Costs'!K13:K14) -> 1328.7693 | J35: =AVERAGE('Attached-IEA2020Projected Costs'!L13:L14) -> 1354.3249 | K35: =AVERAGE('Attached-IEA2020Projected Costs'!M13:M14) -> 1373.1795 | BD35: ME | BE35: 1.662 | BF35: 6.6395034 | BG35: 18.50646 | BH35: 7.687662 | BI35: 30.838971 | BK35: - | BM35: =BE8+BE35 -> 12.465 | BN35: =BF8+BF35 -> 49.796275 | BO35: =BG8+BG35 -> 153.33924 | BP35: =BH8+BH35 -> 57.657465 | BQ35: =BI8+BI35 -> 231.29228 | BR35: - | BS35: - | CA35: -1.41032 | CB35: -2.01982 | CC35: -2.11344 | CD35: -3.1446106 | CE35: -4.7138626 | CP35: IN | CQ35: =CA8+CA49 -> 64.63314 | CR35: =CB8+CB49 -> 155.69664 | CS35: =CC8+CC49 -> 405.8644 | CT35: =CD8+CD49 -> 167.3028 | CU35: =CE8+CE49 -> 490.48783
E36: Mexico | H36: ='Attached-IRENA2024 report'!J40 -> 1049.5172 | O36: ='Attached-DIB_GNESTE_Solar_Power'!V137 -> 990.405 | V36: ASEAN | BD36: AF | BE36: 2.8116 | BF36: 8.1204079 | BG36: 18.93141 | BH36: 13.651779 | BI36: 42.816687 | BK36: - | BM36: =BE9+BE36 -> 30.7572 | BN36: =BF9+BF36 -> 88.832341 | BO36: =BG9+BG36 -> 236.80869 | BP36: =BH9+BH36 -> 149.34218 | BQ36: =BI9+BI36 -> 468.3886 | BR36: - | BS36: - | CA36: 80.4615 | CB36: 165.63078 | CC36: 390.33292 | CD36: 214.23837 | CE36: 436.87735 | CP36: JP | CQ36: =CA9+CA50 -> 204.31424 | CR36: =CB9+CB50 -> 214.98965 | CS36: =CC9+CC50 -> 206.22225 | CT36: =CD9+CD50 -> 279.92465 | CU36: =CE9+CE50 -> 333.11529
E37: North America | O37: ='Attached-DIB_GNESTE_Solar_Power'!AA337 -> 936.56791 | X37: Stated Policies (STEPS) | AD37: Announced Pledges (APS) | BD37: Global | BE37: 345.81311 | BF37: 828.37554 | BG37: 1671.7872 | BH37: 895.01442 | BI37: 1912.8278 | BJ37: 909.30308 | BK37: 2012.4714 | BM37: =BE10+BE37 -> 2155.7409 | BN37: =BF10+BF37 -> 5163.954 | BO37: =BG10+BG37 -> 10421.641 | BP37: =BH10+BH37 -> 5579.3696 | BQ37: =BI10+BI37 -> 11924.247 | BR37: =BJ10+BJ37 -> 5668.4427 | BS37: =BK10+BK37 -> 12545.409 | CA37: 0.213 | CB37: 0.2898 | CC37: 0.40368 | CD37: 0.40476024 | CE37: 0.96824691 | CP37: ASEAN | CQ37: =CA10+CA51 -> 50.615323 | CR37: =CB10+CB51 -> 96.070036 | CS37: =CC10+CC51 -> 283.64063 | CT37: =CD10+CD51 -> 153.94522 | CU37: =CE10+CE51 -> 546.76199
D38: Eurasia | E38: Russia | F38: =Attached_WEO2023!B15 -> 1250 | G38: =Attached_WEO2023!F15 -> 1610 | H38: ='Attached-IRENA2024 report'!J83 -> 1248 | O38: ='Attached-DIB_GNESTE_Solar_Power'!AA341 -> 787.78925 | V38: 2023 | X38: 2030 | Y38: 2035 | Z38: 2040 | AA38: 2045 | AB38: 2050 | AD38: 2030 | AE38: 2035 | AF38: 2040 | AG38: 2045 | AH38: 2050 | BD38: 80% rooftop, 20% ground-mounted | CA38: 11.01184 | CB38: 32.634 | CC38: 75.46104 | CD38: 31.978756 | CE38: 65.744382
D39: Asia Pacific | E39: Japan | F39: =Attached_WEO2023!B14 -> 1880 | G39: =Attached_WEO2023!F14 -> 1850 | H39: ='Attached-IRENA2024 report'!J15 -> 1875.2399 | I39: ='Attached-IEA2020Projected Costs'!K34 -> 2035.9917 | J39: ='Attached-IEA2020Projected Costs'!L34 -> 2075.149 | K39: ='Attached-IEA2020Projected Costs'!M34 -> 2104.0388 | L39: ='Attached-IEA2020Projected Costs'!K33 -> 2367.4727 | M39: ='Attached-IEA2020Projected Costs'!L33 -> 2413.0052 | N39: ='Attached-IEA2020Projected Costs'!M33 -> 2446.5985 | V39: 32.13 | X39: 82.67 | Y39: 150.99 | Z39: 236.9 | AA39: 319.85 | AB39: 408.09 | AD39: 165.71 | AE39: 368.34 | AF39: 669.78 | AG39: 898.17 | AH39: 1074.26 | BD39: EUR | BE39: 46.463955 | BF39: 86.473553 | BG39: 123.40585 | BH39: 95.339442 | BI39: 131.38886 | BK39: - | BM39: =BE3+BE39 -> 347.73533 | BN39: =BF3+BF39 -> 647.16637 | BO39: =BG3+BG39 -> 923.56695 | BP39: =BH3+BH39 -> 713.51851 | BQ39: =BI3+BI39 -> 983.31165 | BR39: - | BS39: - | CA39: 1.13724 | CB39: 2.97984 | CC39: 5.7164 | CD39: 2.9437443 | CE39: 8.6302844 | CP39: EU-27 | CQ39: =CA3+CA54 -> 334.73022 | CR39: =CB3+CB54 -> 514.82096 | CS39: =CC3+CC54 -> 631.7666 | CT39: =CD3+CD54 -> 672.34342 | CU39: =CE3+CE54 -> 869.75571
E40: China | F40: =Attached_WEO2023!B16 -> 670 | G40: =Attached_WEO2023!F16 -> 750 | H40: ='Attached-IRENA2024 report'!J11 -> 671.12616 | I40: ='Attached-IEA2020Projected Costs'!K61 -> 741.29534 | J40: ='Attached-IEA2020Projected Costs'!L61 -> 755.55232 | K40: ='Attached-IEA2020Projected Costs'!M61 -> 766.07096 | O40: ='Attached-DIB_GNESTE_Solar_Power'!AA342 -> 694.64666 | BD40: CSA | BE40: -10.878797 | BF40: -19.349015 | BG40: -32.398378 | BH40: -25.924914 | BI40: -54.480722 | BK40: - | BM40: =BE4+BE40 -> 41.358798 | BN40: =BF4+BF40 -> 73.56071 | BO40: =BG4+BG40 -> 123.17153 | BP40: =BH4+BH40 -> 98.560838 | BQ40: =BI4+BI40 -> 207.12376 | BR40: - | BS40: - | CA40: -0.64896 | CB40: 1.0149 | CC40: 2.1151 | CD40: -0.88912011 | CE40: -1.0580687 | CP40: BR | CQ40: =CA4+CA55 -> 25.46872 | CR40: =CB4+CB55 -> 34.15332 | CS40: =CC4+CC55 -> 41.36304 | CT40: =CD4+CD55 -> 56.787967 | CU40: =CE4+CE55 -> 85.126814
E41: India | F41: =Attached_WEO2023!B17 -> 710 | G41: =Attached_WEO2023!F17 -> 780 | H41: ='Attached-IRENA2024 report'!J13 -> 711.32819 | I41: ='Attached-IEA2020Projected Costs'!K62 -> 638.03526 | J41: ='Attached-IEA2020Projected Costs'!L62 -> 650.30629 | K41: ='Attached-IEA2020Projected Costs'!M62 -> 659.35972 | O41: =AVERAGE('Attached-DIB_GNESTE_Solar_Power'!W25,'Attached-DIB_GNESTE_Solar_Power'!V135,'Attached-DIB_GNESTE_Solar_Power'!AA343) -> 670.57179 | BD41: NA | BE41: 80.215954 | BF41: 177.55594 | BG41: 397.58767 | BH41: 208.17763 | BI41: 442.66046 | BK41: - | BM41: =BE5+BE41 -> 381.86251 | BN41: =BF5+BF41 -> 845.24282 | BO41: =BG5+BG41 -> 1892.6887 | BP41: =BH5+BH41 -> 991.01525 | BQ41: =BI5+BI41 -> 2107.2546 | BR41: - | BS41: - | CA41: 0.64512371 | CB41: 1.2244723 | CC41: 3.615176 | CD41: 1.9621273 | CE41: 6.968821 | CP41: USA | CQ41: =CA5+CA56 -> 511.966 | CR41: =CB5+CB56 -> 1051.2484 | CS41: =CC5+CC56 -> 2470.8453 | CT41: =CD5+CD56 -> 1363.1707 | CU41: =CE5+CE56 -> 2779.7934
E42: Republic of Korea | H42: ='Attached-IRENA2024 report'!J17 -> 1205.2601 | I42: ='Attached-IEA2020Projected Costs'!K36 -> 1244.0419 | J42: ='Attached-IEA2020Projected Costs'!L36 -> 1267.9679 | K42: ='Attached-IEA2020Projected Costs'!M36 -> 1285.6203 | L42: ='Attached-IEA2020Projected Costs'!K35 -> 1258.5589 | M42: ='Attached-IEA2020Projected Costs'!L35 -> 1282.7641 | N42: ='Attached-IEA2020Projected Costs'!M35 -> 1300.6225 | BD42: Eurasia | BE42: 1.8074387 | BF42: 4.3579395 | BG42: 6.8333039 | BH42: 5.0949662 | BI42: 12.372667 | BK42: - | BM42: =BE6+BE42 -> 9.4832806 | BN42: =BF6+BF42 -> 22.865264 | BO42: =BG6+BG42 -> 35.853021 | BP42: =BH6+BH42 -> 26.7323 | BQ42: =BI6+BI42 -> 64.916986 | BR42: - | BS42: - | CP42: RU | CQ42: =CA6+CA57 -> 4.4943 | CR42: =CB6+CB57 -> 5.6718 | CS42: =CC6+CC57 -> 8.09042 | CT42: =CD6+CD57 -> 8.5404411 | CU42: =CE6+CE57 -> 20.43001
E43: Australia | H43: ='Attached-IRENA2024 report'!J45 -> 988.62812 | I43: ='Attached-IEA2020Projected Costs'!K7 -> 895.14787 | J43: ='Attached-IEA2020Projected Costs'!L7 -> 912.36383 | K43: ='Attached-IEA2020Projected Costs'!M7 -> 925.06556 | O43: =AVERAGE('Attached-DIB_GNESTE_Solar_Power'!AA19:AA21) -> 932.2705 | V43: India | BD43: APJ | BE43: 170.4101 | BF43: 440.7786 | BG43: 914.69881 | BH43: 456.70929 | BI43: 992.6173 | BK43: - | BM43: =BE7+BE43 -> 1529.4089 | BN43: =BF7+BF43 -> 3955.9318 | BO43: =BG7+BG43 -> 8209.3053 | BP43: =BH7+BH43 -> 4098.9077 | BQ43: =BI7+BI43 -> 8908.6139 | BR43: - | BS43: - | CP43: CN | CQ43: =CA7+CA58 -> 539.58016 | CR43: =CB7+CB58 -> 1533.798 | CS43: =CC7+CC58 -> 3131.6332 | CT43: =CD7+CD58 -> 1566.9591 | CU43: =CE7+CE58 -> 3221.4747
E44: Indonesia | H44: ='Attached-IRENA2024 report'!J78 -> 798 | O44: =AVERAGE('Attached-DIB_GNESTE_Solar_Power'!V3:V4,'Attached-DIB_GNESTE_Solar_Power'!V133) -> 1913.4028 | X44: Stated Policies (STEPS) | AD44: Announced Pledges (APS) | BD44: ME | BE44: 2.216 | BF44: 8.8526712 | BG44: 24.67528 | BH44: 10.250216 | BI44: 41.118628 | BK44: - | BM44: =BE8+BE44 -> 13.019 | BN44: =BF8+BF44 -> 52.009443 | BO44: =BG8+BG44 -> 159.50806 | BP44: =BH8+BH44 -> 60.220019 | BQ44: =BI8+BI44 -> 241.57194 | BR44: - | BS44: - | BZ44: 30-pct | CA44: 26.42607 | CB44: 42.68616 | CC44: 54.9831 | CD44: 53.079743 | CE44: 68.664924 | CP44: IN | CQ44: =CA8+CA59 -> 65.20176 | CR44: =CB8+CB59 -> 157.18656 | CS44: =CC8+CC59 -> 408.7226 | CT44: =CD8+CD59 -> 168.77467 | CU44: =CE8+CE59 -> 494.80297
E45: Malaysia | O45: =AVERAGE('Attached-DIB_GNESTE_Solar_Power'!V5:V6) -> 2262.804 | V45: 2023 | X45: 2030 | Y45: 2035 | Z45: 2040 | AA45: 2045 | AB45: 2050 | AD45: 2030 | AE45: 2035 | AF45: 2040 | AG45: 2045 | AH45: 2050 | BD45: AF | BE45: 3.7488 | BF45: 10.827211 | BG45: 25.24188 | BH45: 18.202371 | BI45: 57.088915 | BK45: - | BM45: =BE9+BE45 -> 31.6944 | BN45: =BF9+BF45 -> 91.539144 | BO45: =BG9+BG45 -> 243.11916 | BP45: =BH9+BH45 -> 153.89278 | BQ45: =BI9+BI45 -> 482.66083 | BR45: - | BS45: - | CA45: -2.11548 | CB45: -3.02973 | CC45: -3.17016 | CD45: -4.7169158 | CE45: -7.070794 | CP45: JP | CQ45: =CA9+CA60 -> 203.98976 | CR45: =CB9+CB60 -> 215.4971 | CS45: =CC9+CC60 -> 207.2798 | CT45: =CD9+CD60 -> 279.48009 | CU45: =CE9+CE60 -> 332.58625
E46: Philippines | O46: =AVERAGE('Attached-DIB_GNESTE_Solar_Power'!V7:V8) -> 2229.198 | V46: 94.77 | X46: 372.48 | Y46: 645.98 | Z46: 934.4 | AA46: 1201.1 | AB46: 1429.1 | AD46: 385.32 | AE46: 767.79 | AF46: 1243.49 | AG46: 1584.94 | AH46: 1882.45 | BD46: Global | BE46: 461.08415 | BF46: 1104.5007 | BG46: 2229.0496 | BH46: 1193.3526 | BI46: 2550.4371 | BJ46: 1212.4041 | BK46: 2683.2952 | BM46: =BE10+BE46 -> 2271.0119 | BN46: =BF10+BF46 -> 5440.0792 | BO46: =BG10+BG46 -> 10978.903 | BP46: =BH10+BH46 -> 5877.7077 | BQ46: =BI10+BI46 -> 12561.857 | BR46: =BJ10+BJ46 -> 5971.5438 | BS46: =BK10+BK46 -> 13216.233 | CA46: 120.69225 | CB46: 248.44617 | CC46: 585.49938 | CD46: 321.35756 | CE46: 655.31602 | CP46: ASEAN | CQ46: =CA10+CA61 -> 50.937884 | CR46: =CB10+CB61 -> 96.682272 | CS46: =CC10+CC61 -> 285.44822 | CT46: =CD10+CD61 -> 154.92628 | CU46: =CE10+CE61 -> 550.2464
E47: Thailand | O47: =AVERAGE('Attached-DIB_GNESTE_Solar_Power'!V136) -> 1108.1532 | BD47: 90% rooftop, 10% ground-mounted | CA47: 0.3195 | CB47: 0.4347 | CC47: 0.60552 | CD47: 0.60714037 | CE47: 1.4523704
E48: Asia | O48: ='Attached-DIB_GNESTE_Solar_Power'!V11 -> 2254.9626 | BD48: EUR | BE48: 58.079944 | BF48: 108.09194 | BG48: 154.25731 | BH48: 119.1743 | BI48: 164.23608 | BK48: - | BM48: =BE3+BE48 -> 359.35132 | BN48: =BF3+BF48 -> 668.78476 | BO48: =BG3+BG48 -> 954.41841 | BP48: =BH3+BH48 -> 737.35337 | BQ48: =BI3+BI48 -> 1016.1589 | BR48: - | BS48: - | CA48: 16.51776 | CB48: 48.951 | CC48: 113.19156 | CD48: 47.968134 | CE48: 98.616574 | CP48: EU-27 | CQ48: =CA3+CA64 -> 343.53891 | CR48: =CB3+CB64 -> 529.04968 | CS48: =CC3+CC64 -> 650.0943 | CT48: =CD3+CD64 -> 690.03666 | CU48: =CE3+CE64 -> 892.64401
E49: Southeast Asia | O49: ='Attached-DIB_GNESTE_Solar_Power'!AA344 -> 718.76686 | BD49: CSA | BE49: -13.598496 | BF49: -24.186268 | BG49: -40.497972 | BH49: -32.406143 | BI49: -68.100903 | BK49: - | BM49: =BE4+BE49 -> 38.639099 | BN49: =BF4+BF49 -> 68.723456 | BO49: =BG4+BG49 -> 115.07193 | BP49: =BH4+BH49 -> 92.07961 | BQ49: =BI4+BI49 -> 193.50358 | BR49: - | BS49: - | CA49: 1.70586 | CB49: 4.46976 | CC49: 8.5746 | CD49: 4.4156164 | CE49: 12.945427 | CP49: BR | CQ49: =CA4+CA65 -> 24.76356 | CR49: =CB4+CB65 -> 33.14341 | CS49: =CC4+CC65 -> 40.30632 | CT49: =CD4+CD65 -> 55.215662 | CU49: =CE4+CE65 -> 82.769882
E50: OECD Asia & Oceania | O50: ='Attached-DIB_GNESTE_Solar_Power'!AA345 -> 922.20862 | BD50: NA | BE50: 100.26994 | BF50: 221.94493 | BG50: 496.98459 | BH50: 260.22204 | BI50: 553.32558 | BK50: - | BM50: =BE5+BE50 -> 401.9165 | BN50: =BF5+BF50 -> 889.6318 | BO50: =BG5+BG50 -> 1992.0856 | BP50: =BH5+BH50 -> 1043.0597 | BQ50: =BI5+BI50 -> 2217.9197 | BR50: - | BS50: - | CA50: -0.97344 | CB50: 1.52235 | CC50: 3.17265 | CD50: -1.3336802 | CE50: -1.587103 | CP50: USA | CQ50: =CA5+CA66 -> 552.19675 | CR50: =CB5+CB66 -> 1134.0638 | CS50: =CC5+CC66 -> 2666.0117 | CT50: =CD5+CD66 -> 1470.2899 | CU50: =CE5+CE66 -> 2998.2321
D51: Global | H51: ='Attached-IRENA2024 report'!AB11 -> 757.68783 | O51: =AVERAGE('Attached-DIB_GNESTE_Solar_Power'!W76:W322) -> 918.0296 | V51: Japan | BD51: Eurasia | BE51: 2.2592984 | BF51: 5.4474244 | BG51: 8.5416299 | BH51: 6.3687078 | BI51: 15.465834 | BK51: - | BM51: =BE6+BE51 -> 9.9351403 | BN51: =BF6+BF51 -> 23.954749 | BO51: =BG6+BG51 -> 37.561347 | BP51: =BH6+BH51 -> 28.006041 | BQ51: =BI6+BI51 -> 68.010153 | BR51: - | BS51: - | CA51: 0.96768557 | CB51: 1.8367084 | CC51: 5.4227639 | CD51: 2.943191 | CE51: 10.453231 | CP51: RU | CQ51: =CA6+CA67 -> 4.6008 | CR51: =CB6+CB67 -> 5.8167 | CS51: =CC6+CC67 -> 8.29226 | CT51: =CD6+CD67 -> 8.7428213 | CU51: =CE6+CE67 -> 20.914133
X52: Stated Policies (STEPS) | AD52: Announced Pledges (APS) | BD52: APJ | BE52: 213.01262 | BF52: 550.97325 | BG52: 1143.3735 | BH52: 570.88662 | BI52: 1240.7716 | BK52: - | BM52: =BE7+BE52 -> 1572.0115 | BN52: =BF7+BF52 -> 4066.1264 | BO52: =BG7+BG52 -> 8437.98 | BP52: =BH7+BH52 -> 4213.0851 | BQ52: =BI7+BI52 -> 9156.7682 | BR52: - | BS52: - | CP52: CN | CQ52: =CA7+CA68 -> 545.08608 | CR52: =CB7+CB68 -> 1550.115 | CS52: =CC7+CC68 -> 3169.3637 | CT52: =CD7+CD68 -> 1582.9484 | CU52: =CE7+CE68 -> 3254.3469
V53: 2023 | X53: 2030 | Y53: 2035 | Z53: 2040 | AA53: 2045 | AB53: 2050 | AD53: 2030 | AE53: 2035 | AF53: 2040 | AG53: 2045 | AH53: 2050 | BD53: ME | BE53: 2.77 | BF53: 11.065839 | BG53: 30.8441 | BH53: 12.81277 | BI53: 51.398285 | BK53: - | BM53: =BE8+BE53 -> 13.573 | BN53: =BF8+BF53 -> 54.222611 | BO53: =BG8+BG53 -> 165.67688 | BP53: =BH8+BH53 -> 62.782573 | BQ53: =BI8+BI53 -> 251.8516 | BR53: - | BS53: - | CP53: IN | CQ53: =CA8+CA69 -> 65.77038 | CR53: =CB8+CB69 -> 158.67648 | CS53: =CC8+CC69 -> 411.5808 | CT53: =CD8+CD69 -> 170.24654 | CU53: =CE8+CE69 -> 499.11811
V54: 108.16 | X54: 169.15 | Y54: 199.96 | Z54: 210.54 | AA54: 211.48 | AB54: 211.51 | AD54: 172.08 | AE54: 204.21 | AF54: 219.15 | AG54: 222.29 | AH54: 222.41 | BD54: AF | BE54: 4.686 | BF54: 13.534013 | BG54: 31.55235 | BH54: 22.752964 | BI54: 71.361144 | BK54: - | BM54: =BE9+BE54 -> 32.6316 | BN54: =BF9+BF54 -> 94.245946 | BO54: =BG9+BG54 -> 249.42963 | BP54: =BH9+BH54 -> 158.44337 | BQ54: =BI9+BI54 -> 496.93306 | BR54: - | BS54: - | BZ54: 20-pct | CA54: 35.23476 | CB54: 56.91488 | CC54: 73.3108 | CD54: 70.772991 | CE54: 91.553232 | CP54: JP | CQ54: =CA9+CA70 -> 203.66528 | CR54: =CB9+CB70 -> 216.00455 | CS54: =CC9+CC70 -> 208.33735 | CT54: =CD9+CD70 -> 279.03553 | CU54: =CE9+CE70 -> 332.05722
BD55: Global | BE55: 576.35518 | BF55: 1380.6259 | BG55: 2786.3121 | BH55: 1491.6907 | BI55: 3188.0464 | BJ55: 1515.5051 | BK55: 3354.119 | BM55: =BE10+BE55 -> 2386.2829 | BN55: =BF10+BF55 -> 5716.2044 | BO55: =BG10+BG55 -> 11536.166 | BP55: =BH10+BH55 -> 6176.0459 | BQ55: =BI10+BI55 -> 13199.466 | BR55: =BJ10+BJ55 -> 6274.6448 | BS55: =BK10+BK55 -> 13887.056 | CA55: -2.82064 | CB55: -4.03964 | CC55: -4.22688 | CD55: -6.2892211 | CE55: -9.4277253 | CP55: ASEAN | CQ55: =CA10+CA71 -> 51.260446 | CR55: =CB10+CB71 -> 97.294508 | CS55: =CC10+CC71 -> 287.25581 | CT55: =CD10+CD71 -> 155.90734 | CU55: =CE10+CE71 -> 553.73081
BD56: 100% rooftop (zero ground-mounted) | CA56: 160.923 | CB56: 331.26156 | CC56: 780.66584 | CD56: 428.47674 | CE56: 873.75469
BD57: EUR | BE57: 69.695933 | BF57: 129.71033 | BG57: 185.10877 | BH57: 143.00916 | BI57: 197.08329 | BK57: - | BM57: =BE3+BE57 -> 370.9673 | BN57: =BF3+BF57 -> 690.40315 | BO57: =BG3+BG57 -> 985.26988 | BP57: =BH3+BH57 -> 761.18823 | BQ57: =BI3+BI57 -> 1049.0061 | BR57: - | BS57: - | CA57: 0.426 | CB57: 0.5796 | CC57: 0.80736 | CD57: 0.80952049 | CE57: 1.9364938 | CP57: EU-27 | CQ57: =CA3+CA74 -> 352.3476 | CR57: =CB3+CB74 -> 543.2784 | CS57: =CC3+CC74 -> 668.422 | CT57: =CD3+CD74 -> 707.72991 | CU57: =CE3+CE74 -> 915.53232
B58: CAPEX | E58: Current-2023 | H58: SPS-2050 | K58: APS-2050 | N58: NZE-2050 | X58: Stated Policies (STEPS) | AD58: Announced Pledges (APS) | BD58: CSA | BE58: -16.318195 | BF58: -29.023522 | BG58: -48.597567 | BH58: -38.887371 | BI58: -81.721083 | BK58: - | BM58: =BE4+BE58 -> 35.9194 | BN58: =BF4+BF58 -> 63.886202 | BO58: =BG4+BG58 -> 106.97234 | BP58: =BH4+BH58 -> 85.598381 | BQ58: =BI4+BI58 -> 179.8834 | BR58: - | BS58: - | CA58: 22.02368 | CB58: 65.268 | CC58: 150.92208 | CD58: 63.957512 | CE58: 131.48876 | CP58: BR | CQ58: =CA4+CA75 -> 24.0584 | CR58: =CB4+CB75 -> 32.1335 | CS58: =CC4+CC75 -> 39.2496 | CT58: =CD4+CD75 -> 53.643357 | CU58: =CE4+CE75 -> 80.412951
E59: Large, ground-mounted PV | F59: Rooftop PV | G59: Differences | V59: 2023 | X59: 2030 | Y59: 2035 | Z59: 2040 | AA59: 2045 | AB59: 2050 | AD59: 2030 | AE59: 2035 | AF59: 2040 | AG59: 2045 | AH59: 2050 | BD59: NA | BE59: 120.32393 | BF59: 266.33391 | BG59: 596.38151 | BH59: 312.26644 | BI59: 663.99069 | BK59: - | BM59: =BE5+BE59 -> 421.97049 | BN59: =BF5+BF59 -> 934.02079 | BO59: =BG5+BG59 -> 2091.4825 | BP59: =BH5+BH59 -> 1095.1041 | BQ59: =BI5+BI59 -> 2328.5848 | BR59: - | BS59: - | CA59: 2.27448 | CB59: 5.95968 | CC59: 11.4328 | CD59: 5.8874886 | CE59: 17.260569 | CP59: USA | CQ59: =CA5+CA76 -> 592.4275 | CR59: =CB5+CB76 -> 1216.8792 | CS59: =CC5+CC76 -> 2861.1782 | CT59: =CD5+CD76 -> 1577.4091 | CU59: =CE5+CE76 -> 3216.6707
D60: =D83 -> European Union | E60: =E83 -> 750 | F60: =F83 -> 990 | G60: =F60-E60 -> 240 | H60: 340 | I60: 470 | J60: =I60-H60 -> 130 | K60: =H60*(0.8)^(LOG((AH19/AB19),2)) -> 338.65961 | L60: =I60*(0.8)^(LOG((AH19/AB19),2)) -> 468.1471 | M60: =L60-K60 -> 129.4875 | V60: 17.04 | X60: 81.43 | Y60: 152.02 | Z60: 220.44 | AA60: 285.15 | AB60: 332.13 | AD60: 175.19 | AE60: 347.96 | AF60: 535.77 | AG60: 737.89 | AH60: 945.41 | BD60: Eurasia | BE60: 2.7111581 | BF60: 6.5369093 | BG60: 10.249956 | BH60: 7.6424493 | BI60: 18.559001 | BK60: - | BM60: =BE6+BE60 -> 10.387 | BN60: =BF6+BF60 -> 25.044234 | BO60: =BG6+BG60 -> 39.269673 | BP60: =BH6+BH60 -> 29.279783 | BQ60: =BI6+BI60 -> 71.10332 | BR60: - | BS60: - | CA60: -1.29792 | CB60: 2.0298 | CC60: 4.2302 | CD60: -1.7782402 | CE60: -2.1161373 | CP60: RU | CQ60: =CA6+CA77 -> 4.7073 | CR60: =CB6+CB77 -> 5.9616 | CS60: =CC6+CC77 -> 8.4941 | CT60: =CD6+CD77 -> 8.9452014 | CU60: =CE6+CE77 -> 21.398257
D61: =D89 -> Brazil | E61: =E89 -> 730 | F61: =F89 -> 560 | G61: =F61-E61 -> -170 | H61: 330 | I61: 260 | J61: =I61-H61 -> -70 | K61: =H61*(0.8)^(LOG((AH13/AB13),2)) -> 282.04312 | L61: =I61*(0.8)^(LOG((AH13/AB13),2)) -> 222.21579 | M61: =L61-K61 -> -59.827329 | BD61: APJ | BE61: 255.61515 | BF61: 661.1679 | BG61: 1372.0482 | BH61: 685.06394 | BI61: 1488.926 | BK61: - | BM61: =BE7+BE61 -> 1614.614 | BN61: =BF7+BF61 -> 4176.3211 | BO61: =BG7+BG61 -> 8666.6547 | BP61: =BH7+BH61 -> 4327.2624 | BQ61: =BI7+BI61 -> 9404.9225 | BR61: - | BS61: - | CA61: 1.2902474 | CB61: 2.4489445 | CC61: 7.2303519 | CD61: 3.9242547 | CE61: 13.937642 | CP61: CN | CQ61: =CA7+CA78 -> 550.592 | CR61: =CB7+CB78 -> 1566.432 | CS61: =CC7+CC78 -> 3207.0942 | CT61: =CD7+CD78 -> 1598.9378 | CU61: =CE7+CE78 -> 3287.2191
D62: =D84 -> United States | E62: =E84 -> 1110 | F62: =F84 -> 3460 | G62: =F62-E62 -> 2350 | H62: 480 | I62: 1490 | J62: =I62-H62 -> 1010 | K62: =H62*(0.8)^(LOG((AH6/AB6),2)) -> 467.40863 | L62: =I62*(0.8)^(LOG((AH6/AB6),2)) -> 1450.9143 | M62: =L62-K62 -> 983.50566 | BD62: ME | BE62: 3.324 | BF62: 13.279007 | BG62: 37.01292 | BH62: 15.375324 | BI62: 61.677942 | BK62: - | BM62: =BE8+BE62 -> 14.127 | BN62: =BF8+BF62 -> 56.435779 | BO62: =BG8+BG62 -> 171.8457 | BP62: =BH8+BH62 -> 65.345127 | BQ62: =BI8+BI62 -> 262.13125 | BR62: - | BS62: - | CP62: IN | CQ62: =CA8+CA79 -> 66.339 | CR62: =CB8+CB79 -> 160.1664 | CS62: =CC8+CC79 -> 414.439 | CT62: =CD8+CD79 -> 171.71842 | CU62: =CE8+CE79 -> 503.43325
D63: =D86 -> Russia | E63: =E86 -> 1250 | F63: =F86 -> 1610 | G63: =F63-E63 -> 360 | H63: 580 | I63: 780 | J63: =I63-H63 -> 200 | K63: =H63*(0.8)^(LOG((AH25/AB25),2)) -> 439.76376 | L63: =I63*(0.8)^(LOG((AH25/AB25),2)) -> 591.40644 | M63: =L63-K63 -> 151.64268 | BD63: AF | BE63: 5.6232 | BF63: 16.240816 | BG63: 37.86282 | BH63: 27.303557 | BI63: 85.633373 | BK63: - | BM63: =BE9+BE63 -> 33.5688 | BN63: =BF9+BF63 -> 96.952749 | BO63: =BG9+BG63 -> 255.7401 | BP63: =BH9+BH63 -> 162.99396 | BQ63: =BI9+BI63 -> 511.20529 | BR63: - | BS63: - | CP63: JP | CQ63: =CA9+CA80 -> 203.3408 | CR63: =CB9+CB80 -> 216.512 | CS63: =CC9+CC80 -> 209.3949 | CT63: =CD9+CD80 -> 278.59097 | CU63: =CE9+CE80 -> 331.52818
D64: =D87 -> China | E64: =E87 -> 670 | F64: =F87 -> 750 | G64: =F64-E64 -> 80 | H64: 280 | I64: 310 | J64: =I64-H64 -> 30 | K64: =H64*(0.8)^(LOG((AH31/AB31),2)) -> 278.44215 | L64: =I64*(0.8)^(LOG((AH31/AB31),2)) -> 308.27524 | M64: =L64-K64 -> 29.833088 | BD64: Global | BE64: 691.62622 | BF64: 1656.7511 | BG64: 3343.5745 | BH64: 1790.0288 | BI64: 3825.6556 | BJ64: 1818.6062 | BK64: 4024.9428 | BM64: =BE10+BE64 -> 2501.554 | BN64: =BF10+BF64 -> 5992.3296 | BO64: =BG10+BG64 -> 12093.428 | BP64: =BH10+BH64 -> 6474.384 | BQ64: =BI10+BI64 -> 13837.075 | BR64: =BJ10+BJ64 -> 6577.7458 | BS64: =BK10+BK64 -> 14557.88 | BZ64: 10-pct | CA64: 44.04345 | CB64: 71.1436 | CC64: 91.6385 | CD64: 88.466239 | CE64: 114.44154 | CP64: ASEAN | CQ64: =CA10+CA81 -> 51.583008 | CR64: =CB10+CB81 -> 97.906744 | CS64: =CC10+CC81 -> 289.0634 | CT64: =CD10+CD81 -> 156.88841 | CU64: =CE10+CE81 -> 557.21522
D65: =D88 -> India | E65: =E88 -> 710 | F65: =F88 -> 780 | G65: =F65-E65 -> 70 | H65: 300 | I65: 330 | J65: =I65-H65 -> 30 | K65: =H65*(0.8)^(LOG((AH46/AB46),2)) -> 274.53585 | L65: =I65*(0.8)^(LOG((AH46/AB46),2)) -> 301.98944 | M65: =L65-K65 -> 27.453585 | CA65: -3.5258 | CB65: -5.04955 | CC65: -5.2836 | CD65: -7.8615264 | CE65: -11.784657
D66: =D85 -> Japan | E66: =E85 -> 1880 | F66: =F85 -> 1850 | G66: =F66-E66 -> -30 | H66: 940 | I66: 990 | J66: =I66-H66 -> 50 | K66: =H66*(0.8)^(LOG((AH54/AB54),2)) -> 924.91599 | L66: =I66*(0.8)^(LOG((AH54/AB54),2)) -> 974.11365 | M66: =L66-K66 -> 49.197659 | CA66: 201.15375 | CB66: 414.07695 | CC66: 975.8323 | CD66: 535.59593 | CE66: 1092.1934
D67: Southeast Asia | E67: =AVERAGE(H44,O44:O47,O49) -> 1505.0541 | F67: ='Summarize-ForReg(Current&2050)'!F64 -> 1605.4469 | G67: =F67-E67 -> 100.39273 | H67: =E67*(0.8)^(LOG((AB39/V39),2)) -> 664.03861 | I67: =F67*(0.8)^(LOG((AB39/V39),2)) -> 708.33247 | J67: =I67-H67 -> 44.293856 | K67: =E67*(0.8)^(LOG((AH39/V39),2)) -> 486.26134 | L67: =F67*(0.8)^(LOG((AH39/V39),2)) -> 518.69679 | M67: =L67-K67 -> 32.435448 | N67: - | O67: - | P67: - | CA67: 0.5325 | CB67: 0.7245 | CC67: 1.0092 | CD67: 1.0119006 | CE67: 2.4206173
CA68: 27.5296 | CB68: 81.585 | CC68: 188.6526 | CD68: 79.946891 | CE68: 164.36096
CA69: 2.8431 | CB69: 7.4496 | CC69: 14.291 | CD69: 7.3593607 | CE69: 21.575711
CA70: -1.6224 | CB70: 2.53725 | CC70: 5.28775 | CD70: -2.2228003 | CE70: -2.6451717
CA71: 1.6128093 | CB71: 3.0611806 | CC71: 9.0379399 | CD71: 4.9053184 | CE71: 17.422052
B72: Costs related to CAPEX | E72: Current (2023) | F72: SPS-2050 | G72: APS-2050 | I72: Recalculated but not applied
D73: European Union | E73: =(E60*0.6+F60*0.4)*X95/1000 -> 225.82278 | F73: =(H60*0.6+I60*0.4)*Z95/1000 -> 422.6152 | G73: =(K60*0.6+L60*0.4)*AB95/1000 -> 426.14606 | I73: European Union | J73: =(H60*0.6+I60*0.4)*Z95/1000 -> 422.6152
D74: Brazil | E74: =(E61*0.6+F61*0.4)*X96/1000 -> 27.45976 | F74: =(H61*0.6+I61*0.4)*Z96/1000 -> 45.58992 | G74: =(K61*0.6+L61*0.4)*AB96/1000 -> 63.462045 | I74: Brazil | J74: =(H61*0.6+I61*0.4)*Z96/1000 -> 45.58992 | BZ74: 0-pct | CA74: 52.85214 | CB74: 85.37232 | CC74: 109.9662 | CD74: 106.15949 | CE74: 137.32985
D75: United States | E75: =(E62*0.6+F62*0.4)*X97/1000 -> 347.9875 | F75: =(H62*0.6+I62*0.4)*Z97/1000 -> 1675.0209 | G75: =(K62*0.6+L62*0.4)*AB97/1000 -> 1771.48 | I75: United States | J75: =(H62*0.6+I62*0.4)*Z97/1000 -> 1675.0209 | CA75: -4.23096 | CB75: -6.05946 | CC75: -6.34032 | CD75: -9.4338317 | CE75: -14.141588
D76: Russia | E76: =(E63*0.6+F63*0.4)*X98/1000 -> 2.96922 | F76: =(H63*0.6+I63*0.4)*Z98/1000 -> 5.5506 | G76: =(K63*0.6+L63*0.4)*AB98/1000 -> 9.943362 | I76: Russia | J76: =(H63*0.6+I63*0.4)*Z98/1000 -> 5.5506 | CA76: 241.3845 | CB76: 496.89234 | CC76: 1170.9988 | CD76: 642.71512 | CE76: 1310.632
D77: China | E77: =(E64*0.6+F64*0.4)*X99/1000 -> 483.14448 | F77: =(H64*0.6+I64*0.4)*Z99/1000 -> 2754.328 | G77: =(K64*0.6+L64*0.4)*AB99/1000 -> 2786.8865 | I77: China | J77: =(H64*0.6+I64*0.4)*Z99/1000 -> 2754.328 | CA77: 0.639 | CB77: 0.8694 | CC77: 1.21104 | CD77: 1.2142807 | CE77: 2.9047407
D78: India | E78: =(E65*0.6+F65*0.4)*X100/1000 -> 69.94026 | F78: =(H65*0.6+I65*0.4)*Z100/1000 -> 445.8792 | G78: =(K65*0.6+L65*0.4)*AB100/1000 -> 537.47202 | I78: India | J78: =(H65*0.6+I65*0.4)*Z100/1000 -> 445.8792 | CA78: 33.03552 | CB78: 97.902 | CC78: 226.38312 | CD78: 95.936269 | CE78: 197.23315
D79: Japan | E79: =(E66*0.6+F66*0.4)*X101/1000 -> 202.04288 | F79: =(H66*0.6+I66*0.4)*Z101/1000 -> 203.0496 | G79: =(K66*0.6+L66*0.4)*AB101/1000 -> 210.08739 | I79: Japan | J79: =(H66*0.6+I66*0.4)*Z101/1000 -> 203.0496 | CA79: 3.41172 | CB79: 8.93952 | CC79: 17.1492 | CD79: 8.8312329 | CE79: 25.890853
D80: Southeast Asia | E80: =(E67*0.6+F67*0.4)*V39/1000 -> 49.647637 | F80: =(H67*0.6+I67*0.4)*Z102/1000 -> 278.21787 | G80: =(K67*0.6+L67*0.4)*AB102/1000 -> 536.30875 | CA80: -1.94688 | CB80: 3.0447 | CC80: 6.3453 | CD80: -2.6673603 | CE80: -3.174206
CA81: 1.9353711 | CB81: 3.6734168 | CC81: 10.845528 | CD81: 5.886382 | CE81: 20.906463
D83: European Union | E83: 750 | F83: 990 | G83: =F83-E83 -> 240 | N83: 320 | O83: 450 | P83: =O83-N83 -> 130
D84: United States | E84: 1110 | F84: 3460 | G84: =F84-E84 -> 2350 | N84: 300 | O84: 240 | P84: =O84-N84 -> -60
D85: Japan | E85: 1880 | F85: 1850 | G85: =F85-E85 -> -30 | N85: 440 | O85: 1440 | P85: =O85-N85 -> 1000
D86: Russia | E86: 1250 | F86: 1610 | G86: =F86-E86 -> 360 | N86: 460 | O86: 580 | P86: =O86-N86 -> 120
D87: China | E87: 670 | F87: 750 | G87: =F87-E87 -> 80 | N87: 270 | O87: 300 | P87: =O87-N87 -> 30
D88: India | E88: 710 | F88: 780 | G88: =F88-E88 -> 70 | N88: 280 | O88: 300 | P88: =O88-N88 -> 20
D89: Brazil | E89: 730 | F89: 560 | G89: =F89-E89 -> -170 | N89: 880 | O89: 940 | P89: =O89-N89 -> 60
V92: G-PV: APS's CAPEX | AK92: R-PV: APS's CAPEX
D93: 50-PCT | J93: Inputting to Origin: additional cost: SPS-2050
D94: European Union | E94: =(E60*0.5+F60*0.5)*X95/1000-E73 -> 6.40632 | F94: =(H60*0.5+I60*0.5)*Z95/1000-F73 -> 14.0153 | G94: =(K60*0.5+L60*0.5)*AB95/1000-G73 -> 14.132395 | I94: European Union | J94: =F144 -> 84.0918 | K94: =F134 -> 70.0765 | L94: =F124 -> 56.0612 | M94: =F114 -> 42.0459 | N94: =F104 -> 28.0306 | O94: =F94 -> 14.0153 | V94: Capacity | X94: 2023 | Y94: SPS-2030 | Z94: SPS-2050 | AA94: APS-2030 | AB94: APS-2050 | AK94: Capacity | AM94: 2023 | AN94: SPS-2030 | AO94: SPS-2050 | AP94: APS-2030 | AQ94: APS-2050
D95: Brazil | E95: =(E61*0.5+F61*0.5)*X96/1000-E74 -> -0.70516 | F95: =(H61*0.5+I61*0.5)*Z96/1000-F74 -> -1.05672 | G95: =(K61*0.5+L61*0.5)*AB96/1000-G74 -> -1.4709745 | I95: United States | J95: =F146 -> 1148.2609 | K95: =F136 -> 956.8841 | L95: =F126 -> 765.50728 | M95: =F116 -> 574.13046 | N95: =F106 -> 382.75364 | O95: =F96 -> 191.37682 | W95: European Union | X95: =V19 -> 266.93 | Y95: =X19 -> 646.76 | Z95: =AB19 -> 1078.1 | AA95: =AD19 -> 746.62 | AB95: =AH19 -> 1091.41 | AL95: European Union | AM95: 266.93 | AN95: 646.76 | AO95: 1078.1 | AP95: 746.62 | AQ95: 1091.41
D96: United States | E96: =(E62*0.5+F62*0.5)*X97/1000-E75 -> 39.89125 | F96: =(H62*0.5+I62*0.5)*Z97/1000-F75 -> 191.37682 | G96: =(K62*0.5+L62*0.5)*AB97/1000-G75 -> 202.3976 | I96: Japan | J96: =F150 -> 6.3453 | K96: =F140 -> 5.28775 | L96: =F130 -> 4.2302 | M96: =F120 -> 3.17265 | N96: =F110 -> 2.1151 | O96: =F100 -> 1.05755 | W96: Brazil | X96: =V13 -> 41.48 | Y96: =X13 -> 91.81 | Z96: =AB13 -> 150.96 | AA96: =AD13 -> 135.34 | AB96: =AH13 -> 245.87 | AL96: Brazil | AM96: 41.48 | AN96: 91.81 | AO96: 150.96 | AP96: 135.34 | AQ96: 245.87
D97: Russia | E97: =(E63*0.5+F63*0.5)*X98/1000-E76 -> 0.07668 | F97: =(H63*0.5+I63*0.5)*Z98/1000-F76 -> 0.1682 | G97: =(K63*0.5+L63*0.5)*AB98/1000-G76 -> 0.301314 | I97: Russia | J97: =F147 -> 1.0092 | K97: =F137 -> 0.841 | L97: =F127 -> 0.6728 | M97: =F117 -> 0.5046 | N97: =F107 -> 0.3364 | O97: =F97 -> 0.1682 | W97: United States | X97: =V6 -> 169.75 | Y97: =X6 -> 563.37 | Z97: =AB6 -> 1894.82 | AA97: =AD6 -> 719.52 | AB97: =AH6 -> 2057.92 | AL97: United States | AM97: 169.75 | AN97: 563.37 | AO97: 1894.82 | AP97: 719.52 | AQ97: 2057.92
D98: China | E98: =(E64*0.5+F64*0.5)*X99/1000-E77 -> 5.50592 | F98: =(H64*0.5+I64*0.5)*Z99/1000-F77 -> 28.29789 | G98: =(K64*0.5+L64*0.5)*AB99/1000-G77 -> 28.632395 | I98: China | J98: =F148 -> 169.78734 | K98: =F138 -> 141.48945 | L98: =F128 -> 113.19156 | M98: =F118 -> 84.89367 | N98: =F108 -> 56.59578 | O98: =F98 -> 28.29789 | W98: Russia | X98: =V25 -> 2.13 | Y98: =X25 -> 4.14 | Z98: =AB25 -> 8.41 | AA98: =AD25 -> 5.49 | AB98: =AH25 -> 19.87 | AL98: Russia | AM98: 2.13 | AN98: 4.14 | AO98: 8.41 | AP98: 5.49 | AQ98: 19.87
D99: India | E99: =(E65*0.5+F65*0.5)*X100/1000-E78 -> 0.66339 | F99: =(H65*0.5+I65*0.5)*Z100/1000-F78 -> 4.2873 | G99: =(K65*0.5+L65*0.5)*AB100/1000-G78 -> 5.1680002 | I99: India | J99: =F149 -> 25.7238 | K99: =F139 -> 21.4365 | L99: =F129 -> 17.1492 | M99: =F119 -> 12.8619 | N99: =F109 -> 8.5746 | O99: =F99 -> 4.2873 | W99: China | X99: =V31 -> 688.24 | Y99: =X31 -> 3263.4 | Z99: =AB31 -> 9432.63 | AA99: =AD31 -> 3315.59 | AB99: =AH31 -> 9597.53 | AL99: China | AM99: 688.24 | AN99: 3263.4 | AO99: 9432.63 | AP99: 3315.59 | AQ99: 9597.53
D100: Japan | E100: =(E66*0.5+F66*0.5)*X101/1000-E79 -> -0.32448 | F100: =(H66*0.5+I66*0.5)*Z101/1000-F79 -> 1.05755 | G100: =(K66*0.5+L66*0.5)*AB101/1000-G79 -> 1.0942051 | I100: Brazil | J100: =F145 -> -6.34032 | K100: =F135 -> -5.2836 | L100: =F125 -> -4.22688 | M100: =F115 -> -3.17016 | N100: =F105 -> -2.11344 | O100: =F95 -> -1.05672 | W100: India | X100: =V46 -> 94.77 | Y100: =X46 -> 372.48 | Z100: =AB46 -> 1429.1 | AA100: =AD46 -> 385.32 | AB100: =AH46 -> 1882.45 | AL100: India | AM100: 94.77 | AN100: 372.48 | AO100: 1429.1 | AP100: 385.32 | AQ100: 1882.45
D101: Southeast Asia | E101: =(E67*0.5+F67*0.5)*X102/1000-E80 -> 0.32256186 | F101: =(H67*0.5+I67*0.5)*Z102/1000-F80 -> 1.807588 | G101: =(K67*0.5+L67*0.5)*AB102/1000-G80 -> 3.4844105 | I101: Southeast Asia | J101: =F151 -> 10.845528 | K101: =F141 -> 9.0379399 | L101: =F131 -> 7.2303519 | M101: =F121 -> 5.4227639 | N101: =F111 -> 3.615176 | O101: =F101 -> 1.807588 | W101: Japan | X101: =V54 -> 108.16 | Y101: =X54 -> 169.15 | Z101: =AB54 -> 211.51 | AA101: =AD54 -> 172.08 | AB101: =AH54 -> 222.41 | AL101: Japan | AM101: 108.16 | AN101: 169.15 | AO101: 211.51 | AP101: 172.08 | AQ101: 222.41
W102: Southeast Asia | X102: =V39 -> 32.13 | Y102: =X39 -> 82.67 | Z102: =AB39 -> 408.09 | AA102: =AD39 -> 165.71 | AB102: =AH39 -> 1074.26 | AL102: Southeast Asia | AM102: 32.13 | AN102: 82.67 | AO102: 408.09 | AP102: 165.71 | AQ102: 1074.26
J103: Inputting to Origin: additional cost: APS-2050
...

Sheet Summarize-ForReg(2030)
A1: *Priciple: Exclusive the duplicate records from WEO, IEA2020, IRENA from Data of Brief; Use the record of now (preferring latest year); if there are multiple records in a same reference (except those notifying maximum or minimum value), average them to represent the figure for this reference
F3: WEO2024 (large, ground-mounted) | G3: WEO2024 (rooftop) | H3: IRENA2024 (large, ground-mounted) | I3: IEA2020 (large, ground-mounted, 3% disc-rate) | J3: IEA2020 (large, ground-mounted, 7% discount rate) | K3: IEA2020 (large, ground-mounted, 10% discount rate) | L3: IEA2020 (rooftop, 3% disc-rate) | M3: IEA2020 (rooftop, 7% discount rate) | N3: IEA2020 (rooftop, 10% discount rate) | O3: Hatton et al., 2024 (large, ground-mounted) | V3: NA
D4: Europe | E4: EU-27 | F4: =Attached_WEO2023!B12 -> 750 | G4: =Attached_WEO2023!F12 -> 990 | O4: =AVERAGE('Attached-DIB_GNESTE_Solar_Power'!W70:W74) -> 860.90269 | X4: Stated Policies (STEPS) | AD4: Announced Pledges (APS)
E5: Greece | H5: ='Attached-IRENA2024 report'!J20 -> 626.34564 | V5: 2023 | X5: 2030 | Y5: 2035 | Z5: 2040 | AA5: 2045 | AB5: 2050 | AD5: 2030 | AE5: 2035 | AF5: 2040 | AG5: 2045 | AH5: 2050 | BD5: Cost components across | BE5: SPS | BK5: APS | BO5: NZE
E6: Netherlands | H6: ='Attached-IRENA2024 report'!J22 -> 753.19994 | I6: ='Attached-IEA2020Projected Costs'!K39 -> 819.39997 | J6: ='Attached-IEA2020Projected Costs'!L39 -> 835.15911 | K6: ='Attached-IEA2020Projected Costs'!M39 -> 846.78601 | L6: ='Attached-IEA2020Projected Costs'!K38 -> 858.48319 | M6: ='Attached-IEA2020Projected Costs'!L38 -> 874.994 | N6: ='Attached-IEA2020Projected Costs'!M38 -> 887.17547 | O6: =AVERAGE('Attached-DIB_GNESTE_Solar_Power'!V66:V68) -> 787.41448 | V6: 188.55 | X6: 608.6 | Y6: 973.35 | Z6: 1356.32 | AA6: 1718.79 | AB6: 1998.23 | AD6: 769.55 | AE6: 1311.5 | AF6: 1768.76 | AG6: 2146.99 | AH6: 2341.13 | BD6: geographies over years and scenarios | BE6: CAPEX ($/kW) | BH6: AOM ($/kW) | BK6: CAPEX | BM6: CAPEX ($/kW) | BO6: NZE-CAPEX ($/kW) | BR6: NZE-AOM ($/kW)
E7: Germany | H7: ='Attached-IRENA2024 report'!J24 -> 730.77006 | O7: =AVERAGE('Attached-DIB_GNESTE_Solar_Power'!X89:X90) -> 757.7542 | BK7: ($/kW)
E8: United Kingdom | H8: ='Attached-IRENA2024 report'!J26 -> 932.69058 | BE8: Present year | BF8: 2030 | BG8: 2050 | BH8: 2022 | BI8: 2030 | BJ8: 2050 | BK8: 2030 | BL8: 2050 | BM8: 2030 | BN8: 2050 | BP8: 2030 | BQ8: 2050 | BR8: 2030 | BS8: 2050
E9: Portugal | H9: ='Attached-IRENA2024 report'!J28 -> 723.26964 | BD9: Large,ground-mounted PV
E10: France | H10: ='Attached-IRENA2024 report'!J30 -> 954.78012 | I10: {='Attached-IEA2020Projected Costs'!K21:M21} -> 718.7719 | J10: 732.59571 | K10: 742.79475 | L10: =AVERAGE('Attached-IEA2020Projected Costs'!K19:K20) -> 1293.7894 | M10: =AVERAGE('Attached-IEA2020Projected Costs'!L19:L20) -> 1318.6723 | N10: =AVERAGE('Attached-IEA2020Projected Costs'!M19:M20) -> 1337.0305 | V10: CSA | BD10: EUR# | BE10: 801 | BF10: 596 | BG10: ='Summarize-ForReg(Current&2050)'!H60 -> 500.58529 | BK10: =K60 -> 565.8252 | BL10: ='Summarize-ForReg(Current&2050)'!K60 -> 485.9074
E11: Italy | H11: ='Attached-IRENA2024 report'!J32 -> 821.34079 | I11: =AVERAGE('Attached-IEA2020Projected Costs'!K31:K32) -> 844.08816 | J11: =AVERAGE('Attached-IEA2020Projected Costs'!L31:L32) -> 860.32211 | K11: =AVERAGE('Attached-IEA2020Projected Costs'!M31:M32) -> 872.29933 | L11: =AVERAGE('Attached-IEA2020Projected Costs'!K26:K30) -> 1347.0298 | M11: =AVERAGE('Attached-IEA2020Projected Costs'!L26:L30) -> 1372.9366 | N11: =AVERAGE('Attached-IEA2020Projected Costs'!M26:M30) -> 1392.0503 | X11: Stated Policies (STEPS) | AD11: Announced Pledges (APS) | BD11: EU-27 | BE11: 990 | BF11: 620 | BG11: 450 | BH11: 14 | BI11: 14 | BJ11: 12 | BK11: 711* | BL11: 629* | BM11: 10* | BN11: 9* | BP11: 580 | BQ11: 410 | BR11: 14 | BS11: 12
E12: Spain | H12: ='Attached-IRENA2024 report'!J57 -> 670.76717 | V12: 2023 | X12: 2030 | Y12: 2035 | Z12: 2040 | AA12: 2045 | AB12: 2050 | AD12: 2030 | AE12: 2035 | AF12: 2040 | AG12: 2045 | AH12: 2050 | BD12: NA# | BE12: 1174 | BF12: 805 | BG12: ='Summarize-ForReg(Current&2050)'!H62 -> 548.88299 | BK12: =K62 -> 746.25896 | BL12: ='Summarize-ForReg(Current&2050)'!K62 -> 521.59995
E13: Turkey | H13: ='Attached-IRENA2024 report'!J58 -> 715.36 | V13: 61.93 | X13: 144.78 | Y13: 176.87 | Z13: 219.78 | AA13: 258.21 | AB13: 309.64 | AD13: 222.89 | AE13: 321.92 | AF13: 432.17 | AG13: 534.61 | AH13: 666.41 | BD13: USA | BE13: 1 120 | BF13: 690 | BG13: 480 | BH13: 16 | BI13: 16 | BJ13: 16 | BK13: 704* | BL13: 502* | BM13: 10* | BN13: 7* | BP13: 640 | BQ13: 440 | BR13: 16 | BS13: 16
E14: Hungary | H14: ='Attached-IRENA2024 report'!J62 -> 1078 | I14: ='Attached-IEA2020Projected Costs'!K25 -> 978.03747 | J14: ='Attached-IEA2020Projected Costs'!L25 -> 996.84761 | K14: ='Attached-IEA2020Projected Costs'!M25 -> 1010.7255 | L14: =AVERAGE('Attached-IEA2020Projected Costs'!K22:K24) -> 1445.272 | M14: =AVERAGE('Attached-IEA2020Projected Costs'!L22:L24) -> 1473.0682 | N14: =AVERAGE('Attached-IEA2020Projected Costs'!M22:M24) -> 1493.5759 | BD14: Eurasia# | BE14: 1249 | BF14: =H63 -> 721.19557 | BG14: ='Summarize-ForReg(Current&2050)'!H63 -> 582.51482 | BK14: =K63 -> 669.63033 | BL14: ='Summarize-ForReg(Current&2050)'!K63 -> 439.43621
E15: Belgium | H15: ='Attached-IRENA2024 report'!J63 -> 965 | I15: ='Attached-IEA2020Projected Costs'!K12 -> 1006.2807 | J15: ='Attached-IEA2020Projected Costs'!L12 -> 1025.634 | K15: ='Attached-IEA2020Projected Costs'!M12 -> 1039.9126 | L15: =AVERAGE('Attached-IEA2020Projected Costs'!K9:K11) -> 1419.3349 | M15: =AVERAGE('Attached-IEA2020Projected Costs'!L9:L11) -> 1446.6323 | N15: =AVERAGE('Attached-IEA2020Projected Costs'!M9:M11) -> 1466.772 | BD15: RU | BE15: 1 710 | BF15: 1 090 | BG15: 770 | BH15: 26 | BI15: 24 | BJ15: 22 | BK15: 1261* | BL15: 833* | BM15: 19* | BN15: 13* | BP15: 940 | BQ15: 610 | BR15: 22 | BS15: 22
E16: Cyprus | H16: ='Attached-IRENA2024 report'!J64 -> 854 | V16: EUR | BD16: APJ# | BE16: 1182 | BF16: =H64 -> 752.49095 | BG16: ='Summarize-ForReg(Current&2050)'!H64 -> 532.07381 | BK16: =K64 -> 739.91297 | BL16: ='Summarize-ForReg(Current&2050)'!K64 -> 511.81827
E17: Slovakia | H17: ='Attached-IRENA2024 report'!J65 -> 844 | X17: Stated Policies (STEPS) | AD17: Announced Pledges (APS) | BD17: JP | BE17: 1 910 | BF17: 1 250 | BG17: 940 | BH17: 28 | BI17: 26 | BJ17: 24 | BK17: 1645* | BL17: 1514* | BM17: 24* | BN17: 22* | BP17: 1 180 | BQ17: 860 | BR17: 24 | BS17: 22
E18: Romania | H18: ='Attached-IRENA2024 report'!J67 -> 743 | V18: 2023 | X18: 2030 | Y18: 2035 | Z18: 2040 | AA18: 2045 | AB18: 2050 | AD18: 2030 | AE18: 2035 | AF18: 2040 | AG18: 2045 | AH18: 2050 | BD18: CN | BE18: 720 | BF18: 430 | BG18: 300 | BH18: 12 | BI18: 10 | BJ18: 10 | BK18: 434* | BL18: 308* | BM18: 7* | BN18: 5* | BP18: 410 | BQ18: 280 | BR18: 10 | BS18: 10
E19: Latvia | H19: ='Attached-IRENA2024 report'!J68 -> 716 | V19: 318.09 | X19: 795.05 | Y19: 1069.78 | Z19: 1216.75 | AA19: 1302.64 | AB19: 1343.31 | AD19: 918.14 | AE19: 1214.27 | AF19: 1349.99 | AG19: 1431.75 | AH19: 1473.41 | BD19: IN | BE19: 640 | BF19: 390 | BG19: 270 | BH19: 10 | BI19: 8 | BJ19: 8 | BK19: 407* | BL19: 245* | BM19: 6* | BN19: 4* | BP19: 360 | BQ19: 240 | BR19: 8 | BS19: 8
E20: Estonia | H20: ='Attached-IRENA2024 report'!J69 -> 705 | BD20: ASEAN# | BE20: 1505 | BF20: ='Summari-ForCount (2030)'!H67 -> 1110.2502 | BG20: ='Summari-ForCount (Current&2050)'!H67 -> 664.03861 | BK20: ='Summari-ForCount (2030)'!K67 -> 887.56122 | BL20: ='Summari-ForCount (Current&2050)'!K67 -> 486.26134
E21: Poland | H21: ='Attached-IRENA2024 report'!J70 -> 700 | BD21: ME | BE21: 620 | BF21: 360 | BG21: 250 | BH21: 10 | BI21: 8 | BJ21: 8 | BK21: 300* | BL21: 155* | BM21: 5* | BN21: 2* | BP21: 330 | BQ21: 220 | BR21: 8 | BS21: 8
E22: Ireland | H22: ='Attached-IRENA2024 report'!J71 -> 686 | V22: Eurasia | BD22: AF | BE22: 1 420 | BF22: 850 | BG22: 580 | BH22: 22 | BI22: 20 | BJ22: 18 | BK22: 671* | BL22: 390* | BM22: 10* | BN22: 6* | BP22: 760 | BQ22: 490 | BR22: 18 | BS22: 18
E23: Luxembourg | H23: ='Attached-IRENA2024 report'!J72 -> 684 | X23: Stated Policies (STEPS) | AD23: Announced Pledges (APS) | BD23: CSA# | BE23: 1019 | BF23: =H61 -> 773.68396 | BG23: ='Summarize-ForReg(Current&2050)'!H61 -> 605.73061 | BK23: =K61 -> 673.34875 | BL23: ='Summarize-ForReg(Current&2050)'!K61 -> 473.2762
E24: Austria | H24: ='Attached-IRENA2024 report'!J73 -> 678 | I24: ='Attached-IEA2020Projected Costs'!K6 -> 729.55348 | J24: ='Attached-IEA2020Projected Costs'!L6 -> 743.58464 | K24: ='Attached-IEA2020Projected Costs'!M6 -> 753.93667 | L24: ='Attached-IEA2020Projected Costs'!K6 -> 729.55348 | M24: ='Attached-IEA2020Projected Costs'!L6 -> 743.58464 | N24: ='Attached-IEA2020Projected Costs'!M6 -> 753.93667 | V24: 2023 | X24: 2030 | Y24: 2035 | Z24: 2040 | AA24: 2045 | AB24: 2050 | AD24: 2030 | AE24: 2035 | AF24: 2040 | AG24: 2045 | AH24: 2050 | BD24: BR | BE24: 750 | BF24: 460 | BG24: 330 | BH24: 12 | BI24: 10 | BJ24: 10 | BK24: 513* | BL24: 423* | BM24: 8* | BN24: 7* | BP24: 430 | BQ24: 300 | BR24: 10 | BS24: 10
E25: Czech Republic | H25: ='Attached-IRENA2024 report'!J74 -> 663 | V25: 4.7 | X25: 17.21 | Y25: 22.8 | Z25: 27.15 | AA25: 30.57 | AB25: 33.41 | AD25: 21.67 | AE25: 36.9 | AF25: 51.96 | AG25: 65.8 | AH25: 80.19 | BD25: Rooftop PV
E26: Bulgaria | H26: ='Attached-IRENA2024 report'!J75 -> 659 | BD26: EUR# | BE26: 1166 | BF26: 868 | BG26: ='Summarize-ForReg(Current&2050)'!I60 -> 725.16256 | BK26: =L60 -> 819.671 | BL26: ='Summarize-ForReg(Current&2050)'!L60 -> 703.89974
E27: Denmark | I27: =AVERAGE('Attached-IEA2020Projected Costs'!K17:K18) -> 587.43464 | J27: =AVERAGE('Attached-IEA2020Projected Costs'!L17:L18) -> 598.7325 | K27: =AVERAGE('Attached-IEA2020Projected Costs'!M17:M18) -> 607.06792 | L27: =AVERAGE('Attached-IEA2020Projected Costs'!K15:K16) -> 1026.7533 | M27: =AVERAGE('Attached-IEA2020Projected Costs'!L15:L16) -> 1046.5004 | N27: =AVERAGE('Attached-IEA2020Projected Costs'!M15:M16) -> 1061.0695 | BD27: EU-27 | BE27: 1 320 | BF27: 840 | BG27: 620 | BH27: 20 | BI27: 18 | BJ27: 18 | BK27: 948* | BL27: 839* | BM27: 14* | BN27: 13* | BP27: 800 | BQ27: 570 | BR27: 18 | BS27: 14
E28: Norway | L28: ='Attached-IEA2020Projected Costs'!K40 -> 998.35392 | M28: ='Attached-IEA2020Projected Costs'!L40 -> 1017.5548 | N28: ='Attached-IEA2020Projected Costs'!M40 -> 1031.721 | V28: APJ | BD28: NA# | BE28: 2238 | BF28: =I62 -> 1529.5607 | BG28: ='Summarize-ForReg(Current&2050)'!I62 -> 1043.1599 | BK28: =L62 -> 1418.2757 | BL28: ='Summarize-ForReg(Current&2050)'!L62 -> 991.30812
E29: Croatia | X29: Stated Policies (STEPS) | AD29: Announced Pledges (APS) | BD29: USA | BE29: 3 490 | BF29: 2 160 | BG29: 1 510 | BH29: 52 | BI29: 48 | BJ29: 44 | BK29: 2192* | BL29: 1563* | BM29: 33* | BN29: 23* | BP29: 2 020 | BQ29: 1 390 | BR29: 46 | BS29: 44
D30: South America | E30: Chile | H30: ='Attached-IRENA2024 report'!J50 -> 953.80679 | V30: 2023 | X30: 2030 | Y30: 2035 | Z30: 2040 | AA30: 2045 | AB30: 2050 | AD30: 2030 | AE30: 2035 | AF30: 2040 | AG30: 2045 | AH30: 2050 | BD30: Eurasia# | BE30: 2210 | BF30: =I63 -> 1060.1333 | BG30: ='Summarize-ForReg(Current&2050)'!I63 -> 856.27726 | BK30: =L63 -> 984.33413 | BL30: ='Summarize-ForReg(Current&2050)'!L63 -> 645.95649
E31: Argentina | H31: ='Attached-IRENA2024 report'!J53 -> 830 | V31: 1005.71 | X31: 4084.58 | Y31: 6629.81 | Z31: 9040.8 | AA31: 11049.3 | AB31: 11987.66 | AD31: 4304.15 | AE31: 7182.92 | AF31: 10076.95 | AG31: 12366.68 | AH31: 13523.66 | BD31: RU | BE31: 2 210 | BF31: 1 440 | BG31: 1 010 | BH31: 34 | BI31: 30 | BJ31: 28 | BK31: 1629* | BL31: 1077* | BM31: 25* | BN31: 17* | BP31: 1 200 | BQ31: 760 | BR31: 30 | BS31: 28
E32: Brazil | F32: =Attached_WEO2023!B18 -> 730 | G32: =Attached_WEO2023!F18 -> 560 | H32: ='Attached-IRENA2024 report'!J48 -> 726.98559 | I32: ='Attached-IEA2020Projected Costs'!K60 -> 1215.2033 | J32: ='Attached-IEA2020Projected Costs'!L60 -> 1238.5747 | K32: ='Attached-IEA2020Projected Costs'!M60 -> 1255.8179 | O32: ='Attached-DIB_GNESTE_Solar_Power'!V134 -> 1382.1652 | BD32: APJ# | BE32: 1605 | BF32: =I64 -> 1022.4603 | BG32: ='Summarize-ForReg(Current&2050)'!I64 -> 722.96468 | BK32: =L64 -> 1005.3698 | BL32: ='Summarize-ForReg(Current&2050)'!L64 -> 695.4421
E33: South America | O33: ='Attached-DIB_GNESTE_Solar_Power'!AA338 -> 819.85934 | BD33: JP | BE33: 1 880 | BF33: 1 280 | BG33: 990 | BH33: 28 | BI33: 26 | BJ33: 24 | BK33: 1619* | BL33: 1491* | BM33: 24* | BN33: 22* | BP33: 1 210 | BQ33: 910 | BR33: 24 | BS33: 22
D34: North America | E34: United States | F34: =Attached_WEO2023!B13 -> 1110 | G34: =Attached_WEO2023!F13 -> 3460 | H34: ='Attached-IRENA2024 report'!J42 -> 1108.5304 | I34: =AVERAGE('Attached-IEA2020Projected Costs'!K51:K55) -> 1087.637 | J34: =AVERAGE('Attached-IEA2020Projected Costs'!L51:L55) -> 1108.555 | K34: =AVERAGE('Attached-IEA2020Projected Costs'!M51:M55) -> 1123.9881 | L34: =AVERAGE('Attached-IEA2020Projected Costs'!K41:K50) -> 1789.2317 | M34: =AVERAGE('Attached-IEA2020Projected Costs'!L41:L50) -> 1823.6432 | N34: =AVERAGE('Attached-IEA2020Projected Costs'!M41:M50) -> 1849.0316 | O34: =AVERAGE('Attached-DIB_GNESTE_Solar_Power'!V15,'Attached-DIB_GNESTE_Solar_Power'!Z17:Z310,'Attached-DIB_GNESTE_Solar_Power'!AB313:AB315,'Attached-DIB_GNESTE_Solar_Power'!Z319,'Attached-DIB_GNESTE_Solar_Power'!X325,'Attached-DIB_GNESTE_Solar_Power'!Y326,'Attached-DIB_GNESTE_Solar_Power'!X331,'Attached-DIB_GNESTE_Solar_Power'!Y332) -> 1349.0303 | BD34: CN | BE34: 800 | BF34: 480 | BG34: 340 | BH34: 14 | BI34: 12 | BJ34: 12 | BK34: 482* | BL34: 343* | BM34: 8* | BN34: 6* | BP34: 450 | BQ34: 320 | BR34: 10 | BS34: 10
E35: Canada | H35: ='Attached-IRENA2024 report'!J38 -> 1336.5221 | I35: =AVERAGE('Attached-IEA2020Projected Costs'!K13:K14) -> 1328.7693 | J35: =AVERAGE('Attached-IEA2020Projected Costs'!L13:L14) -> 1354.3249 | K35: =AVERAGE('Attached-IEA2020Projected Costs'!M13:M14) -> 1373.1795 | BD35: IN | BE35: 700 | BF35: 430 | BG35: 290 | BH35: 10 | BI35: 10 | BJ35: 8 | BK35: 446* | BL35: 267* | BM35: 6* | BN35: 4* | BP35: 390 | BQ35: 260 | BR35: 10 | BS35: 8
E36: Mexico | H36: ='Attached-IRENA2024 report'!J40 -> 1049.5172 | O36: ='Attached-DIB_GNESTE_Solar_Power'!V137 -> 990.405 | V36: ASEAN | BD36: ASEAN# | BE36: 1605 | BF36: ='Summari-ForCount (2030)'!I67 -> 1184.308 | BG36: ='Summari-ForCount (Current&2050)'!I67 -> 708.33247 | BK36: ='Summari-ForCount (2030)'!L67 -> 946.76487 | BL36: ='Summari-ForCount (Current&2050)'!L67 -> 518.69679
E37: North America | O37: ='Attached-DIB_GNESTE_Solar_Power'!AA337 -> 936.56791 | X37: Stated Policies (STEPS) | AD37: Announced Pledges (APS) | BD37: ME | BE37: 1 020 | BF37: 580 | BG37: 390 | BH37: 16 | BI37: 14 | BJ37: 12 | BK37: 493* | BL37: 255* | BM37: 8* | BN37: 4* | BP37: 530 | BQ37: 340 | BR37: 14 | BS37: 12
D38: Eurasia | E38: Russia | F38: =Attached_WEO2023!B15 -> 1250 | G38: =Attached_WEO2023!F15 -> 1610 | H38: ='Attached-IRENA2024 report'!J83 -> 1248 | O38: ='Attached-DIB_GNESTE_Solar_Power'!AA341 -> 787.78925 | V38: 2023 | X38: 2030 | Y38: 2035 | Z38: 2040 | AA38: 2045 | AB38: 2050 | AD38: 2030 | AE38: 2035 | AF38: 2040 | AG38: 2045 | AH38: 2050 | BD38: AF | BE38: 1 970 | BF38: 1 150 | BG38: 770 | BH38: 30 | BI38: 26 | BJ38: 26 | BK38: 930* | BL38: 541* | BM38: 14* | BN38: 8* | BP38: 1 000 | BQ38: 640 | BR38: 26 | BS38: 24
D39: Asia Pacific | E39: Japan | F39: =Attached_WEO2023!B14 -> 1880 | G39: =Attached_WEO2023!F14 -> 1850 | H39: ='Attached-IRENA2024 report'!J15 -> 1875.2399 | I39: ='Attached-IEA2020Projected Costs'!K34 -> 2035.9917 | J39: ='Attached-IEA2020Projected Costs'!L34 -> 2075.149 | K39: ='Attached-IEA2020Projected Costs'!M34 -> 2104.0388 | L39: ='Attached-IEA2020Projected Costs'!K33 -> 2367.4727 | M39: ='Attached-IEA2020Projected Costs'!L33 -> 2413.0052 | N39: ='Attached-IEA2020Projected Costs'!M33 -> 2446.5985 | V39: 32.13 | X39: 82.67 | Y39: 150.99 | Z39: 236.9 | AA39: 319.85 | AB39: 408.09 | AD39: 165.71 | AE39: 368.34 | AF39: 669.78 | AG39: 898.17 | AH39: 1074.26 | BD39: CSA# | BE39: 580 | BF39: =I61 -> 426.048 | BG39: ='Summarize-ForReg(Current&2050)'!I61 -> 333.56038 | BK39: =L61 -> 370.79597 | BL39: ='Summarize-ForReg(Current&2050)'!L61 -> 260.62112
E40: China | F40: =Attached_WEO2023!B16 -> 670 | G40: =Attached_WEO2023!F16 -> 750 | H40: ='Attached-IRENA2024 report'!J11 -> 671.12616 | I40: ='Attached-IEA2020Projected Costs'!K61 -> 741.29534 | J40: ='Attached-IEA2020Projected Costs'!L61 -> 755.55232 | K40: ='Attached-IEA2020Projected Costs'!M61 -> 766.07096 | O40: ='Attached-DIB_GNESTE_Solar_Power'!AA342 -> 694.64666 | BD40: BR | BE40: 580 | BF40: 350 | BG40: 260 | BH40: 8 | BI40: 8 | BJ40: 8 | BK40: 396* | BL40: 327* | BM40: 5* | BN40: 5* | BP40: 330 | BQ40: 240 | BR40: 8 | BS40: 8
E41: India | F41: =Attached_WEO2023!B17 -> 710 | G41: =Attached_WEO2023!F17 -> 780 | H41: ='Attached-IRENA2024 report'!J13 -> 711.32819 | I41: ='Attached-IEA2020Projected Costs'!K62 -> 638.03526 | J41: ='Attached-IEA2020Projected Costs'!L62 -> 650.30629 | K41: ='Attached-IEA2020Projected Costs'!M62 -> 659.35972 | O41: =AVERAGE('Attached-DIB_GNESTE_Solar_Power'!W25,'Attached-DIB_GNESTE_Solar_Power'!V135,'Attached-DIB_GNESTE_Solar_Power'!AA343) -> 670.57179
E42: Republic of Korea | H42: ='Attached-IRENA2024 report'!J17 -> 1205.2601 | I42: ='Attached-IEA2020Projected Costs'!K36 -> 1244.0419 | J42: ='Attached-IEA2020Projected Costs'!L36 -> 1267.9679 | K42: ='Attached-IEA2020Projected Costs'!M36 -> 1285.6203 | L42: ='Attached-IEA2020Projected Costs'!K35 -> 1258.5589 | M42: ='Attached-IEA2020Projected Costs'!L35 -> 1282.7641 | N42: ='Attached-IEA2020Projected Costs'!M35 -> 1300.6225
E43: Australia | H43: ='Attached-IRENA2024 report'!J45 -> 988.62812 | I43: ='Attached-IEA2020Projected Costs'!K7 -> 895.14787 | J43: ='Attached-IEA2020Projected Costs'!L7 -> 912.36383 | K43: ='Attached-IEA2020Projected Costs'!M7 -> 925.06556 | O43: =AVERAGE('Attached-DIB_GNESTE_Solar_Power'!AA19:AA21) -> 932.2705 | V43: World
E44: Indonesia | H44: ='Attached-IRENA2024 report'!J78 -> 798 | O44: =AVERAGE('Attached-DIB_GNESTE_Solar_Power'!V3:V4,'Attached-DIB_GNESTE_Solar_Power'!V133) -> 1913.4028 | W44: Stated Policies (GW) | AB44: Announced Pledges (GW) | AG44: Net Zero Emissions by 2050 (GW)
E45: Malaysia | O45: =AVERAGE('Attached-DIB_GNESTE_Solar_Power'!V5:V6) -> 2262.804 | V45: 2023 | W45: 2030 | X45: 2035 | Y45: 2040 | Z45: 2045 | AA45: 2050 | AB45: 2030 | AC45: 2035 | AD45: 2040 | AE45: 2045 | AF45: 2050 | AG45: 2030 | AH45: 2035 | AI45: 2040 | AJ45: 2045 | AK45: 2050
E46: Philippines | O46: =AVERAGE('Attached-DIB_GNESTE_Solar_Power'!V7:V8) -> 2229.198 | V46: 1609.87 | W46: 5838.45 | X46: 9203.17 | Y46: 12333.11 | Z46: 14972.81 | AA46: 16445.01 | AB46: 6544.16 | AC46: 10792.62 | AD46: 14800.73 | AE46: 18066.24 | AF46: 20058.6 | AG46: 6698.82 | AH46: 12044.04 | AI46: 16455.02 | AJ46: 19462.09 | AK46: 21618.47
E47: Thailand | O47: =AVERAGE('Attached-DIB_GNESTE_Solar_Power'!V136) -> 1108.1532
E48: Asia | O48: ='Attached-DIB_GNESTE_Solar_Power'!V11 -> 2254.9626
E49: Southeast Asia | O49: ='Attached-DIB_GNESTE_Solar_Power'!AA344 -> 718.76686
E50: OECD Asia & Oceania | O50: ='Attached-DIB_GNESTE_Solar_Power'!AA345 -> 922.20862
D51: Global | H51: ='Attached-IRENA2024 report'!AB11 -> 757.68783 | O51: =AVERAGE('Attached-DIB_GNESTE_Solar_Power'!W76:W322) -> 918.0296
V52: ME | X52: Stated Policies (STEPS) | AD52: Announced Pledges (APS)
V53: 2023 | X53: 2030 | Y53: 2035 | Z53: 2040 | AA53: 2045 | AB53: 2050 | AD53: 2030 | AE53: 2035 | AF53: 2040 | AG53: 2045 | AH53: 2050
V54: 13.85 | X54: 106.79 | Y54: 178.54 | Z54: 251.87 | AA54: 328.15 | AB54: 440.63 | AD54: 132.56 | AE54: 377.15 | AF54: 585.12 | AG54: 782.52 | AH54: 1028.37
B58: CAPEX | E58: Current-2023 | H58: SPS-2030 | K58: APS-2030 | N58: NZE-2030 | V58: AF | X58: Stated Policies (STEPS) | AD58: Announced Pledges (APS) | AK58: Capacity
E59: Large, ground-mounted PV | F59: Rooftop PV | G59: Differences | V59: 2023 | X59: 2030 | Y59: 2035 | Z59: 2040 | AA59: 2045 | AB59: 2050 | AD59: 2030 | AE59: 2035 | AF59: 2040 | AG59: 2045 | AH59: 2050 | AL59: 2023 | AM59: SPS2030 | AN59: SPS2050 | AP59: APS2030 | AQ59: APS2050
D60: Europe | E60: =AVERAGE(F4:F29,H4:K29,O4:O29) -> 795.94809 | F60: =AVERAGE(G4:G29,L4:N29) -> 1153.0338 | G60: =F60-E60 -> 357.0857 | H60: =E60*(0.8)^(LOG((X19/V19),2)) -> 592.6625 | I60: =F60*(0.8)^(LOG((X19/V19),2)) -> 858.5483 | J60: =I60-H60 -> 265.88581 | K60: =E60*(0.8)^(LOG((AD19/V19),2)) -> 565.8252 | L60: =F60*(0.8)^(LOG((AD19/V19),2)) -> 819.671 | M60: =L60-K60 -> 253.84581 | V60: 17.04 | X60: 81.43 | Y60: 152.02 | Z60: 220.44 | AA60: 285.15 | AB60: 332.13 | AD60: 175.19 | AE60: 347.96 | AF60: 535.77 | AG60: 737.89 | AH60: 945.41 | AK60: Europe | AL60: =V19 -> 318.09 | AM60: =X19 -> 795.05 | AN60: =AB19 -> 1343.31 | AP60: =AD19 -> 918.14 | AQ60: =AH19 -> 1473.41 | AS60: =SUM(AL60:AL66) -> 1609.87
D61: =D30 -> South America | E61: =AVERAGE(F30:F33,H30:K33,O30:O33) -> 1016.9347 | F61: =AVERAGE(G30:G33,L30:N33) -> 560 | G61: =F61-E61 -> -456.93475 | H61: =E61*(0.8)^(LOG((X13/V13),2)) -> 773.68396 | I61: =F61*(0.8)^(LOG((X13/V13),2)) -> 426.048 | J61: =I61-H61 -> -347.63596 | K61: =E61*(0.8)^(LOG((AD13/V13),2)) -> 673.34875 | L61: =F61*(0.8)^(LOG((AD13/V13),2)) -> 370.79597 | M61: =L61-K61 -> -302.55279 | AK61: South America | AL61: =V13 -> 61.93 | AM61: =X13 -> 144.78 | AN61: =AB13 -> 309.64 | AP61: =AD13 -> 222.89 | AQ61: =AH13 -> 666.41 | AS61: =AS60 -> 1609.87
D62: =D34 -> North America | E62: =AVERAGE(F34:F37,H34:K37,O34:O37) -> 1173.6174 | F62: =AVERAGE(G34:G37,L34:N37) -> 2230.4766 | G62: =F62-E62 -> 1056.8592 | H62: =E62*(0.8)^(LOG((X6/V6),2)) -> 804.81415 | I62: =F62*(0.8)^(LOG((X6/V6),2)) -> 1529.5607 | J62: =I62-H62 -> 724.74658 | K62: =E62*(0.8)^(LOG((AD6/V6),2)) -> 746.25896 | L62: =F62*(0.8)^(LOG((AD6/V6),2)) -> 1418.2757 | M62: =L62-K62 -> 672.01679 | AK62: North America | AL62: =V6 -> 188.55 | AM62: =X6 -> 608.6 | AN62: =AB6 -> 1998.23 | AP62: =AD6 -> 769.55 | AQ62: =AH6 -> 2341.13 | AS62: =AS61 -> 1609.87
D63: =D38 -> Eurasia | E63: =AVERAGE(F38,H38:K38,O38) -> 1095.2631 | F63: =AVERAGE(G38,L38:N38) -> 1610 | G63: =F63-E63 -> 514.73692 | H63: =E63*(0.8)^(LOG((X25/V25),2)) -> 721.19557 | I63: =F63*(0.8)^(LOG((X25/V25),2)) -> 1060.1333 | J63: =I63-H63 -> 338.93773 | K63: =E63*(0.8)^(LOG((AD25/V25),2)) -> 669.63033 | L63: =F63*(0.8)^(LOG((AD25/V25),2)) -> 984.33413 | M63: =L63-K63 -> 314.7038 | AK63: Eurasia | AL63: =V25 -> 4.7 | AM63: =X25 -> 17.21 | AN63: =AB25 -> 33.41 | AP63: =AD25 -> 21.67 | AQ63: =AH25 -> 80.19 | AS63: =AS62 -> 1609.87
D64: =D39 -> Asia Pacific | E64: =AVERAGE(F39:F50,H39:K50,O39:O50) -> 1181.5463 | F64: =AVERAGE(G39:G50,L39:N50) -> 1605.4469 | G64: =F64-E64 -> 423.90057 | H64: =E64*(0.8)^(LOG((X31/V31),2)) -> 752.49095 | I64: =F64*(0.8)^(LOG((X31/V31),2)) -> 1022.4603 | J64: =I64-H64 -> 269.9694 | K64: =E64*(0.8)^(LOG((AD31/V31),2)) -> 739.91297 | L64: =F64*(0.8)^(LOG((AD31/V31),2)) -> 1005.3698 | M64: =L64-K64 -> 265.45682 | AK64: Asia Pacific | AL64: =V31 -> 1005.71 | AM64: =X31 -> 4084.58 | AN64: =AB31 -> 11987.66 | AP64: =AD31 -> 4304.15 | AQ64: =AH31 -> 13523.66 | AS64: =AS63 -> 1609.87
D65: Middle East | E65: 610 | F65: 1010 | G65: =F65-E65 -> 400 | H65: 360 | I65: 580 | J65: =I65-H65 -> 220 | K65: =H65*(0.8)^(LOG((AD54/X54),2)) -> 335.79891 | L65: =I65*(0.8)^(LOG((AD54/X54),2)) -> 541.00935 | M65: =L65-K65 -> 205.21044 | N65: 330 | O65: 530 | P65: =O65-N65 -> 200 | AK65: Middle East | AL65: =V54 -> 13.85 | AM65: =X54 -> 106.79 | AN65: =AB54 -> 440.63 | AP65: =AD54 -> 132.56 | AQ65: =AH54 -> 1028.37 | AS65: =AS64 -> 1609.87
D66: Africa | E66: 1330 | F66: 1830 | G66: =F66-E66 -> 500 | H66: 820 | I66: 1120 | J66: =I66-H66 -> 300 | K66: =H66*(0.8)^(LOG((AD60/X60),2)) -> 640.76734 | L66: =I66*(0.8)^(LOG((AD60/X60),2)) -> 875.19441 | M66: =L66-K66 -> 234.42707 | N66: 760 | O66: 950 | P66: =O66-N66 -> 190 | AK66: Africa | AL66: =V60 -> 17.04 | AM66: =X60 -> 81.43 | AN66: =AB60 -> 332.13 | AP66: =AD60 -> 175.19 | AQ66: =AH60 -> 945.41 | AS66: =AS65 -> 1609.87
D69: Global | E69: ='Summarize-ForReg(Current&2050)'!E69 -> 1094.4982 | F69: =AVERAGE(F60*AL60/AS60+F61*AL61/AS61+F62*AL62/AS62+F63*AL63/AS63+F64*AL64/AS64+F65*AL65/AS65+F66*AL66/AS66) -> 1546.3102 | G69: =F69-E69 -> 451.81196 | H69: =E69*(0.8)^(LOG((W46/V46),2)) -> 722.92644 | I69: =F69*(0.8)^(LOG((W46/V46),2)) -> 1021.3525 | J69: =I69-H69 -> 298.42609 | K69: =E69*(0.8)^(LOG((AB46/V46),2)) -> 696.85197 | L69: =F69*(0.8)^(LOG((AB46/V46),2)) -> 984.51444 | M69: =L69-K69 -> 287.66247 | N69: =E69*(0.8)^(LOG((AG46/V46),2)) -> 691.6315 | O69: =F69*(0.8)^(LOG((AG46/V46),2)) -> 977.13894 | P69: =O69-N69 -> 285.50744
B78: Costs related to CAPEX | E78: Current (2023) | F78: SPS-2030 | G78: APS-2030 | H78: NZE-2030 | I78: Recalculated but not applied | O78: 2023 | P78: 2030 | Q78: 2050
D79: Europe | E79: =(E60*0.6+F60*0.4)*AL60/1000 -> 298.61728 | F79: =(H60*0.6+I60*0.4)*AM60/1000 -> 555.75332 | G79: =(K60*0.6+L60*0.4)*AP60/1000 -> 612.73314 | N79: Solar photovoltaics - Large scale unit
D80: CSA | E80: =(E61*0.6+F61*0.4)*AL61/1000 -> 51.659581 | F80: =(H61*0.6+I61*0.4)*AM61/1000 -> 91.88167 | G80: =(K61*0.6+L61*0.4)*AP61/1000 -> 123.10831 | N80: European Union | O80: 750 | P80: 480 | Q80: 340
D81: NA | E81: =(E62*0.6+F62*0.4)*AL62/1000 -> 300.99389 | F81: =(H62*0.6+I62*0.4)*AM62/1000 -> 666.2422 | G81: =(K62*0.6+L62*0.4)*AP62/1000 -> 781.14379 | N81: United States | O81: 1 110 | P81: 690 | Q81: 480
D82: Eurasia | E82: =(E63*0.6+F63*0.4)*AL63/1000 -> 6.1154419 | F82: =(H63*0.6+I63*0.4)*AM63/1000 -> 14.745023 | G82: =(K63*0.6+L63*0.4)*AP63/1000 -> 17.238742 | N82: Japan | O82: 1 880 | P82: 1 260 | Q82: 940
D83: APJ | E83: =(E64*0.6+F64*0.4)*AL64/1000 -> 1358.8214 | F83: =(H64*0.6+I64*0.4)*AM64/1000 -> 3514.6941 | G83: =(K64*0.6+L64*0.4)*AP64/1000 -> 3641.7228 | N83: Russia | O83: 1 250 | P83: 820 | Q83: 580
D84: ME | E84: =(E65*0.6+F65*0.4)*AL65/1000 -> 10.6645 | F84: =(H65*0.6+I65*0.4)*AM65/1000 -> 47.84192 | G84: =(K65*0.6+L65*0.4)*AP65/1000 -> 55.394581 | I84: ME | N84: China | O84: 670 | P84: 410 | Q84: 280
D85: AF | E85: =(E66*0.6+F66*0.4)*AL66/1000 -> 26.0712 | F85: =(H66*0.6+I66*0.4)*AM66/1000 -> 76.5442 | G85: =(K66*0.6+L66*0.4)*AP66/1000 -> 128.68374 | I85: AF | N85: India | O85: 710 | P85: 450 | Q85: 300
D86: Global | E86: =(E69*0.6+F69*0.4)*V46/1000 -> 2052.9432 | F86: =(H69*0.6+I69*0.4)*W46/1000 -> 4917.7082 | G86: =(K69*0.6+L69*0.4)*AB46/1000 -> 5313.3145 | H86: =(N69*0.6+O69*0.4)*AG46/1000 -> 5398.1401 | N86: Middle East | O86: 610 | P86: 360 | Q86: 250 | T86: 330 | U86: 220
N87: Africa | O87: 1 330 | P87: 820 | Q87: 550 | T87: 760 | U87: 480
N88: Brazil | O88: 730 | P88: 460 | Q88: 330
N89: Solar photovoltaics - Buildings
N90: European Union | O90: 990 | P90: 650 | Q90: 470
N91: United States | O91: 3 460 | P91: 2 200 | Q91: 1 490
N92: Japan | O92: 1 850 | P92: 1 280 | Q92: 990
D93: 50-pct | E93: =(E60*0.5+F60*0.5)*AL60/1000-E79 -> 11.358539 | F93: =(H60*0.5+I60*0.5)*AM60/1000-F79 -> 21.139251 | G93: =(K60*0.5+L60*0.5)*AP60/1000-G79 -> 23.306599 | N93: Russia | O93: 1 610 | P93: 1 080 | Q93: 780
E94: =(E61*0.5+F61*0.5)*AL61/1000-E80 -> -2.8297969 | F94: =(H61*0.5+I61*0.5)*AM61/1000-F80 -> -5.0330734 | G94: =(K61*0.5+L61*0.5)*AP61/1000-G80 -> -6.7435991 | N94: China | O94: 750 | P94: 450 | Q94: 310
E95: =(E62*0.5+F62*0.5)*AL62/1000-E81 -> 19.92708 | F95: =(H62*0.5+I62*0.5)*AM62/1000-F81 -> 44.108077 | G95: =(K62*0.5+L62*0.5)*AP62/1000-G81 -> 51.715052 | N95: India | O95: 780 | P95: 490 | Q95: 330
E96: =(E63*0.5+F63*0.5)*AL63/1000-E82 -> 0.24192635 | F96: =(H63*0.5+I63*0.5)*AM63/1000-F82 -> 0.58331184 | G96: =(K63*0.5+L63*0.5)*AP63/1000-G82 -> 0.68196313 | N96: Middle East | O96: 1 010 | P96: 580 | Q96: 390 | T96: 530 | U96: 340
E97: =(E64*0.5+F64*0.5)*AL64/1000-E83 -> 42.632104 | F97: =(H64*0.5+I64*0.5)*AM64/1000-F83 -> 110.27116 | G97: =(K64*0.5+L64*0.5)*AP64/1000-G83 -> 114.2566 | N97: Africa | O97: 1 830 | P97: 1 120 | Q97: 750 | T97: 950 | U97: 620
E98: =(E65*0.5+F65*0.5)*AL65/1000-E84 -> 0.554 | F98: =(H65*0.5+I65*0.5)*AM65/1000-F84 -> 2.34938 | G98: =(K65*0.5+L65*0.5)*AP65/1000-G84 -> 2.7202696
E99: =(E66*0.5+F66*0.5)*AL66/1000-E85 -> 0.852 | F99: =(H66*0.5+I66*0.5)*AM66/1000-F85 -> 2.4429 | G99: =(K66*0.5+L66*0.5)*AP66/1000-G85 -> 4.1069279
E100: =(E69*0.5+F69*0.5)*V46/1000-E86 -> 72.735853 | F100: =(H69*0.5+I69*0.5)*W46/1000-F86 -> 174.23458 | G100: =(K69*0.5+L69*0.5)*AB46/1000-G86 -> 188.25092 | H100: =(N69*0.5+O69*0.5)*AG46/1000-H86 -> 191.2563
D103: 40-pct | E103: =E93*2 -> 22.717078 | F103: =F93*2 -> 42.278502 | G103: =G93*2 -> 46.613198
E104: =E94*2 -> -5.6595938 | F104: =F94*2 -> -10.066147 | G104: =G94*2 -> -13.487198
E105: =E95*2 -> 39.85416 | F105: =F95*2 -> 88.216154 | G105: =G95*2 -> 103.4301
E106: =E96*2 -> 0.4838527 | F106: =F96*2 -> 1.1666237 | G106: =G96*2 -> 1.3639263
E107: =E97*2 -> 85.264209 | F107: =F97*2 -> 220.54232 | G107: =G97*2 -> 228.5132
E108: =E98*2 -> 1.108 | F108: =F98*2 -> 4.69876 | G108: =G98*2 -> 5.4405393
E109: =E99*2 -> 1.704 | F109: =F99*2 -> 4.8858 | G109: =G99*2 -> 8.2138559 | J109: Baseline cost ($ billion) | K109: Current (2023) | L109: SPS-2030 | M109: SPS-2050 | N109: APS-2030 | O109: APS-2050
E110: =E100*2 -> 145.47171 | F110: =F100*2 -> 348.46916 | G110: =G100*2 -> 376.50184 | H110: =H100*2 -> 382.51259 | J110: Europe | K110: 298.61728 | L110: 555.75332 | M110: 793.11198 | N110: 612.73314 | O110: 844.41767
J111: CSA | K111: 51.659581 | L111: 91.88167 | M111: 153.84851 | N111: 123.10831 | O111: 258.7098
J112: NA | K112: 300.99389 | L112: 666.2422 | M112: 1491.8661 | N112: 781.14379 | O112: 1660.9924
D113: 30-pct | E113: =E93*3 -> 34.075617 | F113: =F93*3 -> 63.417754 | G113: =G93*3 -> 69.919797 | J113: Eurasia | K113: 6.1154419 | L113: 14.745023 | M113: 23.120381 | N113: 17.238742 | O113: 41.862734
E114: =E94*3 -> -8.4893907 | F114: =F94*3 -> -15.09922 | G114: =G94*3 -> -20.230797 | J114: APJ | K114: 1358.8214 | L114: 3514.6941 | M114: 7293.6539 | N114: 3641.7228 | O114: 7914.9628
E115: =E95*3 -> 59.781239 | F115: =F95*3 -> 132.32423 | G115: =G95*3 -> 155.14516 | J115: ME | K115: 10.6645 | L115: 47.84192 | M115: 134.83278 | N115: 49.329165 | O115: 197.8834
E116: =E96*3 -> 0.72577905 | F116: =F96*3 -> 1.7499355 | G116: =G96*3 -> 2.0458894 | J116: AF | K116: 26.0712 | L116: 76.5442 | M116: 209.2419 | N116: 126.58922 | O116: 397.02746
...

Sheet Summarize-ForReg(Current&2050)
A1: *Priciple: Exclusive the duplicate records from WEO, IEA2020, IRENA from Data of Brief; Use the record of now (preferring latest year); if there are multiple records in a same reference (except those notifying maximum or minimum value), average them to represent the figure for this reference | BD1: Baseline PV generation mix (40% rooftop vs. 60% ground-mounted)
BD2: Capital expenditure ($ billion) | BE2: 2023 | BF2: SPS-2030 | BG2: SPS-2050 | BH2: APS-2030 | BI2: APS-2050 | BJ2: NZE-2030 | BK2: NZE-2050
F3: WEO2024 (large, ground-mounted) | G3: WEO2024 (rooftop) | H3: IRENA2024 (large, ground-mounted) | I3: IEA2020 (large, ground-mounted, 3% disc-rate) | J3: IEA2020 (large, ground-mounted, 7% discount rate) | K3: IEA2020 (large, ground-mounted, 10% discount rate) | L3: IEA2020 (rooftop, 3% disc-rate) | M3: IEA2020 (rooftop, 7% discount rate) | N3: IEA2020 (rooftop, 10% discount rate) | O3: Hatton et al., 2024 (large, ground-mounted) | V3: NA | BD3: EUR | BE3: 301.27137 | BF3: 560.69282 | BG3: 800.1611 | BH3: 618.17907 | BI3: 851.92279 | BK3: -
D4: Europe | E4: EU-27 | F4: =Attached_WEO2023!B12 -> 750 | G4: =Attached_WEO2023!F12 -> 990 | O4: =AVERAGE('Attached-DIB_GNESTE_Solar_Power'!W70:W74) -> 860.90269 | X4: Stated Policies (STEPS) | AD4: Announced Pledges (APS) | BD4: CSA | BE4: 52.237595 | BF4: 92.909724 | BG4: 155.5699 | BH4: 124.48575 | BI4: 261.60448 | BK4: -
E5: Greece | H5: ='Attached-IRENA2024 report'!J20 -> 626.34564 | V5: 2023 | X5: 2030 | Y5: 2035 | Z5: 2040 | AA5: 2045 | AB5: 2050 | AD5: 2030 | AE5: 2035 | AF5: 2040 | AG5: 2045 | AH5: 2050 | BD5: NA | BE5: 301.64656 | BF5: 667.68688 | BG5: 1495.101 | BH5: 782.83762 | BI5: 1664.5941 | BK5: -
E6: Netherlands | H6: ='Attached-IRENA2024 report'!J22 -> 753.19994 | I6: ='Attached-IEA2020Projected Costs'!K39 -> 819.39997 | J6: ='Attached-IEA2020Projected Costs'!L39 -> 835.15911 | K6: ='Attached-IEA2020Projected Costs'!M39 -> 846.78601 | L6: ='Attached-IEA2020Projected Costs'!K38 -> 858.48319 | M6: ='Attached-IEA2020Projected Costs'!L38 -> 874.994 | N6: ='Attached-IEA2020Projected Costs'!M38 -> 887.17547 | O6: =AVERAGE('Attached-DIB_GNESTE_Solar_Power'!V66:V68) -> 787.41448 | V6: 188.55 | X6: 608.6 | Y6: 973.35 | Z6: 1356.32 | AA6: 1718.79 | AB6: 1998.23 | AD6: 769.55 | AE6: 1311.5 | AF6: 1768.76 | AG6: 2146.99 | AH6: 2341.13 | BD6: Eurasia | BE6: 7.6758419 | BF6: 18.507324 | BG6: 29.019717 | BH6: 21.637334 | BI6: 52.544319 | BK6: -
E7: Germany | H7: ='Attached-IRENA2024 report'!J24 -> 730.77006 | O7: =AVERAGE('Attached-DIB_GNESTE_Solar_Power'!X89:X90) -> 757.7542 | BD7: APJ | BE7: 1358.9988 | BF7: 3515.1532 | BG7: 7294.6065 | BH7: 3642.1984 | BI7: 7915.9966 | BK7: -
E8: United Kingdom | H8: ='Attached-IRENA2024 report'!J26 -> 932.69058 | BD8: ME | BE8: 10.803 | BF8: 43.156772 | BG8: 134.83278 | BH8: 49.969803 | BI8: 200.45331 | BK8: -
E9: Portugal | H9: ='Attached-IRENA2024 report'!J28 -> 723.26964 | BD9: AF | BE9: 27.9456 | BF9: 80.711933 | BG9: 217.87728 | BH9: 135.69041 | BI9: 425.57191 | BK9: -
E10: France | H10: ='Attached-IRENA2024 report'!J30 -> 954.78012 | I10: {='Attached-IEA2020Projected Costs'!K21:M21} -> 718.7719 | J10: 732.59571 | K10: 742.79475 | L10: =AVERAGE('Attached-IEA2020Projected Costs'!K19:K20) -> 1293.7894 | M10: =AVERAGE('Attached-IEA2020Projected Costs'!L19:L20) -> 1318.6723 | N10: =AVERAGE('Attached-IEA2020Projected Costs'!M19:M20) -> 1337.0305 | V10: CSA | BD10: Global | BE10: 1809.9278 | BF10: 4335.5785 | BG10: 8749.8537 | BH10: 4684.3552 | BI10: 10011.42 | BJ10: 4759.1397 | BK10: 10532.937
E11: Italy | H11: ='Attached-IRENA2024 report'!J32 -> 821.34079 | I11: =AVERAGE('Attached-IEA2020Projected Costs'!K31:K32) -> 844.08816 | J11: =AVERAGE('Attached-IEA2020Projected Costs'!L31:L32) -> 860.32211 | K11: =AVERAGE('Attached-IEA2020Projected Costs'!M31:M32) -> 872.29933 | L11: =AVERAGE('Attached-IEA2020Projected Costs'!K26:K30) -> 1347.0298 | M11: =AVERAGE('Attached-IEA2020Projected Costs'!L26:L30) -> 1372.9366 | N11: =AVERAGE('Attached-IEA2020Projected Costs'!M26:M30) -> 1392.0503 | X11: Stated Policies (STEPS) | AD11: Announced Pledges (APS) | BD11: 50% rooftop, 50% ground-mounted
E12: Spain | H12: ='Attached-IRENA2024 report'!J57 -> 670.76717 | V12: 2023 | X12: 2030 | Y12: 2035 | Z12: 2040 | AA12: 2045 | AB12: 2050 | AD12: 2030 | AE12: 2035 | AF12: 2040 | AG12: 2045 | AH12: 2050 | BD12: EUR | BE12: 11.615989 | BF12: 21.618388 | BG12: 30.851462 | BH12: 23.834861 | BI12: 32.847215 | BK12: - | BM12: =BE3+BE12 -> 312.88736 | BN12: =BF3+BF12 -> 582.31121 | BO12: =BG3+BG12 -> 831.01256 | BP12: =BH3+BH12 -> 642.01393 | BQ12: =BI3+BI12 -> 884.77 | BR12: - | BS12: -
E13: Turkey | H13: ='Attached-IRENA2024 report'!J58 -> 715.36 | V13: 61.93 | X13: 144.78 | Y13: 176.87 | Z13: 219.78 | AA13: 258.21 | AB13: 309.64 | AD13: 222.89 | AE13: 321.92 | AF13: 432.17 | AG13: 534.61 | AH13: 666.41 | BD13: CSA | BE13: -2.7196991 | BF13: -4.8372536 | BG13: -8.0995944 | BH13: -6.4812286 | BI13: -13.620181 | BK13: - | BM13: =BE4+BE13 -> 49.517896 | BN13: =BF4+BF13 -> 88.072471 | BO13: =BG4+BG13 -> 147.47031 | BP13: =BH4+BH13 -> 118.00452 | BQ13: =BI4+BI13 -> 247.9843 | BR13: - | BS13: -
E14: Hungary | H14: ='Attached-IRENA2024 report'!J62 -> 1078 | I14: ='Attached-IEA2020Projected Costs'!K25 -> 978.03747 | J14: ='Attached-IEA2020Projected Costs'!L25 -> 996.84761 | K14: ='Attached-IEA2020Projected Costs'!M25 -> 1010.7255 | L14: =AVERAGE('Attached-IEA2020Projected Costs'!K22:K24) -> 1445.272 | M14: =AVERAGE('Attached-IEA2020Projected Costs'!L22:L24) -> 1473.0682 | N14: =AVERAGE('Attached-IEA2020Projected Costs'!M22:M24) -> 1493.5759 | BD14: NA | BE14: 20.053988 | BF14: 44.388986 | BG14: 99.396918 | BH14: 52.044407 | BI14: 110.66512 | BK14: - | BM14: =BE5+BE14 -> 321.70055 | BN14: =BF5+BF14 -> 712.07586 | BO14: =BG5+BG14 -> 1594.4979 | BP14: =BH5+BH14 -> 834.88202 | BQ14: =BI5+BI14 -> 1775.2592 | BR14: - | BS14: -
E15: Belgium | H15: ='Attached-IRENA2024 report'!J63 -> 965 | I15: ='Attached-IEA2020Projected Costs'!K12 -> 1006.2807 | J15: ='Attached-IEA2020Projected Costs'!L12 -> 1025.634 | K15: ='Attached-IEA2020Projected Costs'!M12 -> 1039.9126 | L15: =AVERAGE('Attached-IEA2020Projected Costs'!K9:K11) -> 1419.3349 | M15: =AVERAGE('Attached-IEA2020Projected Costs'!L9:L11) -> 1446.6323 | N15: =AVERAGE('Attached-IEA2020Projected Costs'!M9:M11) -> 1466.772 | BD15: Eurasia | BE15: 0.45185968 | BF15: 1.0894849 | BG15: 1.708326 | BH15: 1.2737416 | BI15: 3.0931668 | BK15: - | BM15: =BE6+BE15 -> 8.1277016 | BN15: =BF6+BF15 -> 19.596809 | BO15: =BG6+BG15 -> 30.728043 | BP15: =BH6+BH15 -> 22.911075 | BQ15: =BI6+BI15 -> 55.637486 | BR15: - | BS15: -
E16: Cyprus | H16: ='Attached-IRENA2024 report'!J64 -> 854 | V16: EUR | BD16: APJ | BE16: 42.602525 | BF16: 110.19465 | BG16: 228.6747 | BH16: 114.17732 | BI16: 248.15433 | BK16: - | BM16: =BE7+BE16 -> 1401.6014 | BN16: =BF7+BF16 -> 3625.3478 | BO16: =BG7+BG16 -> 7523.2812 | BP16: =BH7+BH16 -> 3756.3758 | BQ16: =BI7+BI16 -> 8164.1509 | BR16: - | BS16: -
E17: Slovakia | H17: ='Attached-IRENA2024 report'!J65 -> 844 | X17: Stated Policies (STEPS) | AD17: Announced Pledges (APS) | BD17: ME | BE17: 0.554 | BF17: 2.2131678 | BG17: 6.16882 | BH17: 2.562554 | BI17: 10.279657 | BK17: - | BM17: =BE8+BE17 -> 11.357 | BN17: =BF8+BF17 -> 45.36994 | BO17: =BG8+BG17 -> 141.0016 | BP17: =BH8+BH17 -> 52.532357 | BQ17: =BI8+BI17 -> 210.73297 | BR17: - | BS17: -
E18: Romania | H18: ='Attached-IRENA2024 report'!J67 -> 743 | V18: 2023 | X18: 2030 | Y18: 2035 | Z18: 2040 | AA18: 2045 | AB18: 2050 | AD18: 2030 | AE18: 2035 | AF18: 2040 | AG18: 2045 | AH18: 2050 | BD18: AF | BE18: 0.9372 | BF18: 2.7068026 | BG18: 6.31047 | BH18: 4.5505929 | BI18: 14.272229 | BK18: - | BM18: =BE9+BE18 -> 28.8828 | BN18: =BF9+BF18 -> 83.418736 | BO18: =BG9+BG18 -> 224.18775 | BP18: =BH9+BH18 -> 140.241 | BQ18: =BI9+BI18 -> 439.84414 | BR18: - | BS18: -
E19: Latvia | H19: ='Attached-IRENA2024 report'!J68 -> 716 | V19: 318.09 | X19: 795.05 | Y19: 1069.78 | Z19: 1216.75 | AA19: 1302.64 | AB19: 1343.31 | AD19: 918.14 | AE19: 1214.27 | AF19: 1349.99 | AG19: 1431.75 | AH19: 1473.41 | BD19: Global | BE19: 115.27104 | BF19: 276.12518 | BG19: 557.26241 | BH19: 298.33814 | BI19: 637.60927 | BJ19: 303.10103 | BK19: 670.8238 | BM19: =BE10+BE19 -> 1925.1988 | BN19: =BF10+BF19 -> 4611.7037 | BO19: =BG10+BG19 -> 9307.1161 | BP19: =BH10+BH19 -> 4982.6933 | BQ19: =BI10+BI19 -> 10649.029 | BR19: =BJ10+BJ19 -> 5062.2407 | BS19: =BK10+BK19 -> 11203.761
E20: Estonia | H20: ='Attached-IRENA2024 report'!J69 -> 705 | BD20: 60% rooftop, 40% ground-mounted
E21: Poland | H21: ='Attached-IRENA2024 report'!J70 -> 700 | BD21: EUR | BE21: 23.231978 | BF21: 43.236777 | BG21: 61.702925 | BH21: 47.669721 | BI21: 65.694431 | BK21: - | BM21: =BE3+BE21 -> 324.50335 | BN21: =BF3+BF21 -> 603.92959 | BO21: =BG3+BG21 -> 861.86403 | BP21: =BH3+BH21 -> 665.84879 | BQ21: =BI3+BI21 -> 917.61722 | BR21: - | BS21: -
E22: Ireland | H22: ='Attached-IRENA2024 report'!J71 -> 686 | V22: Eurasia | BD22: CSA | BE22: -5.4393983 | BF22: -9.6745073 | BG22: -16.199189 | BH22: -12.962457 | BI22: -27.240361 | BK22: - | BM22: =BE4+BE22 -> 46.798197 | BN22: =BF4+BF22 -> 83.235217 | BO22: =BG4+BG22 -> 139.37072 | BP22: =BH4+BH22 -> 111.5233 | BQ22: =BI4+BI22 -> 234.36412 | BR22: - | BS22: -
E23: Luxembourg | H23: ='Attached-IRENA2024 report'!J72 -> 684 | X23: Stated Policies (STEPS) | AD23: Announced Pledges (APS) | BD23: NA | BE23: 40.107977 | BF23: 88.777972 | BG23: 198.79384 | BH23: 104.08881 | BI23: 221.33023 | BK23: - | BM23: =BE5+BE23 -> 341.75454 | BN23: =BF5+BF23 -> 756.46485 | BO23: =BG5+BG23 -> 1693.8949 | BP23: =BH5+BH23 -> 886.92643 | BQ23: =BI5+BI23 -> 1885.9244 | BR23: - | BS23: -
E24: Austria | H24: ='Attached-IRENA2024 report'!J73 -> 678 | I24: ='Attached-IEA2020Projected Costs'!K6 -> 729.55348 | J24: ='Attached-IEA2020Projected Costs'!L6 -> 743.58464 | K24: ='Attached-IEA2020Projected Costs'!M6 -> 753.93667 | L24: ='Attached-IEA2020Projected Costs'!K6 -> 729.55348 | M24: ='Attached-IEA2020Projected Costs'!L6 -> 743.58464 | N24: ='Attached-IEA2020Projected Costs'!M6 -> 753.93667 | V24: 2023 | X24: 2030 | Y24: 2035 | Z24: 2040 | AA24: 2045 | AB24: 2050 | AD24: 2030 | AE24: 2035 | AF24: 2040 | AG24: 2045 | AH24: 2050 | BD24: Eurasia | BE24: 0.90371937 | BF24: 2.1789698 | BG24: 3.4166519 | BH24: 2.5474831 | BI24: 6.1863336 | BK24: - | BM24: =BE6+BE24 -> 8.5795613 | BN24: =BF6+BF24 -> 20.686294 | BO24: =BG6+BG24 -> 32.436369 | BP24: =BH6+BH24 -> 24.184817 | BQ24: =BI6+BI24 -> 58.730652 | BR24: - | BS24: -
E25: Czech Republic | H25: ='Attached-IRENA2024 report'!J74 -> 663 | V25: 4.7 | X25: 17.21 | Y25: 22.8 | Z25: 27.15 | AA25: 30.57 | AB25: 33.41 | AD25: 21.67 | AE25: 36.9 | AF25: 51.96 | AG25: 65.8 | AH25: 80.19 | BD25: APJ | BE25: 85.205049 | BF25: 220.3893 | BG25: 457.34941 | BH25: 228.35465 | BI25: 496.30865 | BK25: - | BM25: =BE7+BE25 -> 1444.2039 | BN25: =BF7+BF25 -> 3735.5425 | BO25: =BG7+BG25 -> 7751.9559 | BP25: =BH7+BH25 -> 3870.5531 | BQ25: =BI7+BI25 -> 8412.3052 | BR25: - | BS25: -
E26: Bulgaria | H26: ='Attached-IRENA2024 report'!J75 -> 659 | BD26: ME | BE26: 1.108 | BF26: 4.4263356 | BG26: 12.33764 | BH26: 5.125108 | BI26: 20.559314 | BK26: - | BM26: =BE8+BE26 -> 11.911 | BN26: =BF8+BF26 -> 47.583108 | BO26: =BG8+BG26 -> 147.17042 | BP26: =BH8+BH26 -> 55.094911 | BQ26: =BI8+BI26 -> 221.01263 | BR26: - | BS26: -
E27: Denmark | I27: =AVERAGE('Attached-IEA2020Projected Costs'!K17:K18) -> 587.43464 | J27: =AVERAGE('Attached-IEA2020Projected Costs'!L17:L18) -> 598.7325 | K27: =AVERAGE('Attached-IEA2020Projected Costs'!M17:M18) -> 607.06792 | L27: =AVERAGE('Attached-IEA2020Projected Costs'!K15:K16) -> 1026.7533 | M27: =AVERAGE('Attached-IEA2020Projected Costs'!L15:L16) -> 1046.5004 | N27: =AVERAGE('Attached-IEA2020Projected Costs'!M15:M16) -> 1061.0695 | BD27: AF | BE27: 1.8744 | BF27: 5.4136053 | BG27: 12.62094 | BH27: 9.1011857 | BI27: 28.544458 | BK27: - | BM27: =BE9+BE27 -> 29.82 | BN27: =BF9+BF27 -> 86.125538 | BO27: =BG9+BG27 -> 230.49822 | BP27: =BH9+BH27 -> 144.79159 | BQ27: =BI9+BI27 -> 454.11637 | BR27: - | BS27: -
E28: Norway | L28: ='Attached-IEA2020Projected Costs'!K40 -> 998.35392 | M28: ='Attached-IEA2020Projected Costs'!L40 -> 1017.5548 | N28: ='Attached-IEA2020Projected Costs'!M40 -> 1031.721 | V28: APJ | BD28: Global | BE28: 230.54207 | BF28: 552.25036 | BG28: 1114.5248 | BH28: 596.67628 | BI28: 1275.2185 | BJ28: 606.20205 | BK28: 1341.6476 | BM28: =BE10+BE28 -> 2040.4698 | BN28: =BF10+BF28 -> 4887.8289 | BO28: =BG10+BG28 -> 9864.3785 | BP28: =BH10+BH28 -> 5281.0315 | BQ28: =BI10+BI28 -> 11286.638 | BR28: =BJ10+BJ28 -> 5365.3417 | BS28: =BK10+BK28 -> 11874.585
E29: Croatia | X29: Stated Policies (STEPS) | AD29: Announced Pledges (APS) | BD29: 70% rooftop, 30% ground-mounted
D30: South America | E30: Chile | H30: ='Attached-IRENA2024 report'!J50 -> 953.80679 | V30: 2023 | X30: 2030 | Y30: 2035 | Z30: 2040 | AA30: 2045 | AB30: 2050 | AD30: 2030 | AE30: 2035 | AF30: 2040 | AG30: 2045 | AH30: 2050 | BD30: EUR | BE30: 34.847966 | BF30: 64.855165 | BG30: 92.554387 | BH30: 71.504582 | BI30: 98.541646 | BK30: - | BM30: =BE3+BE30 -> 336.11934 | BN30: =BF3+BF30 -> 625.54798 | BO30: =BG3+BG30 -> 892.71549 | BP30: =BH3+BH30 -> 689.68365 | BQ30: =BI3+BI30 -> 950.46444 | BR30: - | BS30: -
E31: Argentina | H31: ='Attached-IRENA2024 report'!J53 -> 830 | V31: 1005.71 | X31: 4084.58 | Y31: 6629.81 | Z31: 9040.8 | AA31: 11049.3 | AB31: 11987.66 | AD31: 4304.15 | AE31: 7182.92 | AF31: 10076.95 | AG31: 12366.68 | AH31: 13523.66 | BD31: CSA | BE31: -8.1590974 | BF31: -14.511761 | BG31: -24.298783 | BH31: -19.443686 | BI31: -40.860542 | BK31: - | BM31: =BE4+BE31 -> 44.078497 | BN31: =BF4+BF31 -> 78.397963 | BO31: =BG4+BG31 -> 131.27112 | BP31: =BH4+BH31 -> 105.04207 | BQ31: =BI4+BI31 -> 220.74394 | BR31: - | BS31: -
E32: Brazil | F32: =Attached_WEO2023!B18 -> 730 | G32: =Attached_WEO2023!F18 -> 560 | H32: ='Attached-IRENA2024 report'!J48 -> 726.98559 | I32: ='Attached-IEA2020Projected Costs'!K60 -> 1215.2033 | J32: ='Attached-IEA2020Projected Costs'!L60 -> 1238.5747 | K32: ='Attached-IEA2020Projected Costs'!M60 -> 1255.8179 | O32: ='Attached-DIB_GNESTE_Solar_Power'!V134 -> 1382.1652 | BD32: NA | BE32: 60.161965 | BF32: 133.16696 | BG32: 298.19075 | BH32: 156.13322 | BI32: 331.99535 | BK32: - | BM32: =BE5+BE32 -> 361.80853 | BN32: =BF5+BF32 -> 800.85383 | BO32: =BG5+BG32 -> 1793.2918 | BP32: =BH5+BH32 -> 938.97084 | BQ32: =BI5+BI32 -> 1996.5895 | BR32: - | BS32: -
E33: South America | O33: ='Attached-DIB_GNESTE_Solar_Power'!AA338 -> 819.85934 | BD33: Eurasia | BE33: 1.3555791 | BF33: 3.2684546 | BG33: 5.1249779 | BH33: 3.8212247 | BI33: 9.2795004 | BK33: - | BM33: =BE6+BE33 -> 9.0314209 | BN33: =BF6+BF33 -> 21.775779 | BO33: =BG6+BG33 -> 34.144695 | BP33: =BH6+BH33 -> 25.458558 | BQ33: =BI6+BI33 -> 61.823819 | BR33: - | BS33: -
D34: North America | E34: United States | F34: =Attached_WEO2023!B13 -> 1110 | G34: =Attached_WEO2023!F13 -> 3460 | H34: ='Attached-IRENA2024 report'!J42 -> 1108.5304 | I34: =AVERAGE('Attached-IEA2020Projected Costs'!K51:K55) -> 1087.637 | J34: =AVERAGE('Attached-IEA2020Projected Costs'!L51:L55) -> 1108.555 | K34: =AVERAGE('Attached-IEA2020Projected Costs'!M51:M55) -> 1123.9881 | L34: =AVERAGE('Attached-IEA2020Projected Costs'!K41:K50) -> 1789.2317 | M34: =AVERAGE('Attached-IEA2020Projected Costs'!L41:L50) -> 1823.6432 | N34: =AVERAGE('Attached-IEA2020Projected Costs'!M41:M50) -> 1849.0316 | O34: =AVERAGE('Attached-DIB_GNESTE_Solar_Power'!V15,'Attached-DIB_GNESTE_Solar_Power'!Z17:Z310,'Attached-DIB_GNESTE_Solar_Power'!AB313:AB315,'Attached-DIB_GNESTE_Solar_Power'!Z319,'Attached-DIB_GNESTE_Solar_Power'!X325,'Attached-DIB_GNESTE_Solar_Power'!Y326,'Attached-DIB_GNESTE_Solar_Power'!X331,'Attached-DIB_GNESTE_Solar_Power'!Y332) -> 1349.0303 | BD34: APJ | BE34: 127.80757 | BF34: 330.58395 | BG34: 686.02411 | BH34: 342.53197 | BI34: 744.46298 | BK34: - | BM34: =BE7+BE34 -> 1486.8064 | BN34: =BF7+BF34 -> 3845.7371 | BO34: =BG7+BG34 -> 7980.6306 | BP34: =BH7+BH34 -> 3984.7304 | BQ34: =BI7+BI34 -> 8660.4595 | BR34: - | BS34: -
E35: Canada | H35: ='Attached-IRENA2024 report'!J38 -> 1336.5221 | I35: =AVERAGE('Attached-IEA2020Projected Costs'!K13:K14) -> 1328.7693 | J35: =AVERAGE('Attached-IEA2020Projected Costs'!L13:L14) -> 1354.3249 | K35: =AVERAGE('Attached-IEA2020Projected Costs'!M13:M14) -> 1373.1795 | BD35: ME | BE35: 1.662 | BF35: 6.6395034 | BG35: 18.50646 | BH35: 7.687662 | BI35: 30.838971 | BK35: - | BM35: =BE8+BE35 -> 12.465 | BN35: =BF8+BF35 -> 49.796275 | BO35: =BG8+BG35 -> 153.33924 | BP35: =BH8+BH35 -> 57.657465 | BQ35: =BI8+BI35 -> 231.29228 | BR35: - | BS35: -
E36: Mexico | H36: ='Attached-IRENA2024 report'!J40 -> 1049.5172 | O36: ='Attached-DIB_GNESTE_Solar_Power'!V137 -> 990.405 | V36: ASEAN | BD36: AF | BE36: 2.8116 | BF36: 8.1204079 | BG36: 18.93141 | BH36: 13.651779 | BI36: 42.816687 | BK36: - | BM36: =BE9+BE36 -> 30.7572 | BN36: =BF9+BF36 -> 88.832341 | BO36: =BG9+BG36 -> 236.80869 | BP36: =BH9+BH36 -> 149.34218 | BQ36: =BI9+BI36 -> 468.3886 | BR36: - | BS36: -
E37: North America | O37: ='Attached-DIB_GNESTE_Solar_Power'!AA337 -> 936.56791 | X37: Stated Policies (STEPS) | AD37: Announced Pledges (APS) | BD37: Global | BE37: 345.81311 | BF37: 828.37554 | BG37: 1671.7872 | BH37: 895.01442 | BI37: 1912.8278 | BJ37: 909.30308 | BK37: 2012.4714 | BM37: =BE10+BE37 -> 2155.7409 | BN37: =BF10+BF37 -> 5163.954 | BO37: =BG10+BG37 -> 10421.641 | BP37: =BH10+BH37 -> 5579.3696 | BQ37: =BI10+BI37 -> 11924.247 | BR37: =BJ10+BJ37 -> 5668.4427 | BS37: =BK10+BK37 -> 12545.409
D38: Eurasia | E38: Russia | F38: =Attached_WEO2023!B15 -> 1250 | G38: =Attached_WEO2023!F15 -> 1610 | H38: ='Attached-IRENA2024 report'!J83 -> 1248 | O38: ='Attached-DIB_GNESTE_Solar_Power'!AA341 -> 787.78925 | V38: 2023 | X38: 2030 | Y38: 2035 | Z38: 2040 | AA38: 2045 | AB38: 2050 | AD38: 2030 | AE38: 2035 | AF38: 2040 | AG38: 2045 | AH38: 2050 | BD38: 80% rooftop, 20% ground-mounted
D39: Asia Pacific | E39: Japan | F39: =Attached_WEO2023!B14 -> 1880 | G39: =Attached_WEO2023!F14 -> 1850 | H39: ='Attached-IRENA2024 report'!J15 -> 1875.2399 | I39: ='Attached-IEA2020Projected Costs'!K34 -> 2035.9917 | J39: ='Attached-IEA2020Projected Costs'!L34 -> 2075.149 | K39: ='Attached-IEA2020Projected Costs'!M34 -> 2104.0388 | L39: ='Attached-IEA2020Projected Costs'!K33 -> 2367.4727 | M39: ='Attached-IEA2020Projected Costs'!L33 -> 2413.0052 | N39: ='Attached-IEA2020Projected Costs'!M33 -> 2446.5985 | V39: 32.13 | X39: 82.67 | Y39: 150.99 | Z39: 236.9 | AA39: 319.85 | AB39: 408.09 | AD39: 165.71 | AE39: 368.34 | AF39: 669.78 | AG39: 898.17 | AH39: 1074.26 | BD39: EUR | BE39: 46.463955 | BF39: 86.473553 | BG39: 123.40585 | BH39: 95.339442 | BI39: 131.38886 | BK39: - | BM39: =BE3+BE39 -> 347.73533 | BN39: =BF3+BF39 -> 647.16637 | BO39: =BG3+BG39 -> 923.56695 | BP39: =BH3+BH39 -> 713.51851 | BQ39: =BI3+BI39 -> 983.31165 | BR39: - | BS39: -
E40: China | F40: =Attached_WEO2023!B16 -> 670 | G40: =Attached_WEO2023!F16 -> 750 | H40: ='Attached-IRENA2024 report'!J11 -> 671.12616 | I40: ='Attached-IEA2020Projected Costs'!K61 -> 741.29534 | J40: ='Attached-IEA2020Projected Costs'!L61 -> 755.55232 | K40: ='Attached-IEA2020Projected Costs'!M61 -> 766.07096 | O40: ='Attached-DIB_GNESTE_Solar_Power'!AA342 -> 694.64666 | BD40: CSA | BE40: -10.878797 | BF40: -19.349015 | BG40: -32.398378 | BH40: -25.924914 | BI40: -54.480722 | BK40: - | BM40: =BE4+BE40 -> 41.358798 | BN40: =BF4+BF40 -> 73.56071 | BO40: =BG4+BG40 -> 123.17153 | BP40: =BH4+BH40 -> 98.560838 | BQ40: =BI4+BI40 -> 207.12376 | BR40: - | BS40: -
E41: India | F41: =Attached_WEO2023!B17 -> 710 | G41: =Attached_WEO2023!F17 -> 780 | H41: ='Attached-IRENA2024 report'!J13 -> 711.32819 | I41: ='Attached-IEA2020Projected Costs'!K62 -> 638.03526 | J41: ='Attached-IEA2020Projected Costs'!L62 -> 650.30629 | K41: ='Attached-IEA2020Projected Costs'!M62 -> 659.35972 | O41: =AVERAGE('Attached-DIB_GNESTE_Solar_Power'!W25,'Attached-DIB_GNESTE_Solar_Power'!V135,'Attached-DIB_GNESTE_Solar_Power'!AA343) -> 670.57179 | BD41: NA | BE41: 80.215954 | BF41: 177.55594 | BG41: 397.58767 | BH41: 208.17763 | BI41: 442.66046 | BK41: - | BM41: =BE5+BE41 -> 381.86251 | BN41: =BF5+BF41 -> 845.24282 | BO41: =BG5+BG41 -> 1892.6887 | BP41: =BH5+BH41 -> 991.01525 | BQ41: =BI5+BI41 -> 2107.2546 | BR41: - | BS41: -
E42: Republic of Korea | H42: ='Attached-IRENA2024 report'!J17 -> 1205.2601 | I42: ='Attached-IEA2020Projected Costs'!K36 -> 1244.0419 | J42: ='Attached-IEA2020Projected Costs'!L36 -> 1267.9679 | K42: ='Attached-IEA2020Projected Costs'!M36 -> 1285.6203 | L42: ='Attached-IEA2020Projected Costs'!K35 -> 1258.5589 | M42: ='Attached-IEA2020Projected Costs'!L35 -> 1282.7641 | N42: ='Attached-IEA2020Projected Costs'!M35 -> 1300.6225 | BD42: Eurasia | BE42: 1.8074387 | BF42: 4.3579395 | BG42: 6.8333039 | BH42: 5.0949662 | BI42: 12.372667 | BK42: - | BM42: =BE6+BE42 -> 9.4832806 | BN42: =BF6+BF42 -> 22.865264 | BO42: =BG6+BG42 -> 35.853021 | BP42: =BH6+BH42 -> 26.7323 | BQ42: =BI6+BI42 -> 64.916986 | BR42: - | BS42: -
E43: Australia | H43: ='Attached-IRENA2024 report'!J45 -> 988.62812 | I43: ='Attached-IEA2020Projected Costs'!K7 -> 895.14787 | J43: ='Attached-IEA2020Projected Costs'!L7 -> 912.36383 | K43: ='Attached-IEA2020Projected Costs'!M7 -> 925.06556 | O43: =AVERAGE('Attached-DIB_GNESTE_Solar_Power'!AA19:AA21) -> 932.2705 | V43: World | BD43: APJ | BE43: 170.4101 | BF43: 440.7786 | BG43: 914.69881 | BH43: 456.70929 | BI43: 992.6173 | BK43: - | BM43: =BE7+BE43 -> 1529.4089 | BN43: =BF7+BF43 -> 3955.9318 | BO43: =BG7+BG43 -> 8209.3053 | BP43: =BH7+BH43 -> 4098.9077 | BQ43: =BI7+BI43 -> 8908.6139 | BR43: - | BS43: -
E44: Indonesia | H44: ='Attached-IRENA2024 report'!J78 -> 798 | O44: =AVERAGE('Attached-DIB_GNESTE_Solar_Power'!V3:V4,'Attached-DIB_GNESTE_Solar_Power'!V133) -> 1913.4028 | W44: Stated Policies (GW) | AB44: Announced Pledges (GW) | AG44: Net Zero Emissions by 2050 (GW) | BD44: ME | BE44: 2.216 | BF44: 8.8526712 | BG44: 24.67528 | BH44: 10.250216 | BI44: 41.118628 | BK44: - | BM44: =BE8+BE44 -> 13.019 | BN44: =BF8+BF44 -> 52.009443 | BO44: =BG8+BG44 -> 159.50806 | BP44: =BH8+BH44 -> 60.220019 | BQ44: =BI8+BI44 -> 241.57194 | BR44: - | BS44: -
E45: Malaysia | O45: =AVERAGE('Attached-DIB_GNESTE_Solar_Power'!V5:V6) -> 2262.804 | V45: 2023 | W45: 2030 | X45: 2035 | Y45: 2040 | Z45: 2045 | AA45: 2050 | AB45: 2030 | AC45: 2035 | AD45: 2040 | AE45: 2045 | AF45: 2050 | AG45: 2030 | AH45: 2035 | AI45: 2040 | AJ45: 2045 | AK45: 2050 | BD45: AF | BE45: 3.7488 | BF45: 10.827211 | BG45: 25.24188 | BH45: 18.202371 | BI45: 57.088915 | BK45: - | BM45: =BE9+BE45 -> 31.6944 | BN45: =BF9+BF45 -> 91.539144 | BO45: =BG9+BG45 -> 243.11916 | BP45: =BH9+BH45 -> 153.89278 | BQ45: =BI9+BI45 -> 482.66083 | BR45: - | BS45: -
E46: Philippines | O46: =AVERAGE('Attached-DIB_GNESTE_Solar_Power'!V7:V8) -> 2229.198 | V46: 1609.87 | W46: 5838.45 | X46: 9203.17 | Y46: 12333.11 | Z46: 14972.81 | AA46: 16445.01 | AB46: 6544.16 | AC46: 10792.62 | AD46: 14800.73 | AE46: 18066.24 | AF46: 20058.6 | AG46: 6698.82 | AH46: 12044.04 | AI46: 16455.02 | AJ46: 19462.09 | AK46: 21618.47 | BD46: Global | BE46: 461.08415 | BF46: 1104.5007 | BG46: 2229.0496 | BH46: 1193.3526 | BI46: 2550.4371 | BJ46: 1212.4041 | BK46: 2683.2952 | BM46: =BE10+BE46 -> 2271.0119 | BN46: =BF10+BF46 -> 5440.0792 | BO46: =BG10+BG46 -> 10978.903 | BP46: =BH10+BH46 -> 5877.7077 | BQ46: =BI10+BI46 -> 12561.857 | BR46: =BJ10+BJ46 -> 5971.5438 | BS46: =BK10+BK46 -> 13216.233
E47: Thailand | O47: =AVERAGE('Attached-DIB_GNESTE_Solar_Power'!V136) -> 1108.1532 | BD47: 90% rooftop, 10% ground-mounted
E48: Asia | O48: ='Attached-DIB_GNESTE_Solar_Power'!V11 -> 2254.9626 | BD48: EUR | BE48: 58.079944 | BF48: 108.09194 | BG48: 154.25731 | BH48: 119.1743 | BI48: 164.23608 | BK48: - | BM48: =BE3+BE48 -> 359.35132 | BN48: =BF3+BF48 -> 668.78476 | BO48: =BG3+BG48 -> 954.41841 | BP48: =BH3+BH48 -> 737.35337 | BQ48: =BI3+BI48 -> 1016.1589 | BR48: - | BS48: -
E49: Southeast Asia | O49: ='Attached-DIB_GNESTE_Solar_Power'!AA344 -> 718.76686 | BD49: CSA | BE49: -13.598496 | BF49: -24.186268 | BG49: -40.497972 | BH49: -32.406143 | BI49: -68.100903 | BK49: - | BM49: =BE4+BE49 -> 38.639099 | BN49: =BF4+BF49 -> 68.723456 | BO49: =BG4+BG49 -> 115.07193 | BP49: =BH4+BH49 -> 92.07961 | BQ49: =BI4+BI49 -> 193.50358 | BR49: - | BS49: -
E50: OECD Asia & Oceania | O50: ='Attached-DIB_GNESTE_Solar_Power'!AA345 -> 922.20862 | BD50: NA | BE50: 100.26994 | BF50: 221.94493 | BG50: 496.98459 | BH50: 260.22204 | BI50: 553.32558 | BK50: - | BM50: =BE5+BE50 -> 401.9165 | BN50: =BF5+BF50 -> 889.6318 | BO50: =BG5+BG50 -> 1992.0856 | BP50: =BH5+BH50 -> 1043.0597 | BQ50: =BI5+BI50 -> 2217.9197 | BR50: - | BS50: -
D51: Global | H51: ='Attached-IRENA2024 report'!AB11 -> 757.68783 | O51: =AVERAGE('Attached-DIB_GNESTE_Solar_Power'!W76:W322) -> 918.0296 | BD51: Eurasia | BE51: 2.2592984 | BF51: 5.4474244 | BG51: 8.5416299 | BH51: 6.3687078 | BI51: 15.465834 | BK51: - | BM51: =BE6+BE51 -> 9.9351403 | BN51: =BF6+BF51 -> 23.954749 | BO51: =BG6+BG51 -> 37.561347 | BP51: =BH6+BH51 -> 28.006041 | BQ51: =BI6+BI51 -> 68.010153 | BR51: - | BS51: -
V52: ME | W52: Historical | AA52: Stated Policies (STEPS) | AF52: Announced Pledges (APS) | BD52: APJ | BE52: 213.01262 | BF52: 550.97325 | BG52: 1143.3735 | BH52: 570.88662 | BI52: 1240.7716 | BK52: - | BM52: =BE7+BE52 -> 1572.0115 | BN52: =BF7+BF52 -> 4066.1264 | BO52: =BG7+BG52 -> 8437.98 | BP52: =BH7+BH52 -> 4213.0851 | BQ52: =BI7+BI52 -> 9156.7682 | BR52: - | BS52: -
W53: 2010 | X53: 2015 | Y53: 2022 | Z53: 2023 | AA53: 2030 | AB53: 2035 | AC53: 2040 | AD53: 2045 | AE53: 2050 | AF53: 2030 | AG53: 2035 | AH53: 2040 | AI53: 2045 | AJ53: 2050 | BD53: ME | BE53: 2.77 | BF53: 11.065839 | BG53: 30.8441 | BH53: 12.81277 | BI53: 51.398285 | BK53: - | BM53: =BE8+BE53 -> 13.573 | BN53: =BF8+BF53 -> 54.222611 | BO53: =BG8+BG53 -> 165.67688 | BP53: =BH8+BH53 -> 62.782573 | BQ53: =BI8+BI53 -> 251.8516 | BR53: - | BS53: -
V54: Solar PV | W54: 0.02 | X54: 0.34 | Y54: 9.23 | Z54: 13.85 | AA54: 106.79 | AB54: 178.54 | AC54: 251.87 | AD54: 328.15 | AE54: 440.63 | AF54: 132.56 | AG54: 377.15 | AH54: 585.12 | AI54: 782.52 | AJ54: 1028.37 | BD54: AF | BE54: 4.686 | BF54: 13.534013 | BG54: 31.55235 | BH54: 22.752964 | BI54: 71.361144 | BK54: - | BM54: =BE9+BE54 -> 32.6316 | BN54: =BF9+BF54 -> 94.245946 | BO54: =BG9+BG54 -> 249.42963 | BP54: =BH9+BH54 -> 158.44337 | BQ54: =BI9+BI54 -> 496.93306 | BR54: - | BS54: -
BD55: Global | BE55: 576.35518 | BF55: 1380.6259 | BG55: 2786.3121 | BH55: 1491.6907 | BI55: 3188.0464 | BJ55: 1515.5051 | BK55: 3354.119 | BM55: =BE10+BE55 -> 2386.2829 | BN55: =BF10+BF55 -> 5716.2044 | BO55: =BG10+BG55 -> 11536.166 | BP55: =BH10+BH55 -> 6176.0459 | BQ55: =BI10+BI55 -> 13199.466 | BR55: =BJ10+BJ55 -> 6274.6448 | BS55: =BK10+BK55 -> 13887.056
BD56: 100% rooftop (zero ground-mounted)
BD57: EUR | BE57: 69.695933 | BF57: 129.71033 | BG57: 185.10877 | BH57: 143.00916 | BI57: 197.08329 | BK57: - | BM57: =BE3+BE57 -> 370.9673 | BN57: =BF3+BF57 -> 690.40315 | BO57: =BG3+BG57 -> 985.26988 | BP57: =BH3+BH57 -> 761.18823 | BQ57: =BI3+BI57 -> 1049.0061 | BR57: - | BS57: -
B58: CAPEX | E58: Current-2023 | H58: SPS-2050 | K58: APS-2050 | N58: NZE-2050 | V58: AF | X58: Stated Policies (STEPS) | AD58: Announced Pledges (APS) | AK58: Capacity | BD58: CSA | BE58: -16.318195 | BF58: -29.023522 | BG58: -48.597567 | BH58: -38.887371 | BI58: -81.721083 | BK58: - | BM58: =BE4+BE58 -> 35.9194 | BN58: =BF4+BF58 -> 63.886202 | BO58: =BG4+BG58 -> 106.97234 | BP58: =BH4+BH58 -> 85.598381 | BQ58: =BI4+BI58 -> 179.8834 | BR58: - | BS58: -
E59: Large, ground-mounted PV | F59: Rooftop PV | G59: Differences | V59: 2023 | X59: 2030 | Y59: 2035 | Z59: 2040 | AA59: 2045 | AB59: 2050 | AD59: 2030 | AE59: 2035 | AF59: 2040 | AG59: 2045 | AH59: 2050 | AL59: 2023 | AM59: SPS2030 | AN59: SPS2050 | AP59: APS2030 | AQ59: APS2050 | BD59: NA | BE59: 120.32393 | BF59: 266.33391 | BG59: 596.38151 | BH59: 312.26644 | BI59: 663.99069 | BK59: - | BM59: =BE5+BE59 -> 421.97049 | BN59: =BF5+BF59 -> 934.02079 | BO59: =BG5+BG59 -> 2091.4825 | BP59: =BH5+BH59 -> 1095.1041 | BQ59: =BI5+BI59 -> 2328.5848 | BR59: - | BS59: -
D60: Europe | E60: =AVERAGE(F4:F29,H4:K29,O4:O29) -> 795.94809 | F60: =AVERAGE(G4:G29,L4:N29) -> 1153.0338 | G60: =F60-E60 -> 357.0857 | H60: =E60*(0.8)^(LOG((AB19/V19),2)) -> 500.58529 | I60: =F60*(0.8)^(LOG((AB19/V19),2)) -> 725.16256 | J60: =I60-H60 -> 224.57727 | K60: =E60*(0.8)^(LOG((AH19/V19),2)) -> 485.9074 | L60: =F60*(0.8)^(LOG((AH19/V19),2)) -> 703.89974 | M60: =L60-K60 -> 217.99234 | V60: 17.04 | X60: 81.43 | Y60: 152.02 | Z60: 220.44 | AA60: 285.15 | AB60: 332.13 | AD60: 175.19 | AE60: 347.96 | AF60: 535.77 | AG60: 737.89 | AH60: 945.41 | AK60: Europe | AL60: =V19 -> 318.09 | AM60: =X19 -> 795.05 | AN60: =AB19 -> 1343.31 | AP60: =AD19 -> 918.14 | AQ60: =AH19 -> 1473.41 | AS60: =SUM(AL60:AL66) -> 1609.87 | BD60: Eurasia | BE60: 2.7111581 | BF60: 6.5369093 | BG60: 10.249956 | BH60: 7.6424493 | BI60: 18.559001 | BK60: - | BM60: =BE6+BE60 -> 10.387 | BN60: =BF6+BF60 -> 25.044234 | BO60: =BG6+BG60 -> 39.269673 | BP60: =BH6+BH60 -> 29.279783 | BQ60: =BI6+BI60 -> 71.10332 | BR60: - | BS60: -
D61: =D30 -> South America | E61: =AVERAGE(F30:F33,H30:K33,O30:O33) -> 1016.9347 | F61: =AVERAGE(G30:G33,L30:N33) -> 560 | G61: =F61-E61 -> -456.93475 | H61: =E61*(0.8)^(LOG((AB13/V13),2)) -> 605.73061 | I61: =F61*(0.8)^(LOG((AB13/V13),2)) -> 333.56038 | J61: =I61-H61 -> -272.17023 | K61: =E61*(0.8)^(LOG((AH13/V13),2)) -> 473.2762 | L61: =F61*(0.8)^(LOG((AH13/V13),2)) -> 260.62112 | M61: =L61-K61 -> -212.65508 | AK61: South America | AL61: =V13 -> 61.93 | AM61: =X13 -> 144.78 | AN61: =AB13 -> 309.64 | AP61: =AD13 -> 222.89 | AQ61: =AH13 -> 666.41 | AS61: =AS60 -> 1609.87 | BD61: APJ | BE61: 255.61515 | BF61: 661.1679 | BG61: 1372.0482 | BH61: 685.06394 | BI61: 1488.926 | BK61: - | BM61: =BE7+BE61 -> 1614.614 | BN61: =BF7+BF61 -> 4176.3211 | BO61: =BG7+BG61 -> 8666.6547 | BP61: =BH7+BH61 -> 4327.2624 | BQ61: =BI7+BI61 -> 9404.9225 | BR61: - | BS61: -
D62: =D34 -> North America | E62: =AVERAGE(F34:F37,H34:K37,O34:O37) -> 1173.6174 | F62: =AVERAGE(G34:G37,L34:N37) -> 2230.4766 | G62: =F62-E62 -> 1056.8592 | H62: =E62*(0.8)^(LOG((AB6/V6),2)) -> 548.88299 | I62: =F62*(0.8)^(LOG((AB6/V6),2)) -> 1043.1599 | J62: =I62-H62 -> 494.27693 | K62: =E62*(0.8)^(LOG((AH6/V6),2)) -> 521.59995 | L62: =F62*(0.8)^(LOG((AH6/V6),2)) -> 991.30812 | M62: =L62-K62 -> 469.70817 | AK62: North America | AL62: =V6 -> 188.55 | AM62: =X6 -> 608.6 | AN62: =AB6 -> 1998.23 | AP62: =AD6 -> 769.55 | AQ62: =AH6 -> 2341.13 | AS62: =AS61 -> 1609.87 | BD62: ME | BE62: 3.324 | BF62: 13.279007 | BG62: 37.01292 | BH62: 15.375324 | BI62: 61.677942 | BK62: - | BM62: =BE8+BE62 -> 14.127 | BN62: =BF8+BF62 -> 56.435779 | BO62: =BG8+BG62 -> 171.8457 | BP62: =BH8+BH62 -> 65.345127 | BQ62: =BI8+BI62 -> 262.13125 | BR62: - | BS62: -
D63: =D38 -> Eurasia | E63: =AVERAGE(F38,H38:K38,O38) -> 1095.2631 | F63: =AVERAGE(G38,L38:N38) -> 1610 | G63: =F63-E63 -> 514.73692 | H63: =E63*(0.8)^(LOG((AB25/V25),2)) -> 582.51482 | I63: =F63*(0.8)^(LOG((AB25/V25),2)) -> 856.27726 | J63: =I63-H63 -> 273.76243 | K63: =E63*(0.8)^(LOG((AH25/V25),2)) -> 439.43621 | L63: =F63*(0.8)^(LOG((AH25/V25),2)) -> 645.95649 | M63: =L63-K63 -> 206.52028 | AK63: Eurasia | AL63: =V25 -> 4.7 | AM63: =X25 -> 17.21 | AN63: =AB25 -> 33.41 | AP63: =AD25 -> 21.67 | AQ63: =AH25 -> 80.19 | AS63: =AS62 -> 1609.87 | BD63: AF | BE63: 5.6232 | BF63: 16.240816 | BG63: 37.86282 | BH63: 27.303557 | BI63: 85.633373 | BK63: - | BM63: =BE9+BE63 -> 33.5688 | BN63: =BF9+BF63 -> 96.952749 | BO63: =BG9+BG63 -> 255.7401 | BP63: =BH9+BH63 -> 162.99396 | BQ63: =BI9+BI63 -> 511.20529 | BR63: - | BS63: -
D64: =D39 -> Asia Pacific | E64: =AVERAGE(F39:F50,H39:K50,O39:O50) -> 1181.5463 | F64: =AVERAGE(G39:G50,L39:N50) -> 1605.4469 | G64: =F64-E64 -> 423.90057 | H64: =E64*(0.8)^(LOG((AB31/V31),2)) -> 532.07381 | I64: =F64*(0.8)^(LOG((AB31/V31),2)) -> 722.96468 | J64: =I64-H64 -> 190.89086 | K64: =E64*(0.8)^(LOG((AH31/V31),2)) -> 511.81827 | L64: =F64*(0.8)^(LOG((AH31/V31),2)) -> 695.4421 | M64: =L64-K64 -> 183.62383 | AK64: Asia Pacific | AL64: =V31 -> 1005.71 | AM64: =X31 -> 4084.58 | AN64: =AB31 -> 11987.66 | AP64: =AD31 -> 4304.15 | AQ64: =AH31 -> 13523.66 | AS64: =AS63 -> 1609.87 | BD64: Global | BE64: 691.62622 | BF64: 1656.7511 | BG64: 3343.5745 | BH64: 1790.0288 | BI64: 3825.6556 | BJ64: 1818.6062 | BK64: 4024.9428 | BM64: =BE10+BE64 -> 2501.554 | BN64: =BF10+BF64 -> 5992.3296 | BO64: =BG10+BG64 -> 12093.428 | BP64: =BH10+BH64 -> 6474.384 | BQ64: =BI10+BI64 -> 13837.075 | BR64: =BJ10+BJ64 -> 6577.7458 | BS64: =BK10+BK64 -> 14557.88
D65: Middle East | E65: 610 | F65: 1010 | G65: =F65-E65 -> 400 | H65: 250 | I65: 390 | J65: =I65-H65 -> 140 | K65: =H65*(0.8)^(LOG((AJ54/AE54),2)) -> 190.30326 | L65: =I65*(0.8)^(LOG((AJ54/AE54),2)) -> 296.87308 | M65: =L65-K65 -> 106.56982 | N65: 220 | O65: 340 | P65: =O65-N65 -> 120 | AK65: Middle East | AL65: =Z54 -> 13.85 | AM65: =AA54 -> 106.79 | AN65: =AE54 -> 440.63 | AP65: =AF54 -> 132.56 | AQ65: =AJ54 -> 1028.37 | AS65: =AS64 -> 1609.87
D66: Africa | E66: 1330 | F66: 1830 | G66: =F66-E66 -> 500 | H66: 550 | I66: 750 | J66: =I66-H66 -> 200 | K66: =H66*(0.8)^(LOG((AH60/AB60),2)) -> 392.74156 | L66: =I66*(0.8)^(LOG((AH60/AB60),2)) -> 535.55668 | M66: =L66-K66 -> 142.81511 | N66: 480 | O66: 620 | P66: =O66-N66 -> 140 | AK66: Africa | AL66: =V60 -> 17.04 | AM66: =X60 -> 81.43 | AN66: =AB60 -> 332.13 | AP66: =AD60 -> 175.19 | AQ66: =AH60 -> 945.41 | AS66: =AS65 -> 1609.87
D69: Global | E69: =AVERAGE(E60*AL60/AS60+E61*AL61/AS61+E62*AL62/AS62+E63*AL63/AS63+E64*AL64/AS64+E65*AL65/AS65+E66*AL66/AS66) -> 1094.4982 | F69: =AVERAGE(F60*AL60/AS60+F61*AL61/AS61+F62*AL62/AS62+F63*AL63/AS63+F64*AL64/AS64+F65*AL65/AS65+F66*AL66/AS66) -> 1546.3102 | G69: =F69-E69 -> 451.81196 | H69: =E69*(0.8)^(LOG((AA46/V46),2)) -> 517.97795 | I69: =F69*(0.8)^(LOG((AA46/V46),2)) -> 731.80072 | J69: =I69-H69 -> 213.82277 | K69: =E69*(0.8)^(LOG((AF46/V46),2)) -> 485.89191 | L69: =F69*(0.8)^(LOG((AF46/V46),2)) -> 686.46947 | M69: =L69-K69 -> 200.57756 | N69: =E69*(0.8)^(LOG((AK46/V46),2)) -> 474.31753 | O69: =F69*(0.8)^(LOG((AK46/V46),2)) -> 670.11715 | P69: =O69-N69 -> 195.79962
B76: Costs related to CAPEX
D78: Baseline cost ($ billion) | E78: Current (2023) | F78: SPS-2050 | G78: APS-2050 | H78: NZE-2050 | I78: Recalculated but not applied | P78: 2023 | Q78: 2030 | R78: 2050
D79: Europe | E79: =(E60*0.6+F60*0.4)*AL60/1000 -> 298.61728 | F79: =(H60*0.6+I60*0.4)*AN60/1000 -> 793.11198 | G79: =(K60*0.6+L60*0.4)*AQ60/1000 -> 844.41767 | O79: Solar photovoltaics - Large scale unit
D80: CSA | E80: =(E61*0.6+F61*0.4)*AL61/1000 -> 51.659581 | F80: =(H61*0.6+I61*0.4)*AN61/1000 -> 153.84851 | G80: =(K61*0.6+L61*0.4)*AQ61/1000 -> 258.7098 | O80: European Union | P80: 750 | Q80: 480 | R80: 340
D81: NA | E81: =(E62*0.6+F62*0.4)*AL62/1000 -> 300.99389 | F81: =(H62*0.6+I62*0.4)*AN62/1000 -> 1491.8661 | G81: =(K62*0.6+L62*0.4)*AQ62/1000 -> 1660.9924 | O81: United States | P81: 1 110 | Q81: 690 | R81: 480
D82: Eurasia | E82: =(E63*0.6+F63*0.4)*AL63/1000 -> 6.1154419 | F82: =(H63*0.6+I63*0.4)*AN63/1000 -> 23.120381 | G82: =(K63*0.6+L63*0.4)*AQ63/1000 -> 41.862734 | O82: Japan | P82: 1 880 | Q82: 1 260 | R82: 940
D83: APJ | E83: =(E64*0.6+F64*0.4)*AL64/1000 -> 1358.8214 | F83: =(H64*0.6+I64*0.4)*AN64/1000 -> 7293.6539 | G83: =(K64*0.6+L64*0.4)*AQ64/1000 -> 7914.9628 | O83: Russia | P83: 1 250 | Q83: 820 | R83: 580
D84: ME | E84: =(E65*0.6+F65*0.4)*AL65/1000 -> 10.6645 | F84: =(H65*0.6+I65*0.4)*AN65/1000 -> 134.83278 | G84: =(K65*0.6+L65*0.4)*AQ65/1000 -> 239.53944 | I84: ME | J84: =(H65*0.6+I65*0.4)*AN65/1000 -> 134.83278 | O84: China | P84: 670 | Q84: 410 | R84: 280
D85: AF | E85: =(E66*0.6+F66*0.4)*AL66/1000 -> 26.0712 | F85: =(H66*0.6+I66*0.4)*AN66/1000 -> 209.2419 | G85: =(K66*0.6+L66*0.4)*AQ66/1000 -> 425.30934 | I85: AF | J85: =(H66*0.6+I66*0.4)*AN66/1000 -> 209.2419 | O85: India | P85: 710 | Q85: 450 | R85: 300
D86: Global | E86: =(E69*0.6+F69*0.4)*V46/1000 -> 2052.9432 | F86: =(H69*0.6+I69*0.4)*AA46/1000 -> 9924.6796 | G86: =(K69*0.6+L69*0.4)*AF46/1000 -> 11355.634 | H86: =(N69*0.6+O69*0.4)*AK46/1000 -> 11947.174 | O86: Middle East | P86: 610 | Q86: 360 | R86: 250 | U86: 330 | V86: 220
O87: Africa | P87: 1 330 | Q87: 820 | R87: 550 | U87: 760 | V87: 480
O88: Brazil | P88: 730 | Q88: 460 | R88: 330
O89: Solar photovoltaics - Buildings
O90: European Union | P90: 990 | Q90: 650 | R90: 470
O91: United States | P91: 3 460 | Q91: 2 200 | R91: 1 490
O92: Japan | P92: 1 850 | Q92: 1 280 | R92: 990
D93: 50-pct | E93: =(E60*0.5+F60*0.5)*AL60/1000-E79 -> 11.358539 | F93: =(H60*0.5+I60*0.5)*AN60/1000-F79 -> 30.167689 | G93: =(K60*0.5+L60*0.5)*AQ60/1000-G79 -> 32.119209 | O93: Russia | P93: 1 610 | Q93: 1 080 | R93: 780
E94: =(E61*0.5+F61*0.5)*AL61/1000-E80 -> -2.8297969 | F94: =(H61*0.5+I61*0.5)*AN61/1000-F80 -> -8.427479 | G94: =(K61*0.5+L61*0.5)*AQ61/1000-G80 -> -14.171547 | O94: China | P94: 750 | Q94: 450 | R94: 310
E95: =(E62*0.5+F62*0.5)*AL62/1000-E81 -> 19.92708 | F95: =(H62*0.5+I62*0.5)*AN62/1000-F81 -> 98.7679 | G95: =(K62*0.5+L62*0.5)*AQ62/1000-G81 -> 109.96479 | O95: India | P95: 780 | Q95: 490 | R95: 330
E96: =(E63*0.5+F63*0.5)*AL63/1000-E82 -> 0.24192635 | F96: =(H63*0.5+I63*0.5)*AN63/1000-F82 -> 0.91464028 | G96: =(K63*0.5+L63*0.5)*AQ63/1000-G82 -> 1.6560861 | O96: Middle East | P96: 1 010 | Q96: 580 | R96: 390 | U96: 530 | V96: 340
E97: =(E64*0.5+F64*0.5)*AL64/1000-E83 -> 42.632104 | F97: =(H64*0.5+I64*0.5)*AN64/1000-F83 -> 228.83348 | G97: =(K64*0.5+L64*0.5)*AQ64/1000-G83 -> 248.32662 | O97: Africa | P97: 1 830 | Q97: 1 120 | R97: 750 | U97: 950 | V97: 620
E98: =(E65*0.5+F65*0.5)*AL65/1000-E84 -> 0.554 | F98: =(H65*0.5+I65*0.5)*AN65/1000-F84 -> 6.16882 | G98: =(K65*0.5+L65*0.5)*AQ65/1000-G84 -> 10.959321
E99: =(E66*0.5+F66*0.5)*AL66/1000-E85 -> 0.852 | F99: =(H66*0.5+I66*0.5)*AN66/1000-F85 -> 6.6426 | G99: =(K66*0.5+L66*0.5)*AQ66/1000-G85 -> 13.501884
D100: Global | E100: =(E69*0.5+F69*0.5)*V46/1000-E86 -> 72.735853 | F100: =(H69*0.5+I69*0.5)*AA46/1000-F86 -> 351.63175 | G100: =(K69*0.5+L69*0.5)*AF46/1000-G86 -> 402.3305 | H100: =(N69*0.5+O69*0.5)*AK46/1000-H86 -> 423.28882
K102: Inputting to Origin: additional cost: SPS-2050 | Q102: Inputting to Origin: additional cost: APS-2050
D103: 40-pct | E103: =E93*2 -> 22.717078 | F103: =F93*2 -> 60.335378 | G103: =G93*2 -> 64.238418 | J103: NA | K103: =F145 -> 592.6074 | L103: =F135 -> 493.8395 | M103: =F125 -> 395.0716 | N103: =F115 -> 296.3037 | O103: =F105 -> 197.5358 | P103: =F95 -> 98.7679 | Q103: =G145 -> 659.78873 | R103: =G135 -> 549.82394 | S103: =G125 -> 439.85915 | T103: =G115 -> 329.89436 | U103: =G105 -> 219.92958 | V103: =G95 -> 109.96479
E104: =E94*2 -> -5.6595938 | F104: =F94*2 -> -16.854958 | G104: =G94*2 -> -28.343095 | J104: CSA | K104: =F144 -> -50.564874 | L104: =F134 -> -42.137395 | M104: =F124 -> -33.709916 | N104: =F114 -> -25.282437 | O104: =F104 -> -16.854958 | P104: =F94 -> -8.427479 | Q104: =G144 -> -85.029284 | R104: =G134 -> -70.857736 | S104: =G124 -> -56.686189 | T104: =G114 -> -42.514642 | U104: =G104 -> -28.343095 | V104: =G94 -> -14.171547
E105: =E95*2 -> 39.85416 | F105: =F95*2 -> 197.5358 | G105: =G95*2 -> 219.92958 | J105: Europe | K105: =F143 -> 181.00613 | L105: =F133 -> 150.83845 | M105: =F123 -> 120.67076 | N105: =F113 -> 90.503067 | O105: =F103 -> 60.335378 | P105: =F93 -> 30.167689 | Q105: =G143 -> 192.71525 | R105: =G133 -> 160.59605 | S105: =G123 -> 128.47684 | T105: =G113 -> 96.357627 | U105: =G103 -> 64.238418 | V105: =G93 -> 32.119209
E106: =E96*2 -> 0.4838527 | F106: =F96*2 -> 1.8292806 | G106: =G96*2 -> 3.3121723 | J106: AF | K106: =F149 -> 39.8556 | L106: =F139 -> 33.213 | M106: =F129 -> 26.5704 | N106: =F119 -> 19.9278 | O106: =F109 -> 13.2852 | P106: =F99 -> 6.6426 | Q106: =G149 -> 81.011302 | R106: =G139 -> 67.509419 | S106: =G129 -> 54.007535 | T106: =G119 -> 40.505651 | U106: =G109 -> 27.003767 | V106: =G99 -> 13.501884
E107: =E97*2 -> 85.264209 | F107: =F97*2 -> 457.66695 | G107: =G97*2 -> 496.65325 | J107: ME | K107: =F148 -> 37.01292 | L107: =F138 -> 30.8441 | M107: =F128 -> 24.67528 | N107: =F118 -> 18.50646 | O107: =F108 -> 12.33764 | P107: =F98 -> 6.16882 | Q107: =G148 -> 65.755925 | R107: =G138 -> 54.796604 | S107: =G128 -> 43.837283 | T107: =G118 -> 32.877963 | U107: =G108 -> 21.918642 | V107: =G98 -> 10.959321
E108: =E98*2 -> 1.108 | F108: =F98*2 -> 12.33764 | G108: =G98*2 -> 21.918642 | J108: Eurasia | K108: =F146 -> 5.4878417 | L108: =F136 -> 4.5732014 | M108: =F126 -> 3.6585611 | N108: =F116 -> 2.7439208 | O108: =F106 -> 1.8292806 | P108: =F96 -> 0.91464028 | Q108: =G146 -> 9.9365168 | R108: =G136 -> 8.2804307 | S108: =G126 -> 6.6243445 | T108: =G116 -> 4.9682584 | U108: =G106 -> 3.3121723 | V108: =G96 -> 1.6560861
E109: =E99*2 -> 1.704 | F109: =F99*2 -> 13.2852 | G109: =G99*2 -> 27.003767 | J109: APJ | K109: =F147 -> 1373.0009 | L109: =F137 -> 1144.1674 | M109: =F127 -> 915.3339 | N109: =F117 -> 686.50043 | O109: =F107 -> 457.66695 | P109: =F97 -> 228.83348 | Q109: =G147 -> 1489.9597 | R109: =G137 -> 1241.6331 | S109: =G127 -> 993.3065 | T109: =G117 -> 744.97987 | U109: =G107 -> 496.65325 | V109: =G97 -> 248.32662
E110: =E100*2 -> 145.47171 | F110: =F100*2 -> 703.2635 | G110: =G100*2 -> 804.661 | H110: =H100*2 -> 846.57764 | J110: Global | K110: =F150 -> 2109.7905 | L110: =F140 -> 1758.1588 | M110: =F130 -> 1406.527 | N110: =F120 -> 1054.8953 | O110: =F110 -> 703.2635 | P110: =F100 -> 351.63175 | Q110: =G150 -> 2413.983 | R110: =G140 -> 2011.6525 | S110: =G130 -> 1609.322 | T110: =G120 -> 1206.9915 | U110: =G110 -> 804.661 | V110: =G100 -> 402.3305
...

Sheet Attached_WEO2023
B1: Large, ground-mounted PV | F1: Rooftop PV
A2: Middle East | B2: =M13 -> 610 | E2: Middle East | F2: =M23 -> 1010
A3: Africa | B3: =M14 -> 1330 | E3: Africa | F3: =M24 -> 1830
M5: 2023
L6: Solar photovoltaics - Large scale unit
L7: European Union | M7: 750
L8: United States | M8: 1110
L9: Japan | M9: 1880
L10: Russia | M10: 1250
A11: Solar photovoltaics - Large scale unit | E11: Solar photovoltaics - Buildings | L11: China | M11: 670
A12: European Union | B12: =M7 -> 750 | E12: European Union | F12: =M17 -> 990 | L12: India | M12: 710
A13: United States | B13: =M8 -> 1110 | E13: United States | F13: =M18 -> 3460 | L13: Middle East | M13: 610
A14: Japan | B14: =M9 -> 1880 | E14: Japan | F14: =M19 -> 1850 | L14: Africa | M14: 1330
A15: Russia | B15: =M10 -> 1250 | E15: Russia | F15: =M20 -> 1610 | L15: Brazil | M15: 730
A16: China | B16: =M11 -> 670 | E16: China | F16: =M21 -> 750 | L16: Solar photovoltaics - Buildings
A17: India | B17: =M12 -> 710 | E17: India | F17: =M22 -> 780 | L17: European Union | M17: 990
A18: Brazil | B18: =M15 -> 730 | E18: Brazil | F18: =M25 -> 560 | L18: United States | M18: 3460
L19: Japan | M19: 1850
L20: Russia | M20: 1610
L21: China | M21: 750
L22: India | M22: 780
L23: Middle East | M23: 1010
L24: Africa | M24: 1830
L25: Brazil | M25: 560

Sheet Attached-IRENA2024 report
B1: Figure 3.5 Utility-scale solar PV total installed cost trends in major utility-scale markets, 2018-2023 | L1: This publication should be cited as: Citation: IRENA (2024), Renewable Power Generation Costs in 2023, International Renewable Energy Agency, Abu Dhabi. | N1: Figure 3.1 Global weighted average and range total installed costs, capacity factors and LCOE for solar PV, 2010-2023
B7: Region | C7: Country | E7: 2018 | F7: 2019 | G7: 2020 | H7: 2021 | I7: 2022 | J7: 2023
B8: Africa | C8: South Africa | D8: Total Installed Cost 2023 USD/kW | E8: 1943.297 | F8: 1536.5297 | G8: 1344.2656 | H8: 1213.2379 | I8: 1302.7058 | J8: 1255.0797 | N8: Total installed cost (2023 USD/kW)
D9: % Difference from previous year | F9: -0.21 | G9: -0.13 | H9: -0.1 | I9: 0.07 | J9: -0.04 | O9: 2010 | P9: 2011 | Q9: 2012 | R9: 2013 | S9: 2014 | T9: 2015 | U9: 2016 | V9: 2017 | W9: 2018 | X9: 2019 | Y9: 2020 | Z9: 2021 | AA9: 2022 | AB9: 2023
N10: 5th percentile | O10: 3883.973 | P10: 2992.9544 | Q10: 2388.6731 | R10: 1951.7283 | S10: 1633.8612 | T10: 1385.1386 | U10: 1184.3459 | V10: 961.93338 | W10: 926.21451 | X10: 826.60847 | Y10: 658.55112 | Z10: 640.56743 | AA10: 585.41345 | AB10: 526.44883
B11: Asia | C11: China | D11: Total Installed Cost 2023 USD/kW | E11: 1022.8316 | F11: 924.11217 | G11: 747.94811 | H11: 696.86688 | I11: 741.61168 | J11: 671.12616 | N11: Weighted average | O11: 5310.4875 | P11: 4553.2582 | Q11: 3466.2198 | R11: 3042.4049 | S11: 2749.1697 | T11: 2090.4419 | U11: 1900.5241 | V11: 1644.2776 | W11: 1404.9553 | X11: 1160.7433 | Y11: 1019.4321 | Z11: 950.07471 | AA11: 908.02086 | AB11: 757.68783
D12: % Difference from previous year | F12: -0.1 | G12: -0.19 | H12: -0.07 | I12: 0.06 | J12: -0.1 | N12: 95th percentile | O12: 8618.6877 | P12: 8500.4764 | Q12: 7381.7377 | R12: 6131.1329 | S12: 5918.9344 | T12: 4642.0855 | U12: 3734.5526 | V12: 3445.7771 | W12: 3321.3135 | X12: 2728.9196 | Y12: 2696.9131 | Z12: 2166.6495 | AA12: 1946.1541 | AB12: 1662.8282
C13: India | D13: Total Installed Cost 2023 USD/kW | E13: 921.83482 | F13: 719.1617 | G13: 684.93912 | H13: 654.06446 | I13: 664.04029 | J13: 711.32819
D14: % Difference from previous year | F14: -0.22 | G14: -0.05 | H14: -0.05 | I14: 0.02 | J14: 0.07
C15: Japan | D15: Total Installed Cost 2023 USD/kW | E15: 2443.8599 | F15: 2407.6673 | G15: 2105.78 | H15: 1878.4591 | I15: 1975.5387 | J15: 1875.2399 | N15: Capacity factor (%)
D16: % Difference from previous year | F16: -0.01 | G16: -0.13 | H16: -0.11 | I16: 0.05 | J16: -0.05 | O16: 2010 | P16: 2011 | Q16: 2012 | R16: 2013 | S16: 2014 | T16: 2015 | U16: 2016 | V16: 2017 | W16: 2018 | X16: 2019 | Y16: 2020 | Z16: 2021 | AA16: 2022 | AB16: 2023
C17: Republic of Korea | D17: Total Installed Cost 2023 USD/kW | E17: 1542.2992 | F17: 1456.2977 | G17: 1090.5517 | H17: 1043.2915 | I17: 1387.0977 | J17: 1205.2601 | N17: 5th percentile | O17: 0.11003125 | P17: 0.101012 | Q17: 0.104705 | R17: 0.118938 | S17: 0.108012 | T17: 0.10795205 | U17: 0.106874 | V17: 0.1147831 | W17: 0.1235139 | X17: 0.10745 | Y17: 0.099 | Z17: 0.108 | AA17: 0.10365 | AB17: 0.1
B18: Europe | D18: % Difference from previous year | F18: -0.06 | G18: -0.25 | H18: -0.04 | I18: 0.33 | J18: -0.13 | N18: Weighted average | O18: 0.13815302 | P18: 0.15304622 | Q18: 0.15111482 | R18: 0.16437076 | S18: 0.16560055 | T18: 0.16504087 | U18: 0.167117 | V18: 0.17550735 | W18: 0.17903257 | X18: 0.17507051 | Y18: 0.16080057 | Z18: 0.17209014 | AA18: 0.16936088 | AB18: 0.16170928
N19: 95th percentile | O19: 0.23 | P19: 0.26 | Q19: 0.2562105 | R19: 0.23 | S19: 0.2436794 | T19: 0.28988495 | U19: 0.2589275 | V19: 0.27 | W19: 0.2694423 | X19: 0.23867634 | Y19: 0.20795 | Z19: 0.213 | AA19: 0.205 | AB19: 0.21698425
C20: Greece | D20: Total Installed Cost 2023 USD/kW | E20: 2114.8213 | G20: 872.41798 | H20: 806.37054 | I20: 1215.8411 | J20: 626.34564
D21: % Difference from previous year | G21: -0.59 | H21: -0.08 | I21: 0.51 | J21: -0.48
C22: Netherlands | D22: Total Installed Cost 2023 USD/kW | E22: 1358.4699 | F22: 1304.2558 | G22: 1291.4504 | H22: 1133.9076 | I22: 1266.2436 | J22: 753.19994 | N22: LCOE (2023 USD/kWh)
D23: % Difference from previous year | F23: -0.04 | G23: -0.01 | H23: -0.12 | I23: 0.12 | J23: 0.14 | O23: 2010 | P23: 2011 | Q23: 2012 | R23: 2013 | S23: 2014 | T23: 2015 | U23: 2016 | V23: 2017 | W23: 2018 | X23: 2019 | Y23: 2020 | Z23: 2021 | AA23: 2022 | AB23: 2023
C24: Germany | D24: Total Installed Cost 2023 USD/kW | E24: 1294.6508 | F24: 1045.3774 | G24: 804.12359 | H24: 769.40993 | I24: 1032.6717 | J24: 730.77006 | N24: 5th percentile | O24: 0.22974323 | P24: 0.19240469 | Q24: 0.15385439 | R24: 0.13321759 | S24: 0.10879781 | T24: 0.086497538 | U24: 0.079925694 | V24: 0.057885199 | W24: 0.052502988 | X24: 0.05008728 | Y24: 0.041288138 | Z24: 0.031589457 | AA24: 0.030574979 | AB24: 0.030975069
D25: % Difference from previous year | F25: -0.19 | G25: -0.23 | H25: -0.04 | I25: 0.34 | J25: -0.29 | N25: Weighted average | O25: 0.46001218 | P25: 0.34292529 | Q25: 0.25565217 | R25: 0.19678167 | S25: 0.17699121 | T25: 0.13236205 | U25: 0.11593225 | V25: 0.091175791 | W25: 0.077331907 | X25: 0.067466522 | Y25: 0.060086136 | Z25: 0.052132524 | AA25: 0.05049542 | AB25: 0.044247408
C26: United Kingdom | D26: Total Installed Cost 2023 USD/kW | E26: 1584.1923 | F26: 1183.5571 | G26: 971.93602 | H26: 940.7776 | I26: 943.38871 | J26: 932.69058 | N26: 95th percentile | O26: 0.57574229 | P26: 0.57231969 | Q26: 0.45833945 | R26: 0.41356913 | S26: 0.39219745 | T26: 0.31557182 | U26: 0.26128957 | V26: 0.23083767 | W26: 0.22041677 | X26: 0.18072519 | Y26: 0.17566198 | Z26: 0.1302541 | AA26: 0.12208644 | AB26: 0.10981654
D27: % Difference from previous year | F27: -0.25 | G27: -0.18 | H27: -0.03 | I27: 0.0027754784 | J27: -0.01
C28: Portugal | D28: Total Installed Cost 2023 USD/kW | E28: 1039.5013 | F28: 985.63752 | G28: 823.97475 | H28: 998.45568 | I28: 1016.9079 | J28: 723.26964
D29: % Difference from previous year | F29: -0.05 | G29: -0.16 | H29: 0.21 | I29: 0.02 | J29: -0.29
C30: France | D30: Total Installed Cost 2023 USD/kW | E30: 1249.0455 | F30: 1138.7246 | G30: 1086.9617 | H30: 896.60674 | I30: 1199.7031 | J30: 954.78012
D31: % Difference from previous year | F31: -0.09 | G31: -0.05 | H31: -0.18 | I31: 0.34 | J31: -0.2
C32: Italy | D32: Total Installed Cost 2023 USD/kW | E32: 1012.264 | F32: 965.58874 | G32: 897.37147 | H32: 870.70276 | I32: 799.39098 | J32: 821.34079
D33: % Difference from previous year | F33: -0.05 | G33: -0.07 | H33: -0.03 | I33: -0.08 | J33: 0.03
B35: Middle East | C35: Saudi Arabia | D35: Total Installed Cost 2023 USD/kW | E35: 1473.466 | F35: 1158.9013 | H35: 1033.9599 | I35: 676.5395 | J35: 794.03843
D36: % Difference from previous year | F36: -0.21 | H36: -0.11 | I36: -0.35 | J36: 0.17
B38: North America | C38: Canada | D38: Total Installed Cost 2023 USD/kW | E38: 2822.5997 | F38: 1632.9734 | G38: 1464.9284 | H38: 1203.1608 | I38: 996.27041 | J38: 1336.5221
D39: % Difference from previous year | F39: -0.42 | G39: -0.1 | H39: -0.18 | I39: -0.17 | J39: 0.34
C40: Mexico | D40: Total Installed Cost 2023 USD/kW | E40: 1723.0092 | F40: 1440.3595 | G40: 1011.2168 | H40: 967.24444 | I40: 993.35624 | J40: 1049.5172
D41: % Difference from previous year | F41: -0.16 | G41: -0.3 | H41: -0.04 | I41: 0.03 | J41: 0.06
C42: United States | D42: Total Installed Cost 2023 USD/kW | E42: 1801.2284 | F42: 1419.7508 | G42: 1286.6641 | H42: 1204.24 | I42: 1159.7502 | J42: 1108.5304
D43: % Difference from previous year | F43: -0.21 | G43: -0.09 | H43: -0.06 | I43: -0.04 | J43: -0.04
B45: Oceania | C45: Australia | D45: Total Installed Cost 2023 USD/kW | E45: 1767.6018 | F45: 1454.588 | G45: 1218.9268 | H45: 1134.9347 | I45: 956.66766 | J45: 988.62812
D46: % Difference from previous year | F46: -0.18 | G46: -0.16 | H46: -0.07 | I46: -0.16 | J46: 0.03
B48: South America | C48: Brazil | D48: Total Installed Cost 2023 USD/kW | E48: 1767.4191 | F48: 1460.2783 | G48: 1268.1135 | H48: 894.18123 | I48: 761.33262 | J48: 726.98559
D49: % Difference from previous year | F49: -0.17 | G49: -0.13 | H49: -0.29 | I49: -0.15 | J49: -0.05
C50: Chile | D50: Total Installed Cost 2023 USD/kW | E50: 2160.3685 | F50: 2008.5203 | G50: 1224.3422 | H50: 1179.6253 | I50: 920.84786 | J50: 953.80679
D51: % Difference from previous year | F51: -0.07 | G51: -0.39 | H51: -0.04 | I51: -0.22 | J51: 0.04
C53: Argentina | J53: 830
A57: Additional information from Figure 3.4 | B57: Europe | C57: Spain | D57: Total Installed Cost 2023 USD/kW | F57: 891.34061 | G57: 876.15371 | H57: 905.10812 | I57: 806.95039 | J57: 670.76717
C58: Turkey | D58: Total Installed Cost 2023 USD/kW | E58: 1402.4404 | F58: 1071.3544 | G58: 950.2604 | H58: 898.61323 | I58: 715.39029 | J58: 715.36
A62: Additional information from Figure 3.6 | B62: Europe | C62: Hungary | J62: 1078
C63: Belgium | J63: 965
C64: Cyprus | J64: 854
C65: Slovakia | J65: 844
C67: Romania | J67: 743
C68: Latvia | J68: 716
C69: Estonia | J69: 705
C70: Poland | J70: 700
C71: Ireland | J71: 686
C72: Luxembourg | J72: 684
C73: Austria | J73: 678
C74: Czech Republic | J74: 663
C75: Bulgaria | J75: 659
B78: Asia | C78: Indonesia | J78: 798
B83: Eurasia | C83: Russian Federation | J83: 1248
B89: APJ | E89: =AVERAGE(E11,E13,E15,E17,E45,E78) -> 1539.6855 | F89: =AVERAGE(F11,F13,F15,F17,F45,F78) -> 1392.3654 | G89: =AVERAGE(G11,G13,G15,G17,G45,G78) -> 1169.6292 | H89: =AVERAGE(H11,H13,H15,H17,H45,H78) -> 1081.5233 | I89: =AVERAGE(I11,I13,I15,I17,I45,I78) -> 1144.9912 | J89: =AVERAGE(J11,J13,J15,J17,J45,J78) -> 1041.5971
B90: Europe | E90: =AVERAGE(E20,E22,E24,E26,E28,E30,E32,E57,E58,E62:E75) -> 1381.9232 | F90: =AVERAGE(F20,F22,F24,F26,F28,F30,F32,F57,F58,F62:F75) -> 1073.2295 | G90: =AVERAGE(G20,G22,G24,G26,G28,G30,G32,G57,G58,G62:G75) -> 952.73889 | H90: =AVERAGE(H20,H22,H24,H26,H28,H30,H32,H57,H58,H62:H75) -> 913.32803 | I90: =AVERAGE(I20,I22,I24,I26,I28,I30,I32,I57,I58,I62:I75) -> 999.60976 | J90: =AVERAGE(J20,J22,J24,J26,J28,J30,J32,J57,J58,J62:J75) -> 768.342
B91: Eurasia | E91: =E83 -> 0 | F91: =F83 -> 0 | G91: =G83 -> 0 | H91: =H83 -> 0 | I91: =I83 -> 0 | J91: =J83 -> 1248
B92: North America | E92: =AVERAGE(E38,E40,E42) -> 2115.6124 | F92: =AVERAGE(F38,F40,F42) -> 1497.6946 | G92: =AVERAGE(G38,G40,G42) -> 1254.2697 | H92: =AVERAGE(H38,H40,H42) -> 1124.8817 | I92: =AVERAGE(I38,I40,I42) -> 1049.7923 | J92: =AVERAGE(J38,J40,J42) -> 1164.8566
B93: South America | E93: =AVERAGE(E48,E50) -> 1963.8938 | F93: =AVERAGE(F48,F50) -> 1734.3993 | G93: =AVERAGE(G48,G50) -> 1246.2278 | H93: =AVERAGE(H48,H50) -> 1036.9033 | I93: =AVERAGE(I48,I50) -> 841.09024 | J93: =AVERAGE(J48,J50) -> 840.39619
B94: Global (median value) | E94: =W11 -> 1404.9553 | F94: =X11 -> 1160.7433 | G94: =Y11 -> 1019.4321 | H94: =Z11 -> 950.07471 | I94: =AA11 -> 908.02086 | J94: =AB11 -> 757.68783

Sheet Attached-IEA2020Projected Costs
A1: Source: IEA. NEA. All rights reserved
A2: https://www.iea.org/reports/projected-costs-of-generating-electricity-2020 | E2: Back to the table of content
A3: www.oecd-nea.org/egc-2020 | E3: Table 3.5: Solar generating technologies
A4: Projected Costs of Generating Electricity 2020 | E4: Country | F4: Technology | G4: Net capacity* (MWe) | H4: Capacity factor (%) | I4: Annual efficiency loss (%) | J4: Overnight costs (USD/kWe) | K4: Investment costs (USD/kWe)
K5: 0.03 | L5: 0.07 | M5: 0.1
D6: Europe | E6: Austria | F6: Solar PV (residential) | G6: 0.02 | H6: 0.114 | I6: 0.005 | J6: 718.85041 | K6: 729.55348 | L6: 743.58464 | M6: 753.93667
D7: APJ | E7: Australia | F7: Solar PV (utility scale) | G7: 100 | H7: 0.28 | I7: 0.005 | J7: 882.0154 | K7: 895.14787 | L7: 912.36383 | M7: 925.06556
D9: Europe | E9: Belgium** | F9: Solar PV (residential) | G9: 0.01 | H9: 0.132 | I9: 0.005 | J9: 1841.3902 | K9: 1868.8069 | L9: 1904.7488 | M9: 1931.2663
F10: Solar PV (residential) | G10: 0.01 | H10: 0.1236 | I10: 0.005 | J10: 1345.6313 | K10: 1365.6666 | L10: 1391.9318 | M10: 1411.31
F11: Solar PV (residential) | G11: 0.01 | H11: 0.1278 | I11: 0.005 | J11: 1008.5152 | K11: 1023.5312 | L11: 1043.2163 | M11: 1057.7397
F12: Solar PV (utility scale) | G12: 1 | H12: 0.132 | I12: 0.005 | J12: 991.5178 | K12: 1006.2807 | L12: 1025.634 | M12: 1039.9126
D13: NA | E13: Canada | F13: Solar PV (utility scale) | G13: 20 | H13: 0.25 | I13: 0.005 | J13: 1354.4227 | K13: 1374.5889 | L13: 1401.0257 | M13: 1420.5305
F14: Solar PV (utility scale) | G14: 20 | H14: 0.19 | I14: 0.005 | J14: 1264.1279 | K14: 1282.9497 | L14: 1307.624 | M14: 1325.8285
D15: Europe | E15: Denmark | F15: Solar PV (residential) | G15: 0.006 | H15: 0.12098355 | I15: 0.005 | J15: 1176.222 | K15: 1193.735 | L15: 1216.6935 | M15: 1233.632
F16: Solar PV (commercial) | G16: 0.1 | H16: 0.13101672 | I16: 0.005 | J16: 847.1582 | K16: 859.77167 | L16: 876.30726 | M16: 888.50702
F17: Solar PV (utility scale) | G17: 8 | H17: 0.16136584 | I17: 0.005 | J17: 534.43084 | K17: 542.38806 | L17: 552.81956 | M17: 560.51579
F18: Solar PV (utility scale) | G18: 8 | H18: 0.17911608 | I18: 0.005 | J18: 623.20227 | K18: 632.48123 | L18: 644.64544 | M18: 653.62006
D19: Europe | E19: France | F19: Solar PV (residential) | G19: 0.01 | H19: 0.1764 | I19: 0.005 | J19: 1699.7448 | K19: 1725.0526 | L19: 1758.2297 | M19: 1782.7074
F20: Solar PV (commercial) | G20: 0.5 | H20: 0.1764 | I20: 0.005 | J20: 849.8724 | K20: 862.52628 | L20: 879.11485 | M20: 891.35369
F21: Solar PV (utility scale) | G21: 25 | H21: 0.24 | I21: 0.005 | J21: 708.227 | K21: 718.7719 | L21: 732.59571 | M21: 742.79475
D22: Europe | E22: Hungary | F22: Solar PV (residential) | G22: 0.0041666667 | H22: 0.15 | I22: 0.005 | J22: 1900.7321 | K22: 1929.0324 | L22: 1966.1326 | M22: 1993.5047
F23: Solar PV (commercial) | G23: 0.05 | H23: 0.135 | I23: 0.005 | J23: 1296.7612 | K23: 1316.0689 | L23: 1341.3802 | M23: 1360.0546
F24: Solar PV (commercial) | G24: 0.5 | H24: 0.135 | I24: 0.005 | J24: 1074.713 | K24: 1090.7146 | L24: 1111.6918 | M24: 1127.1685
F25: Solar PV (utility scale) | G25: 20 | H25: 0.135 | I25: 0.005 | J25: 963.68896 | K25: 978.03747 | L25: 996.84761 | M25: 1010.7255
D26: Europe | E26: Italy** | F26: Solar PV (commercial) | G26: 0.083333333 | H26: 0.19565507 | I26: 0.005 | J26: 1305.5306 | K26: 1324.9689 | L26: 1350.4514 | M26: 1369.2521
F27: Solar PV (commercial) | G27: 0.20833333 | H27: 0.1716 | I27: 0.005 | J27: 906.53056 | K27: 920.02804 | L27: 937.7225 | M27: 950.77727
F28: Solar PV (commercial) | G28: 0.41666667 | H28: 0.19565507 | I28: 0.005 | J28: 1210.1559 | K28: 1228.1741 | L28: 1251.795 | M28: 1269.2223
F29: Solar PV (residential) | G29: 0.0041666667 | H29: 0.19565507 | I29: 0.005 | J29: 1845.8277 | K29: 1873.3105 | L29: 1909.339 | M29: 1935.9204
F30: Solar PV (residential) | G30: 0.005 | H30: 0.1716 | I30: 0.005 | J30: 1368.2946 | K30: 1388.6673 | L30: 1415.3749 | M30: 1435.0794
F31: Solar PV (utility scale) | G31: 0.83333333 | H31: 0.1962 | I31: 0.005 | J31: 827.20914 | K31: 839.52558 | L31: 855.67178 | M31: 867.58426
F32: Solar PV (utility scale) | G32: 0.83333333 | H32: 0.26526704 | I32: 0.005 | J32: 836.20041 | K32: 848.65073 | L32: 864.97243 | M32: 877.01439
D33: APJ | E33: Japan | F33: Solar PV (residential) | G33: 0.004 | H33: 0.12 | I33: 0.005 | J33: 2332.7402 | K33: 2367.4727 | L33: 2413.0052 | M33: 2446.5985
F34: Solar PV (utility scale) | G34: 2 | H34: 0.14 | I34: 0.005 | J34: 2006.1223 | K34: 2035.9917 | L34: 2075.149 | M34: 2104.0388
D35: APJ | E35: Korea | F35: Solar PV (commercial) | G35: 0.099 | H35: 0.15 | I35: 0.005 | J35: 1240.0949 | K35: 1258.5589 | L35: 1282.7641 | M35: 1300.6225
F36: Solar PV (utility scale) | G36: 2.97 | H36: 0.15 | I36: 0.005 | J36: 1225.7909 | K36: 1244.0419 | L36: 1267.9679 | M36: 1285.6203
D37: Europe | E37: Netherlands
F38: Solar PV (commercial) | G38: 0.2 | H38: 0.1375 | I38: 0.005 | J38: 845.88862 | K38: 858.48319 | L38: 874.994 | M38: 887.17547
F39: Solar PV (utility scale) | G39: 8 | H39: 0.14125 | I39: 0.005 | J39: 807.37878 | K39: 819.39997 | L39: 835.15911 | M39: 846.78601
D40: Europe | E40: Norway | F40: Solar PV (commercial) | G40: 0.3 | H40: 0.10273973 | I40: 0.005 | J40: 983.70735 | K40: 998.35392 | L40: 1017.5548 | M40: 1031.721
D41: NA | E41: United States | F41: Solar PV (residential) | G41: 0.005 | H41: 0.13501852 | I41: 0.005 | J41: 1884.4466 | K41: 1912.5044 | L41: 1949.2867 | M41: 1976.4243
F42: Solar PV (residential) | G42: 0.005 | H42: 0.15588898 | I42: 0.005 | J42: 1884.4466 | K42: 1912.5044 | L42: 1949.2867 | M42: 1976.4243
F43: Solar PV (residential)*** | G43: 0.005 | H43: 0.16683142 | I43: 0.005 | J43: 1884.4466 | K43: 1912.5044 | L43: 1949.2867 | M43: 1976.4243
F44: Solar PV (residential) | G44: 0.005 | H44: 0.18996493 | I44: 0.005 | J44: 2596.567 | K44: 2635.2277 | L44: 2685.9098 | M44: 2723.3024
F45: Solar PV (residential) | G45: 0.005 | H45: 0.20750952 | I45: 0.005 | J45: 2596.567 | K45: 2635.2277 | L45: 2685.9098 | M45: 2723.3024
F46: Solar PV (commercial) | G46: 0.3 | H46: 0.13030126 | I46: 0.005 | J46: 1356.6701 | K46: 1376.8697 | L46: 1403.3504 | M46: 1422.8876
F47: Solar PV (commercial) | G47: 0.3 | H47: 0.15104592 | I47: 0.005 | J47: 1356.6701 | K47: 1376.8697 | L47: 1403.3504 | M47: 1422.8876
F48: Solar PV (commercial)*** | G48: 0.3 | H48: 0.16111108 | I48: 0.005 | J48: 1356.6701 | K48: 1376.8697 | L48: 1403.3504 | M48: 1422.8876
F49: Solar PV (commercial) | G49: 0.3 | H49: 0.18827188 | I49: 0.005 | J49: 1356.6701 | K49: 1376.8697 | L49: 1403.3504 | M49: 1422.8876
F50: Solar PV (commercial) | G50: 0.3 | H50: 0.20376224 | I50: 0.005 | J50: 1356.6701 | K50: 1376.8697 | L50: 1403.3504 | M50: 1422.8876
F51: Solar PV (utility scale) | G51: 100 | H51: 0.22883089 | I51: 0.005 | J51: 1071.6806 | K51: 1087.637 | L51: 1108.555 | M51: 1123.9881
F52: Solar PV (utility scale) | G52: 100 | H52: 0.26368685 | I52: 0.005 | J52: 1071.6806 | K52: 1087.637 | L52: 1108.555 | M52: 1123.9881
F53: Solar PV (utility scale)*** | G53: 100 | H53: 0.28422415 | I53: 0.005 | J53: 1071.6806 | K53: 1087.637 | L53: 1108.555 | M53: 1123.9881
... F55: Solar PV (utility scale) | G55: 100 | H55: 0.3635842 | I55: 0.005 | J55: 1071.6806 | K55: 1087.637 | L55: 1108.555 | M55: 1123.9881
E59: Non-OECD countries
D60: CSA | E60: Brazil | F60: Solar PV (utility scale) | G60: 25 | H60: 0.3125 | I60: 0.005 | J60: 1197.3754 | K60: 1215.2033 | L60: 1238.5747 | M60: 1255.8179
D61: APJ | E61: China | F61: Solar PV (utility scale) | G61: 20 | H61: 0.1761 | I61: 0.005 | J61: 730.42 | K61: 741.29534 | L61: 755.55232 | M61: 766.07096
E62: India | F62: Solar PV (utility scale) | G62: 35 | H62: 0.2031 | I62: 0.005 | J62: 628.67482 | K62: 638.03526 | L62: 650.30629 | M62: 659.35972
E63: * All values represent AC capacity.
E64: ** A generic sizing factor of 1.2 was used to convert peak DC capacity into peak AC capacity.
E65: *** Indicated as reference datasets by the providing country.
D68: APJ-Large PV | G68: =AVERAGE(G7,G34,G36,G61:G62) -> 31.994 | H68: =AVERAGE(H7,H34,H36,H61:H62) -> 0.18984 | I68: =AVERAGE(I7,I34,I36,I61:I62) -> 0.005 | J68: =AVERAGE(J7,J34,J36,J61:J62) -> 1094.6047 | K68: =AVERAGE(K7,K34,K36,K61:K62) -> 1110.9024 | L68: =AVERAGE(L7,L34,L36,L61:L62) -> 1132.2679 | M68: =AVERAGE(M7,M34,M36,M61:M62) -> 1148.0311
D69: APJ-Rooftop PV | G69: =AVERAGE(G33,G35) -> 0.0515 | H69: =AVERAGE(H33,H35) -> 0.135 | I69: =AVERAGE(I33,I35) -> 0.005 | J69: =AVERAGE(J33,J35) -> 1786.4175 | K69: =AVERAGE(K33,K35) -> 1813.0158 | L69: =AVERAGE(L33,L35) -> 1847.8847 | M69: =AVERAGE(M33,M35) -> 1873.6105
D70: Europe-Large PV | G70: =AVERAGE(G17:G18,G21,G25,G31:G32,G39) -> 10.095238 | H70: =AVERAGE(H17:H18,H21,H25,H31:H32,H39) -> 0.18831414 | I70: =AVERAGE(I17:I18,I21,I25,I31:I32,I39) -> 0.005 | J70: =AVERAGE(J17:J18,J21,J25,J31:J32,J39) -> 757.19106 | K70: =AVERAGE(K17:K18,K21,K25,K31:K32,K39) -> 768.46499 | L70: =AVERAGE(L17:L18,L21,L25,L31:L32,L39) -> 783.24452 | M70: =AVERAGE(M17:M18,M21,M25,M31:M32,M39) -> 794.14868
D71: Europe-Rooftop PV | G71: =AVERAGE(G6,G9:G11,G15:G16,G19:G20,G22:G24,G26:G30,G38,G40) -> 0.13542593 | H71: =AVERAGE(H6,H9:H11,H15:H16,H19:H20,H22:H24,H26:H30,H38,H40) -> 0.14958918 | I71: =AVERAGE(I6,I9:I11,I15:I16,I19:I20,I22:I24,I26:I30,I38,I40) -> 0.005 | J71: =AVERAGE(J6,J9:J11,J15:J16,J19:J20,J22:J24,J26:J30,J38,J40) -> 1234.7515 | K71: =AVERAGE(K6,K9:K11,K15:K16,K19:K20,K22:K24,K26:K30,K38,K40) -> 1253.1359 | L71: =AVERAGE(L6,L9:L11,L15:L16,L19:L20,L22:L24,L26:L30,L38,L40) -> 1277.2368 | M71: =AVERAGE(M6,M9:M11,M15:M16,M19:M20,M22:M24,M26:M30,M38,M40) -> 1295.0183
D72: NA-large PV | G72: =AVERAGE(G13:G14,G51:G55) -> 77.142857 | H72: =AVERAGE(H13:H14,H51:H55) -> 0.27296203 | I72: =AVERAGE(I13:I14,I51:I55) -> 0.005 | J72: =AVERAGE(J13:J14,J51:J55) -> 1139.5648 | K72: =AVERAGE(K13:K14,K51:K55) -> 1156.5319 | L72: =AVERAGE(L13:L14,L51:L55) -> 1178.775 | M72: =AVERAGE(M13:M14,M51:M55) -> 1195.1856
D73: NA-Rooftop PV | G73: =AVERAGE(G41:G50) -> 0.1525 | H73: =AVERAGE(H41:H50) -> 0.16897058 | I73: =AVERAGE(I41:I50) -> 0.005 | J73: =AVERAGE(J41:J50) -> 1762.9824 | K73: =AVERAGE(K41:K50) -> 1789.2317 | L73: =AVERAGE(L41:L50) -> 1823.6432 | M73: =AVERAGE(M41:M50) -> 1849.0316
D74: CSA-Large PV | G74: =G60 -> 25 | H74: =H60 -> 0.3125 | I74: =I60 -> 0.005 | J74: =J60 -> 1197.3754 | K74: =K60 -> 1215.2033 | L74: =L60 -> 1238.5747 | M74: =M60 -> 1255.8179

Sheet Attached-DIB_GNESTE_Solar_Power
A1: Source: The Global and National Energy Systems Techno-Economic (GNESTE) Database: Solar Power | C1: Technology | D1: ID | E1: Continent | F1: Country | G1: ISO2 | H1: ISO3 | I1: Variable | J1: Code | K1: Unit | L1: Category | M1: Source | N1: Notes | O1: Currency | P1: Energy/Power Ratio | Q1: 2014 | R1: 2015 | S1: 2016 | T1: 2017 | U1: 2018 | V1: 2019 | W1: 2020 | X1: 2021 | Y1: 2022 | Z1: 2023 | AA1: 2024 | AB1: 2025 | AC1: 2030 | AD1: 2040 | AE1: 2050
C3: Solar | D3: S0002 | E3: Asia | F3: Indonesia | G3: ID | H3: IDN | I3: Capital Cost | J3: CAPEX | K3: USD/kW | L3: Unspecified | M3: ASEAN Centre for Energy, 2019 | N3: Highest out of 2 data points for large-scale solar PV | O3: From 2019 USD to 2023 USD = 1.12020 | V3: 2492.445
C4: Solar | D4: S0003 | E4: Asia | F4: Indonesia | G4: ID | H4: IDN | I4: Capital Cost | J4: CAPEX | K4: USD/kW | L4: Unspecified | M4: ASEAN Centre for Energy, 2019 | N4: Lowest out of 2 data points for large-scale solar PV | O4: From 2019 USD to 2023 USD = 1.12020 | V4: 2016.36
C5: Solar | D5: S0004 | E5: Asia | F5: Malaysia | G5: MY | H5: MYS | I5: Capital Cost | J5: CAPEX | K5: USD/kW | L5: Unspecified | M5: ASEAN Centre for Energy, 2019 | N5: Highest out of 6 data points for large-scale solar PV | O5: From 2019 USD to 2023 USD = 1.12020 | V5: 1635.492
C6: Solar | D6: S0005 | E6: Asia | F6: Malaysia | G6: MY | H6: MYS | I6: Capital Cost | J6: CAPEX | K6: USD/kW | L6: Unspecified | M6: ASEAN Centre for Energy, 2019 | N6: Lowest out of 6 data points for large-scale solar PV | O6: From 2019 USD to 2023 USD = 1.12020 | V6: 2890.116
C7: Solar | D7: S0006 | E7: Asia | F7: Philippines | G7: PH | H7: PHL | I7: Capital Cost | J7: CAPEX | K7: USD/kW | L7: Unspecified | M7: ASEAN Centre for Energy, 2019 | N7: Highest out of 4 data points for large-scale solar PV | O7: From 2019 USD to 2023 USD = 1.12020 | V7: 2643.672
C8: Solar | D8: S0007 | E8: Asia | F8: Philippines | G8: PH | H8: PHL | I8: Capital Cost | J8: CAPEX | K8: USD/kW | L8: Unspecified | M8: ASEAN Centre for Energy, 2019 | N8: Lowest out of 4 data points for large-scale solar PV | O8: From 2019 USD to 2023 USD = 1.12020 | V8: 1814.724
C9: Solar | D9: S0008 | E9: Asia | F9: Thailand | G9: TH | H9: THA | I9: Capital Cost | J9: CAPEX | K9: USD/kW | L9: Unspecified | M9: ASEAN Centre for Energy, 2019 | N9: Highest out of 2 data points for large-scale solar PV | O9: From 2019 USD to 2023 USD = 1.12020 | V9: 2094.774
C10: Solar | D10: S0009 | E10: Asia | F10: Thailand | G10: TH | H10: THA | I10: Capital Cost | J10: CAPEX | K10: USD/kW | L10: Unspecified | M10: ASEAN Centre for Energy, 2019 | N10: Lowest out of 2 data points for large-scale solar PV | O10: From 2019 USD to 2023 USD = 1.12020 | V10: 2419.632
C11: Solar | D11: S0010 | E11: Asia | I11: Capital Cost | J11: CAPEX | K11: USD/kW | L11: Unspecified | M11: ASEAN Centre for Energy, 2019 | N11: Capacity-weighted average for large-scale solar PV | O11: From 2019 USD to 2023 USD = 1.12020 | V11: 2254.9626
M12: ASEAN Centre for Energy, 2019 | N12: Nominal WACC for utility scale. Real WACC is 2.1%
C15: Solar | D15: S0014 | E15: North America | F15: United States of America | G15: US | H15: USA | I15: Capital Cost | J15: CAPEX | K15: USD/kW | L15: Single Axis Tracking | M15: EIA, 2020 | O15: From 2019 USD to 2023 USD = 1.12020 | V15: 1470.8226
C17: Solar | D17: S0016 | E17: North America | F17: United States of America | G17: US | H17: USA | I17: Capital Cost | J17: CAPEX | K17: USD/kW | L17: Single Axis Tracking | M17: EIA, 2024 | O17: In 2023 USD | Z17: 1502
C19: Solar | D19: S0018 | E19: Oceania | F19: Australia | G19: AU | H19: AUS | I19: Capital Cost | J19: CAPEX | K19: USD/kW | L19: Unspecified | M19: CSIRO, 2023 | N19: Under the Current Policies scenario | O19: From 2023 AUD to 2023 USD = 0.65730 | Y19: 1033.2756 | Z19: 996.4668 | AA19: 924.8211 | AB19: 855.1473 | AC19: 695.4234 | AD19: 551.4747 | AE19: 444.3348
C20: Solar | D20: S0019 | E20: Oceania | F20: Australia | G20: AU | H20: AUS | I20: Capital Cost | J20: CAPEX | K20: USD/kW | L20: Unspecified | M20: CSIRO, 2023 | N20: Under the Global NZE by 2050 scenario | O20: From 2023 AUD to 2023 USD = 0.65730 | Y20: 1033.2756 | Z20: 996.4668 | AA20: 935.9952 | AB20: 886.0404 | AC20: 703.9683 | AD20: 429.2169 | AE20: 337.1949
C21: Solar | D21: S0020 | E21: Oceania | F21: Australia | G21: AU | H21: AUS | I21: Capital Cost | J21: CAPEX | K21: USD/kW | L21: Unspecified | M21: CSIRO, 2023 | N21: Under the Global NZE post 2050 scenario | O21: From 2023 AUD to 2023 USD = 0.65730 | Y21: 1033.2756 | Z21: 996.4668 | AA21: 935.9952 | AB21: 886.0404 | AC21: 703.9683 | AD21: 451.5651 | AE21: 385.1778
C25: Solar | D25: S0024 | E25: Asia | F25: India | G25: IN | H25: IND | I25: Capital Cost | J25: CAPEX | K25: USD/kW | L25: Unspecified | M25: Danish Energy Agency, 2022 | N25: Large scale utility systems | O25: From 2020 IRP to 2023 USD = 0.0148565 | W25: 609.1165 | AC25: 430.8385 | AD25: 297.13 | AE25: 252.5605
C26: Solar | D26: S0025 | E26: Africa | F26: South Africa | G26: ZA | H26: ZAF | I26: Capital Cost | J26: CAPEX | K26: USD/kW | L26: Single Axis Tracking | M26: DMRE, 2019 | O26: From 2017 USD to 2023 USD = 1.16892 | T26: 1263.9549 | W26: 894.92417 | AB26: 840.0544
M31: Dobrotkova, 2018
M32: Dobrotkova, 2018
M33: Dobrotkova, 2018
M34: Dobrotkova, 2018
M35: Dobrotkova, 2018
M36: Dobrotkova, 2018
M37: Dobrotkova, 2018
M38: Dobrotkova, 2018
M39: Dobrotkova, 2018
M40: Dobrotkova, 2018
M41: Dobrotkova, 2018
M42: Dobrotkova, 2018
... M65: Steffen, 2020
C66: Solar | D66: S0065 | E66: Europe | F66: Netherlands | G66: NL | H66: NLD | I66: Capital Cost | J66: CAPEX | K66: USD/kW | L66: Unspecified | M66: ECN, 2019 | N66: Min value | O66: From 2015 USD to 2023 USD = 1.19245 | V66: 756.0133
C67: Solar | D67: S0066 | E67: Europe | F67: Netherlands | G67: NL | H67: NLD | I67: Capital Cost | J67: CAPEX | K67: USD/kW | L67: Unspecified | M67: ECN, 2019 | N67: Average value | O67: From 2015 USD to 2023 USD = 1.19245 | V67: 787.017
C68: Solar | D68: S0067 | E68: Europe | F68: Netherlands | G68: NL | H68: NLD | I68: Capital Cost | J68: CAPEX | K68: USD/kW | L68: Unspecified | M68: ECN, 2019 | N68: Max value | O68: From 2015 USD to 2023 USD = 1.19245 | V68: 819.21315
C70: Solar | D70: S0069 | E70: Europe | F70: European Union | I70: Capital Cost | J70: CAPEX | K70: USD/kW | L70: Unspecified | M70: ASSET, 2018 | N70: Projection 2018 Medium Potential Solar PV | O70: From 2018 EUR to 2023 USD = 1.21197 | W70: 860.4987
C72: Solar | D72: S0071 | E72: Europe | F72: European Union | I72: Capital Cost | J72: CAPEX | K72: USD/kW | L72: Unspecified | M72: ASSET, 2018 | N72: Projection 2018 High Potential Solar PV | O72: From 2018 EUR to 2023 USD = 1.21197 | W72: 848.379
C74: Solar | D74: S0073 | E74: Europe | F74: European Union | I74: Capital Cost | J74: CAPEX | K74: USD/kW | L74: Unspecified | M74: ASSET, 2018 | N74: Projection 2018 low potential solar PV | O74: From 2018 EUR to 2023 USD = 1.21197 | W74: 873.83037
C76: Solar | D76: S0075 | E76: Global | F76: Global | I76: Capital Cost | J76: CAPEX | K76: USD/kW | L76: Single Axis Tracking | M76: JRC, 2017 | N76: Min value | O76: From 2015 EUR to 2023 USD = 1.25458 | R76: 1405.1296 | W76: 890.7518
C77: Solar | D77: S0076 | E77: Global | F77: Global | I77: Capital Cost | J77: CAPEX | K77: USD/kW | L77: Single Axis Tracking | M77: JRC, 2017 | N77: Baseline value | O77: From 2015 EUR to 2023 USD = 1.25458 | R77: 1405.1296 | W77: 1141.6678
C78: Solar | D78: S0077 | E78: Global | F78: Global | I78: Capital Cost | J78: CAPEX | K78: USD/kW | L78: Single Axis Tracking | M78: JRC, 2017 | N78: Max value | O78: From 2015 EUR to 2023 USD = 1.25458 | R78: 1405.1296 | W78: 1267.1258
C82: Solar | D82: S0081 | E82: Global | F82: Global | I82: Capital Cost | J82: CAPEX | K82: USD/kW | L82: Fixed Axis | M82: JRC, 2017 | N82: Min value | O82: From 2015 EUR to 2023 USD = 1.25458 | R82: 1279.6716 | W82: 815.477
C83: Solar | D83: S0082 | E83: Global | F83: Global | I83: Capital Cost | J83: CAPEX | K83: USD/kW | L83: Fixed Axis | M83: JRC, 2017 | N83: Baseline value | O83: From 2015 EUR to 2023 USD = 1.25458 | R83: 1279.6716 | W83: 1041.3014
